Workbook

Sheet README
A1: Lead Scoring Phase 0 Workbook (DUMMY DATA)
A3: All leads, names, emails and companies in this file are synthetic. Built to rehearse the Phase 0 audit before real data is available.
A5: Tabs
A6: Leads | 800 synthetic leads, Oct 2025 to Sep 2026, with rule-based spam flags calculated by formula (columns R to X).
A7: Audit | Phase 0 baselines. Volume, spam share, logging gaps, qualification rates, response times. All formulas.
A8: Spam Rules | Draft v0 spam rules with hits, precision and recall against tagged leads. Edit keywords or threshold to test.
A9: Label Sample | 150 leads for manual labeling practice. Pick a label from the dropdown in column H.
A10: Answer Key | The hidden true label for each sample lead, to check manual labeling accuracy.
A12: Status values
A13: Spam, Unqualified, Open (in progress), Qualified (opportunity), Won, Lost (qualified then lost). Blank = never tagged.
A14: Qualified+ = Qualified + Won + Lost, i.e. the lead reached qualified opportunity (the proposed primary label).
A16: Legend
... A20: Conversion Model | Phase 3 learned weights, live probability in Leads column AG, test results and calibration check.

Sheet Leads
A1: Lead ID | B1: Created At | C1: Source | D1: Name | E1: Email | F1: Email Type | G1: Company | H1: Website | I1: Country | J1: Product Interest | K1: Form Message | L1: Pages Visited | M1: First Response (hrs) | N1: Owner | O1: Status | P1: Deal Value (USD) | Q1: Flag: Disposable Email | R1: Flag: Vendor/Scam Keyword | S1: Flag: Free Email + No Company | T1: Flag: Very Short Message | U1: Flag: Duplicate Email | V1: Rule Score | W1: Rule Verdict | X1: Pts: Source | Y1: Pts: Email Type | Z1: Pts: Product | AA1: Pts: Engagement | AB1: Pts: Buying Intent | AC1: Pts: Negative Intent | AD1: Lead Score | AE1: Bucket | AF1: Top Reasons | AG1: Conversion Probability | AH1: Resolved Outcome (1 = Qualified+, 0 = Unqualified)
A2: L-0001 | B2: 45931.656 | C2: Website Contact Form | D2: Mateo Ivanova | E2: mateo.ivanova@freemail.example | F2: Free | G2: Quillmoor Money | I2: UAE | J2: Payments - Virtual Accounts | K2: We raised a seed round and plan to launch a digital savings platform for SMEs. Want to discuss infrastructure. | L2: 3 | M2: 26 | N2: Vikram | Q2: =IF(F2="Disposable",1,0) -> 0 | R2: =IF(SUMPRODUCT(--ISNUMBER(SEARCH('Spam Rules'!$A$22:$A$35,K2)))>0,1,0) -> 0 | S2: =IF(AND(F2="Free",G2=""),1,0) -> 0 | T2: =IF(LEN(TRIM(K2))<15,1,0) -> 0 | U2: =IF(COUNTIF($E$2:$E$801,E2)>1,1,0) -> 0 | V2: =Q2*'Spam Rules'!$H$6+R2*'Spam Rules'!$H$7+S2*'Spam Rules'!$H$8+T2*'Spam Rules'!$H$9+U2*'Spam Rules'!$H$10 -> 0 | W2: =IF(V2>='Spam Rules'!$B$3,"Likely Spam","Genuine") -> Genuine | X2: =IFERROR(INDEX('Scoring Model'!$B$5:$B$11,MATCH(C2,'Scoring Model'!$A$5:$A$11,0)),0) -> 10 | Y2: =IFERROR(INDEX('Scoring Model'!$E$5:$E$7,MATCH(F2,'Scoring Model'!$D$5:$D$7,0)),0) -> 0 | Z2: =IFERROR(INDEX('Scoring Model'!$H$5:$H$13,MATCH(J2,'Scoring Model'!$G$5:$G$13,0)),0) -> 15 | AA2: =IF(L2>='Scoring Model'!$B$14,'Scoring Model'!$B$15,IF(L2>='Scoring Model'!$B$16,'Scoring Model'!$B$17,0)) -> 0 | AB2: =IF(SUMPRODUCT(--ISNUMBER(SEARCH('Scoring Model'!$D$16:$D$25,K2)))>0,'Scoring Model'!$B$18,0) -> 15 | AC2: =IF(SUMPRODUCT(--ISNUMBER(SEARCH('Scoring Model'!$G$16:$G$23,K2)))>0,'Scoring Model'!$B$19,0) -> 0 | AD2: =IF(W2="Likely Spam","",SUM(X2:AC2)) -> 40 | AE2: =IF(W2="Likely Spam","Spam",IF(AD2>='Scoring Model'!$B$21,"Hot",IF(AD2>='Scoring Model'!$B$22,"Warm","Nurture"))) -> Nurture | AF2: =IF(W2="Likely Spam","Flagged by spam rules",TRIM(IF(X2>=20,"Strong source. ","")&IF(Y2>0,"Company email. ","")&IF(Z2>=15,"High-value product. ","")&IF(AA2>='Scoring Model'!$B$15,"High engagement. ","")&IF(AB2>0,"Buying intent in message. ","")&IF(AC2<0,"Negative intent in message. ",""))) -> High-value product. Buying intent in message. | AG2: =IF(W2="Likely Spam","",1/(1+EXP(-('Conversion Model'!$B$5+IFERROR(INDEX('Conversion Model'!$B$8:$B$14,MATCH(C2,'Conversion Model'!$A$8:$A$14,0)),0)+IFERROR(INDEX('Conversion Model'!$E$8:$E$9,MATCH(F2,'Conversion Model'!$D$8:$D$9,0)),0)+IFERROR(INDEX('Conversion Model'!$H$8:$H$12,MATCH(IF(LEFT(J2,8)="Payments","Payments",IF(LEFT(J2,7)="Lending","Lending",J2)),'Conversion Model'!$G$8:$G$12,0)),0)+MIN(L2,15)*'Conversion Model'!$B$17+IF(SUMPRODUCT(--ISNUMBER(SEARCH('Scoring Model'!$D$16:$D$25,K2)))>0,'Conversion Model'!$B$18,0)+IF(SUMPRODUCT(--ISNUMBER(SEARCH('Scoring Model'!$G$16:$G$23,K2)))>0,'Conversion Model'!$B$19,0))))) -> 0.15446527 | AH2: =IF(OR(O2="Qualified",O2="Won",O2="Lost"),1,IF(O2="Unqualified",0,""))
A3: L-0002 | B3: 45931.767 | C3: Website Contact Form | D3: Elena Berg | E3: elena60@vanishmail.example | F3: Disposable | I3: UK | J3: Other | K3: Boost your Twitter followers and Telegram members, organic fintech marketing. | L3: 1 | N3: Unassigned | O3: Spam | Q3: =IF(F3="Disposable",1,0) -> 1 | R3: =IF(SUMPRODUCT(--ISNUMBER(SEARCH('Spam Rules'!$A$22:$A$35,K3)))>0,1,0) -> 1 | S3: =IF(AND(F3="Free",G3=""),1,0) -> 0 | T3: =IF(LEN(TRIM(K3))<15,1,0) -> 0 | U3: =IF(COUNTIF($E$2:$E$801,E3)>1,1,0) -> 1 | V3: =Q3*'Spam Rules'!$H$6+R3*'Spam Rules'!$H$7+S3*'Spam Rules'!$H$8+T3*'Spam Rules'!$H$9+U3*'Spam Rules'!$H$10 -> 2 | W3: =IF(V3>='Spam Rules'!$B$3,"Likely Spam","Genuine") -> Likely Spam | X3: =IFERROR(INDEX('Scoring Model'!$B$5:$B$11,MATCH(C3,'Scoring Model'!$A$5:$A$11,0)),0) -> 10 | Y3: =IFERROR(INDEX('Scoring Model'!$E$5:$E$7,MATCH(F3,'Scoring Model'!$D$5:$D$7,0)),0) -> 0 | Z3: =IFERROR(INDEX('Scoring Model'!$H$5:$H$13,MATCH(J3,'Scoring Model'!$G$5:$G$13,0)),0) -> 0 | AA3: =IF(L3>='Scoring Model'!$B$14,'Scoring Model'!$B$15,IF(L3>='Scoring Model'!$B$16,'Scoring Model'!$B$17,0)) -> 0 | AB3: =IF(SUMPRODUCT(--ISNUMBER(SEARCH('Scoring Model'!$D$16:$D$25,K3)))>0,'Scoring Model'!$B$18,0) -> 0 | AC3: =IF(SUMPRODUCT(--ISNUMBER(SEARCH('Scoring Model'!$G$16:$G$23,K3)))>0,'Scoring Model'!$B$19,0) -> 0 | AD3: =IF(W3="Likely Spam","",SUM(X3:AC3)) | AE3: =IF(W3="Likely Spam","Spam",IF(AD3>='Scoring Model'!$B$21,"Hot",IF(AD3>='Scoring Model'!$B$22,"Warm","Nurture"))) -> Spam | AF3: =IF(W3="Likely Spam","Flagged by spam rules",TRIM(IF(X3>=20,"Strong source. ","")&IF(Y3>0,"Company email. ","")&IF(Z3>=15,"High-value product. ","")&IF(AA3>='Scoring Model'!$B$15,"High engagement. ","")&IF(AB3>0,"Buying intent in message. ","")&IF(AC3<0,"Negative intent in message. ",""))) -> Flagged by spam rules | AG3: =IF(W3="Likely Spam","",1/(1+EXP(-('Conversion Model'!$B$5+IFERROR(INDEX('Conversion Model'!$B$8:$B$14,MATCH(C3,'Conversion Model'!$A$8:$A$14,0)),0)+IFERROR(INDEX('Conversion Model'!$E$8:$E$9,MATCH(F3,'Conversion Model'!$D$8:$D$9,0)),0)+IFERROR(INDEX('Conversion Model'!$H$8:$H$12,MATCH(IF(LEFT(J3,8)="Payments","Payments",IF(LEFT(J3,7)="Lending","Lending",J3)),'Conversion Model'!$G$8:$G$12,0)),0)+MIN(L3,15)*'Conversion Model'!$B$17+IF(SUMPRODUCT(--ISNUMBER(SEARCH('Scoring Model'!$D$16:$D$25,K3)))>0,'Conversion Model'!$B$18,0)+IF(SUMPRODUCT(--ISNUMBER(SEARCH('Scoring Model'!$G$16:$G$23,K3)))>0,'Conversion Model'!$B$19,0))))) | AH3: =IF(OR(O3="Qualified",O3="Won",O3="Lost"),1,IF(O3="Unqualified",0,""))
A4: L-0003 | B4: 45931.926 | C4: Website Contact Form | D4: Daniel Brown | E4: daniel.brown@webmail.example | F4: Free | G4: Plumeridge Money | I4: Switzerland | J4: Other | K4: I am a student researching open banking for my thesis. Can you share some material? | L4: 2 | M4: 1.5 | N4: Vikram | Q4: =IF(F4="Disposable",1,0) -> 0 | R4: =IF(SUMPRODUCT(--ISNUMBER(SEARCH('Spam Rules'!$A$22:$A$35,K4)))>0,1,0) -> 0 | S4: =IF(AND(F4="Free",G4=""),1,0) -> 0 | T4: =IF(LEN(TRIM(K4))<15,1,0) -> 0 | U4: =IF(COUNTIF($E$2:$E$801,E4)>1,1,0) -> 0 | V4: =Q4*'Spam Rules'!$H$6+R4*'Spam Rules'!$H$7+S4*'Spam Rules'!$H$8+T4*'Spam Rules'!$H$9+U4*'Spam Rules'!$H$10 -> 0 | W4: =IF(V4>='Spam Rules'!$B$3,"Likely Spam","Genuine") -> Genuine | X4: =IFERROR(INDEX('Scoring Model'!$B$5:$B$11,MATCH(C4,'Scoring Model'!$A$5:$A$11,0)),0) -> 10 | Y4: =IFERROR(INDEX('Scoring Model'!$E$5:$E$7,MATCH(F4,'Scoring Model'!$D$5:$D$7,0)),0) -> 0 | Z4: =IFERROR(INDEX('Scoring Model'!$H$5:$H$13,MATCH(J4,'Scoring Model'!$G$5:$G$13,0)),0) -> 0 | AA4: =IF(L4>='Scoring Model'!$B$14,'Scoring Model'!$B$15,IF(L4>='Scoring Model'!$B$16,'Scoring Model'!$B$17,0)) -> 0 | AB4: =IF(SUMPRODUCT(--ISNUMBER(SEARCH('Scoring Model'!$D$16:$D$25,K4)))>0,'Scoring Model'!$B$18,0) -> 0 | AC4: =IF(SUMPRODUCT(--ISNUMBER(SEARCH('Scoring Model'!$G$16:$G$23,K4)))>0,'Scoring Model'!$B$19,0) -> -30 | AD4: =IF(W4="Likely Spam","",SUM(X4:AC4)) -> -20 | AE4: =IF(W4="Likely Spam","Spam",IF(AD4>='Scoring Model'!$B$21,"Hot",IF(AD4>='Scoring Model'!$B$22,"Warm","Nurture"))) -> Nurture | AF4: =IF(W4="Likely Spam","Flagged by spam rules",TRIM(IF(X4>=20,"Strong source. ","")&IF(Y4>0,"Company email. ","")&IF(Z4>=15,"High-value product. ","")&IF(AA4>='Scoring Model'!$B$15,"High engagement. ","")&IF(AB4>0,"Buying intent in message. ","")&IF(AC4<0,"Negative intent in message. ",""))) -> Negative intent in message. | AG4: =IF(W4="Likely Spam","",1/(1+EXP(-('Conversion Model'!$B$5+IFERROR(INDEX('Conversion Model'!$B$8:$B$14,MATCH(C4,'Conversion Model'!$A$8:$A$14,0)),0)+IFERROR(INDEX('Conversion Model'!$E$8:$E$9,MATCH(F4,'Conversion Model'!$D$8:$D$9,0)),0)+IFERROR(INDEX('Conversion Model'!$H$8:$H$12,MATCH(IF(LEFT(J4,8)="Payments","Payments",IF(LEFT(J4,7)="Lending","Lending",J4)),'Conversion Model'!$G$8:$G$12,0)),0)+MIN(L4,15)*'Conversion Model'!$B$17+IF(SUMPRODUCT(--ISNUMBER(SEARCH('Scoring Model'!$D$16:$D$25,K4)))>0,'Conversion Model'!$B$18,0)+IF(SUMPRODUCT(--ISNUMBER(SEARCH('Scoring Model'!$G$16:$G$23,K4)))>0,'Conversion Model'!$B$19,0))))) -> 0.00206615 | AH4: =IF(OR(O4="Qualified",O4="Won",O4="Lost"),1,IF(O4="Unqualified",0,""))
A5: L-0004 | B5: 45934.185 | C5: Chat Widget | D5: Daniel Costa | E5: daniel257@inboxly.example | F5: Free | G5: Listpeak Directory | I5: Singapore | J5: KYC Verification | K5: Get your app listing on top review sites in 48 hours, guaranteed. Contact our listing agent. | L5: 1 | M5: 10.7 | N5: Unassigned | Q5: =IF(F5="Disposable",1,0) -> 0 | R5: =IF(SUMPRODUCT(--ISNUMBER(SEARCH('Spam Rules'!$A$22:$A$35,K5)))>0,1,0) -> 1 | S5: =IF(AND(F5="Free",G5=""),1,0) -> 0 | T5: =IF(LEN(TRIM(K5))<15,1,0) -> 0 | U5: =IF(COUNTIF($E$2:$E$801,E5)>1,1,0) -> 0 | V5: =Q5*'Spam Rules'!$H$6+R5*'Spam Rules'!$H$7+S5*'Spam Rules'!$H$8+T5*'Spam Rules'!$H$9+U5*'Spam Rules'!$H$10 -> 1 | W5: =IF(V5>='Spam Rules'!$B$3,"Likely Spam","Genuine") -> Likely Spam | X5: =IFERROR(INDEX('Scoring Model'!$B$5:$B$11,MATCH(C5,'Scoring Model'!$A$5:$A$11,0)),0) -> 0 | Y5: =IFERROR(INDEX('Scoring Model'!$E$5:$E$7,MATCH(F5,'Scoring Model'!$D$5:$D$7,0)),0) -> 0 | Z5: =IFERROR(INDEX('Scoring Model'!$H$5:$H$13,MATCH(J5,'Scoring Model'!$G$5:$G$13,0)),0) -> 5 | AA5: =IF(L5>='Scoring Model'!$B$14,'Scoring Model'!$B$15,IF(L5>='Scoring Model'!$B$16,'Scoring Model'!$B$17,0)) -> 0 | AB5: =IF(SUMPRODUCT(--ISNUMBER(SEARCH('Scoring Model'!$D$16:$D$25,K5)))>0,'Scoring Model'!$B$18,0) -> 0 | AC5: =IF(SUMPRODUCT(--ISNUMBER(SEARCH('Scoring Model'!$G$16:$G$23,K5)))>0,'Scoring Model'!$B$19,0) -> 0 | AD5: =IF(W5="Likely Spam","",SUM(X5:AC5)) | AE5: =IF(W5="Likely Spam","Spam",IF(AD5>='Scoring Model'!$B$21,"Hot",IF(AD5>='Scoring Model'!$B$22,"Warm","Nurture"))) -> Spam | AF5: =IF(W5="Likely Spam","Flagged by spam rules",TRIM(IF(X5>=20,"Strong source. ","")&IF(Y5>0,"Company email. ","")&IF(Z5>=15,"High-value product. ","")&IF(AA5>='Scoring Model'!$B$15,"High engagement. ","")&IF(AB5>0,"Buying intent in message. ","")&IF(AC5<0,"Negative intent in message. ",""))) -> Flagged by spam rules | AG5: =IF(W5="Likely Spam","",1/(1+EXP(-('Conversion Model'!$B$5+IFERROR(INDEX('Conversion Model'!$B$8:$B$14,MATCH(C5,'Conversion Model'!$A$8:$A$14,0)),0)+IFERROR(INDEX('Conversion Model'!$E$8:$E$9,MATCH(F5,'Conversion Model'!$D$8:$D$9,0)),0)+IFERROR(INDEX('Conversion Model'!$H$8:$H$12,MATCH(IF(LEFT(J5,8)="Payments","Payments",IF(LEFT(J5,7)="Lending","Lending",J5)),'Conversion Model'!$G$8:$G$12,0)),0)+MIN(L5,15)*'Conversion Model'!$B$17+IF(SUMPRODUCT(--ISNUMBER(SEARCH('Scoring Model'!$D$16:$D$25,K5)))>0,'Conversion Model'!$B$18,0)+IF(SUMPRODUCT(--ISNUMBER(SEARCH('Scoring Model'!$G$16:$G$23,K5)))>0,'Conversion Model'!$B$19,0))))) | AH5: =IF(OR(O5="Qualified",O5="Won",O5="Lost"),1,IF(O5="Unqualified",0,""))
A6: L-0005 | B6: 45934.661 | C6: Chat Widget | D6: Ethan Silva | E6: ethan460@codewhistleoutsourcing.example | F6: Company | G6: Codewhistle Outsourcing | H6: https://codewhistleoutsourcing.example | I6: India | J6: Other | K6: Claim your cashback reward now at the link below. | L6: 2 | M6: 24.1 | N6: Unassigned | O6: Spam | Q6: =IF(F6="Disposable",1,0) -> 0 | R6: =IF(SUMPRODUCT(--ISNUMBER(SEARCH('Spam Rules'!$A$22:$A$35,K6)))>0,1,0) -> 1 | S6: =IF(AND(F6="Free",G6=""),1,0) -> 0 | T6: =IF(LEN(TRIM(K6))<15,1,0) -> 0 | U6: =IF(COUNTIF($E$2:$E$801,E6)>1,1,0) -> 0 | V6: =Q6*'Spam Rules'!$H$6+R6*'Spam Rules'!$H$7+S6*'Spam Rules'!$H$8+T6*'Spam Rules'!$H$9+U6*'Spam Rules'!$H$10 -> 1 | W6: =IF(V6>='Spam Rules'!$B$3,"Likely Spam","Genuine") -> Likely Spam | X6: =IFERROR(INDEX('Scoring Model'!$B$5:$B$11,MATCH(C6,'Scoring Model'!$A$5:$A$11,0)),0) -> 0 | Y6: =IFERROR(INDEX('Scoring Model'!$E$5:$E$7,MATCH(F6,'Scoring Model'!$D$5:$D$7,0)),0) -> 20 | Z6: =IFERROR(INDEX('Scoring Model'!$H$5:$H$13,MATCH(J6,'Scoring Model'!$G$5:$G$13,0)),0) -> 0 | AA6: =IF(L6>='Scoring Model'!$B$14,'Scoring Model'!$B$15,IF(L6>='Scoring Model'!$B$16,'Scoring Model'!$B$17,0)) -> 0 | AB6: =IF(SUMPRODUCT(--ISNUMBER(SEARCH('Scoring Model'!$D$16:$D$25,K6)))>0,'Scoring Model'!$B$18,0) -> 0 | AC6: =IF(SUMPRODUCT(--ISNUMBER(SEARCH('Scoring Model'!$G$16:$G$23,K6)))>0,'Scoring Model'!$B$19,0) -> 0 | AD6: =IF(W6="Likely Spam","",SUM(X6:AC6)) | AE6: =IF(W6="Likely Spam","Spam",IF(AD6>='Scoring Model'!$B$21,"Hot",IF(AD6>='Scoring Model'!$B$22,"Warm","Nurture"))) -> Spam | AF6: =IF(W6="Likely Spam","Flagged by spam rules",TRIM(IF(X6>=20,"Strong source. ","")&IF(Y6>0,"Company email. ","")&IF(Z6>=15,"High-value product. ","")&IF(AA6>='Scoring Model'!$B$15,"High engagement. ","")&IF(AB6>0,"Buying intent in message. ","")&IF(AC6<0,"Negative intent in message. ",""))) -> Flagged by spam rules | AG6: =IF(W6="Likely Spam","",1/(1+EXP(-('Conversion Model'!$B$5+IFERROR(INDEX('Conversion Model'!$B$8:$B$14,MATCH(C6,'Conversion Model'!$A$8:$A$14,0)),0)+IFERROR(INDEX('Conversion Model'!$E$8:$E$9,MATCH(F6,'Conversion Model'!$D$8:$D$9,0)),0)+IFERROR(INDEX('Conversion Model'!$H$8:$H$12,MATCH(IF(LEFT(J6,8)="Payments","Payments",IF(LEFT(J6,7)="Lending","Lending",J6)),'Conversion Model'!$G$8:$G$12,0)),0)+MIN(L6,15)*'Conversion Model'!$B$17+IF(SUMPRODUCT(--ISNUMBER(SEARCH('Scoring Model'!$D$16:$D$25,K6)))>0,'Conversion Model'!$B$18,0)+IF(SUMPRODUCT(--ISNUMBER(SEARCH('Scoring Model'!$G$16:$G$23,K6)))>0,'Conversion Model'!$B$19,0))))) | AH6: =IF(OR(O6="Qualified",O6="Won",O6="Lost"),1,IF(O6="Unqualified",0,""))
A7: L-0006 | B7: 45935.012 | C7: Docs Signup | D7: Chloe Tanaka | E7: noah26@postbox.example | F7: Disposable | I7: Japan | J7: Other | K7: Partnership proposal for fintech influencer marketing campaign, 500k reach. | L7: 2 | M7: 99.9 | N7: Rahul | Q7: =IF(F7="Disposable",1,0) -> 1 | R7: =IF(SUMPRODUCT(--ISNUMBER(SEARCH('Spam Rules'!$A$22:$A$35,K7)))>0,1,0) -> 1 | S7: =IF(AND(F7="Free",G7=""),1,0) -> 0 | T7: =IF(LEN(TRIM(K7))<15,1,0) -> 0 | U7: =IF(COUNTIF($E$2:$E$801,E7)>1,1,0) -> 1 | V7: =Q7*'Spam Rules'!$H$6+R7*'Spam Rules'!$H$7+S7*'Spam Rules'!$H$8+T7*'Spam Rules'!$H$9+U7*'Spam Rules'!$H$10 -> 2 | W7: =IF(V7>='Spam Rules'!$B$3,"Likely Spam","Genuine") -> Likely Spam | X7: =IFERROR(INDEX('Scoring Model'!$B$5:$B$11,MATCH(C7,'Scoring Model'!$A$5:$A$11,0)),0) -> 5 | Y7: =IFERROR(INDEX('Scoring Model'!$E$5:$E$7,MATCH(F7,'Scoring Model'!$D$5:$D$7,0)),0) -> 0 | Z7: =IFERROR(INDEX('Scoring Model'!$H$5:$H$13,MATCH(J7,'Scoring Model'!$G$5:$G$13,0)),0) -> 0 | AA7: =IF(L7>='Scoring Model'!$B$14,'Scoring Model'!$B$15,IF(L7>='Scoring Model'!$B$16,'Scoring Model'!$B$17,0)) -> 0 | AB7: =IF(SUMPRODUCT(--ISNUMBER(SEARCH('Scoring Model'!$D$16:$D$25,K7)))>0,'Scoring Model'!$B$18,0) -> 0 | AC7: =IF(SUMPRODUCT(--ISNUMBER(SEARCH('Scoring Model'!$G$16:$G$23,K7)))>0,'Scoring Model'!$B$19,0) -> 0 | AD7: =IF(W7="Likely Spam","",SUM(X7:AC7)) | AE7: =IF(W7="Likely Spam","Spam",IF(AD7>='Scoring Model'!$B$21,"Hot",IF(AD7>='Scoring Model'!$B$22,"Warm","Nurture"))) -> Spam | AF7: =IF(W7="Likely Spam","Flagged by spam rules",TRIM(IF(X7>=20,"Strong source. ","")&IF(Y7>0,"Company email. ","")&IF(Z7>=15,"High-value product. ","")&IF(AA7>='Scoring Model'!$B$15,"High engagement. ","")&IF(AB7>0,"Buying intent in message. ","")&IF(AC7<0,"Negative intent in message. ",""))) -> Flagged by spam rules | AG7: =IF(W7="Likely Spam","",1/(1+EXP(-('Conversion Model'!$B$5+IFERROR(INDEX('Conversion Model'!$B$8:$B$14,MATCH(C7,'Conversion Model'!$A$8:$A$14,0)),0)+IFERROR(INDEX('Conversion Model'!$E$8:$E$9,MATCH(F7,'Conversion Model'!$D$8:$D$9,0)),0)+IFERROR(INDEX('Conversion Model'!$H$8:$H$12,MATCH(IF(LEFT(J7,8)="Payments","Payments",IF(LEFT(J7,7)="Lending","Lending",J7)),'Conversion Model'!$G$8:$G$12,0)),0)+MIN(L7,15)*'Conversion Model'!$B$17+IF(SUMPRODUCT(--ISNUMBER(SEARCH('Scoring Model'!$D$16:$D$25,K7)))>0,'Conversion Model'!$B$18,0)+IF(SUMPRODUCT(--ISNUMBER(SEARCH('Scoring Model'!$G$16:$G$23,K7)))>0,'Conversion Model'!$B$19,0))))) | AH7: =IF(OR(O7="Qualified",O7="Won",O7="Lost"),1,IF(O7="Unqualified",0,""))
A8: L-0007 | B8: 45935.153 | C8: Docs Signup | D8: Mateo Haddad | E8: mateo.haddad@webmail.example | F8: Free | G8: Zellowmark Labs | I8: Japan | J8: Other | K8: Can I use your API for a personal budget tracker? | L8: 4 | M8: 8.4 | N8: Vikram | Q8: =IF(F8="Disposable",1,0) -> 0 | R8: =IF(SUMPRODUCT(--ISNUMBER(SEARCH('Spam Rules'!$A$22:$A$35,K8)))>0,1,0) -> 0 | S8: =IF(AND(F8="Free",G8=""),1,0) -> 0 | T8: =IF(LEN(TRIM(K8))<15,1,0) -> 0 | U8: =IF(COUNTIF($E$2:$E$801,E8)>1,1,0) -> 0 | V8: =Q8*'Spam Rules'!$H$6+R8*'Spam Rules'!$H$7+S8*'Spam Rules'!$H$8+T8*'Spam Rules'!$H$9+U8*'Spam Rules'!$H$10 -> 0 | W8: =IF(V8>='Spam Rules'!$B$3,"Likely Spam","Genuine") -> Genuine | X8: =IFERROR(INDEX('Scoring Model'!$B$5:$B$11,MATCH(C8,'Scoring Model'!$A$5:$A$11,0)),0) -> 5 | Y8: =IFERROR(INDEX('Scoring Model'!$E$5:$E$7,MATCH(F8,'Scoring Model'!$D$5:$D$7,0)),0) -> 0 | Z8: =IFERROR(INDEX('Scoring Model'!$H$5:$H$13,MATCH(J8,'Scoring Model'!$G$5:$G$13,0)),0) -> 0 | AA8: =IF(L8>='Scoring Model'!$B$14,'Scoring Model'!$B$15,IF(L8>='Scoring Model'!$B$16,'Scoring Model'!$B$17,0)) -> 8 | AB8: =IF(SUMPRODUCT(--ISNUMBER(SEARCH('Scoring Model'!$D$16:$D$25,K8)))>0,'Scoring Model'!$B$18,0) -> 0 | AC8: =IF(SUMPRODUCT(--ISNUMBER(SEARCH('Scoring Model'!$G$16:$G$23,K8)))>0,'Scoring Model'!$B$19,0) -> -30 | AD8: =IF(W8="Likely Spam","",SUM(X8:AC8)) -> -17 | AE8: =IF(W8="Likely Spam","Spam",IF(AD8>='Scoring Model'!$B$21,"Hot",IF(AD8>='Scoring Model'!$B$22,"Warm","Nurture"))) -> Nurture | AF8: =IF(W8="Likely Spam","Flagged by spam rules",TRIM(IF(X8>=20,"Strong source. ","")&IF(Y8>0,"Company email. ","")&IF(Z8>=15,"High-value product. ","")&IF(AA8>='Scoring Model'!$B$15,"High engagement. ","")&IF(AB8>0,"Buying intent in message. ","")&IF(AC8<0,"Negative intent in message. ",""))) -> Negative intent in message. | AG8: =IF(W8="Likely Spam","",1/(1+EXP(-('Conversion Model'!$B$5+IFERROR(INDEX('Conversion Model'!$B$8:$B$14,MATCH(C8,'Conversion Model'!$A$8:$A$14,0)),0)+IFERROR(INDEX('Conversion Model'!$E$8:$E$9,MATCH(F8,'Conversion Model'!$D$8:$D$9,0)),0)+IFERROR(INDEX('Conversion Model'!$H$8:$H$12,MATCH(IF(LEFT(J8,8)="Payments","Payments",IF(LEFT(J8,7)="Lending","Lending",J8)),'Conversion Model'!$G$8:$G$12,0)),0)+MIN(L8,15)*'Conversion Model'!$B$17+IF(SUMPRODUCT(--ISNUMBER(SEARCH('Scoring Model'!$D$16:$D$25,K8)))>0,'Conversion Model'!$B$18,0)+IF(SUMPRODUCT(--ISNUMBER(SEARCH('Scoring Model'!$G$16:$G$23,K8)))>0,'Conversion Model'!$B$19,0))))) -> 0.0074801067 | AH8: =IF(OR(O8="Qualified",O8="Won",O8="Lost"),1,IF(O8="Unqualified",0,""))
A9: L-0008 | B9: 45935.308 | C9: Website Contact Form | D9: Nadia Costa | E9: nadia.costa@larkspindlewallet.example | F9: Company | G9: Larkspindle Wallet | H9: https://larkspindlewallet.example | I9: Turkey | J9: Payments - Payouts | K9: Evaluating payouts providers for our loyalty app. Can we get a demo and a cost comparison? | L9: 9 | M9: 88 | N9: Unassigned | O9: Lost | Q9: =IF(F9="Disposable",1,0) -> 0 | R9: =IF(SUMPRODUCT(--ISNUMBER(SEARCH('Spam Rules'!$A$22:$A$35,K9)))>0,1,0) -> 0 | S9: =IF(AND(F9="Free",G9=""),1,0) -> 0 | T9: =IF(LEN(TRIM(K9))<15,1,0) -> 0 | U9: =IF(COUNTIF($E$2:$E$801,E9)>1,1,0) -> 0 | V9: =Q9*'Spam Rules'!$H$6+R9*'Spam Rules'!$H$7+S9*'Spam Rules'!$H$8+T9*'Spam Rules'!$H$9+U9*'Spam Rules'!$H$10 -> 0 | W9: =IF(V9>='Spam Rules'!$B$3,"Likely Spam","Genuine") -> Genuine | X9: =IFERROR(INDEX('Scoring Model'!$B$5:$B$11,MATCH(C9,'Scoring Model'!$A$5:$A$11,0)),0) -> 10 | Y9: =IFERROR(INDEX('Scoring Model'!$E$5:$E$7,MATCH(F9,'Scoring Model'!$D$5:$D$7,0)),0) -> 20 | Z9: =IFERROR(INDEX('Scoring Model'!$H$5:$H$13,MATCH(J9,'Scoring Model'!$G$5:$G$13,0)),0) -> 15 | AA9: =IF(L9>='Scoring Model'!$B$14,'Scoring Model'!$B$15,IF(L9>='Scoring Model'!$B$16,'Scoring Model'!$B$17,0)) -> 15 | AB9: =IF(SUMPRODUCT(--ISNUMBER(SEARCH('Scoring Model'!$D$16:$D$25,K9)))>0,'Scoring Model'!$B$18,0) -> 15 | AC9: =IF(SUMPRODUCT(--ISNUMBER(SEARCH('Scoring Model'!$G$16:$G$23,K9)))>0,'Scoring Model'!$B$19,0) -> 0 | AD9: =IF(W9="Likely Spam","",SUM(X9:AC9)) -> 75 | AE9: =IF(W9="Likely Spam","Spam",IF(AD9>='Scoring Model'!$B$21,"Hot",IF(AD9>='Scoring Model'!$B$22,"Warm","Nurture"))) -> Hot | AF9: =IF(W9="Likely Spam","Flagged by spam rules",TRIM(IF(X9>=20,"Strong source. ","")&IF(Y9>0,"Company email. ","")&IF(Z9>=15,"High-value product. ","")&IF(AA9>='Scoring Model'!$B$15,"High engagement. ","")&IF(AB9>0,"Buying intent in message. ","")&IF(AC9<0,"Negative intent in message. ",""))) -> Company email. High-value product. High engagement. Buying intent in message. | AG9: =IF(W9="Likely Spam","",1/(1+EXP(-('Conversion Model'!$B$5+IFERROR(INDEX('Conversion Model'!$B$8:$B$14,MATCH(C9,'Conversion Model'!$A$8:$A$14,0)),0)+IFERROR(INDEX('Conversion Model'!$E$8:$E$9,MATCH(F9,'Conversion Model'!$D$8:$D$9,0)),0)+IFERROR(INDEX('Conversion Model'!$H$8:$H$12,MATCH(IF(LEFT(J9,8)="Payments","Payments",IF(LEFT(J9,7)="Lending","Lending",J9)),'Conversion Model'!$G$8:$G$12,0)),0)+MIN(L9,15)*'Conversion Model'!$B$17+IF(SUMPRODUCT(--ISNUMBER(SEARCH('Scoring Model'!$D$16:$D$25,K9)))>0,'Conversion Model'!$B$18,0)+IF(SUMPRODUCT(--ISNUMBER(SEARCH('Scoring Model'!$G$16:$G$23,K9)))>0,'Conversion Model'!$B$19,0))))) -> 0.98188973 | AH9: =IF(OR(O9="Qualified",O9="Won",O9="Lost"),1,IF(O9="Unqualified",0,"")) -> 1
A10: L-0009 | B10: 45935.376 | C10: Event | D10: Mateo Okafor | E10: mateo.okafor@freemail.example | F10: Free | G10: Vexmoor Labs | I10: Brazil | J10: Lending - Credit Scoring | K10: Looking for pricing on KYC verification across 5 countries. Our current vendor keeps missing checks. | L10: 3 | M10: 3.6 | N10: Rahul | Q10: =IF(F10="Disposable",1,0) -> 0 | R10: =IF(SUMPRODUCT(--ISNUMBER(SEARCH('Spam Rules'!$A$22:$A$35,K10)))>0,1,0) -> 0 | S10: =IF(AND(F10="Free",G10=""),1,0) -> 0 | T10: =IF(LEN(TRIM(K10))<15,1,0) -> 0 | U10: =IF(COUNTIF($E$2:$E$801,E10)>1,1,0) -> 0 | V10: =Q10*'Spam Rules'!$H$6+R10*'Spam Rules'!$H$7+S10*'Spam Rules'!$H$8+T10*'Spam Rules'!$H$9+U10*'Spam Rules'!$H$10 -> 0 | W10: =IF(V10>='Spam Rules'!$B$3,"Likely Spam","Genuine") -> Genuine | X10: =IFERROR(INDEX('Scoring Model'!$B$5:$B$11,MATCH(C10,'Scoring Model'!$A$5:$A$11,0)),0) -> 15 | Y10: =IFERROR(INDEX('Scoring Model'!$E$5:$E$7,MATCH(F10,'Scoring Model'!$D$5:$D$7,0)),0) -> 0 | Z10: =IFERROR(INDEX('Scoring Model'!$H$5:$H$13,MATCH(J10,'Scoring Model'!$G$5:$G$13,0)),0) -> 15 | AA10: =IF(L10>='Scoring Model'!$B$14,'Scoring Model'!$B$15,IF(L10>='Scoring Model'!$B$16,'Scoring Model'!$B$17,0)) -> 0 | AB10: =IF(SUMPRODUCT(--ISNUMBER(SEARCH('Scoring Model'!$D$16:$D$25,K10)))>0,'Scoring Model'!$B$18,0) -> 15 | AC10: =IF(SUMPRODUCT(--ISNUMBER(SEARCH('Scoring Model'!$G$16:$G$23,K10)))>0,'Scoring Model'!$B$19,0) -> 0 | AD10: =IF(W10="Likely Spam","",SUM(X10:AC10)) -> 45 | AE10: =IF(W10="Likely Spam","Spam",IF(AD10>='Scoring Model'!$B$21,"Hot",IF(AD10>='Scoring Model'!$B$22,"Warm","Nurture"))) -> Warm | AF10: =IF(W10="Likely Spam","Flagged by spam rules",TRIM(IF(X10>=20,"Strong source. ","")&IF(Y10>0,"Company email. ","")&IF(Z10>=15,"High-value product. ","")&IF(AA10>='Scoring Model'!$B$15,"High engagement. ","")&IF(AB10>0,"Buying intent in message. ","")&IF(AC10<0,"Negative intent in message. ",""))) -> High-value product. Buying intent in message. | AG10: =IF(W10="Likely Spam","",1/(1+EXP(-('Conversion Model'!$B$5+IFERROR(INDEX('Conversion Model'!$B$8:$B$14,MATCH(C10,'Conversion Model'!$A$8:$A$14,0)),0)+IFERROR(INDEX('Conversion Model'!$E$8:$E$9,MATCH(F10,'Conversion Model'!$D$8:$D$9,0)),0)+IFERROR(INDEX('Conversion Model'!$H$8:$H$12,MATCH(IF(LEFT(J10,8)="Payments","Payments",IF(LEFT(J10,7)="Lending","Lending",J10)),'Conversion Model'!$G$8:$G$12,0)),0)+MIN(L10,15)*'Conversion Model'!$B$17+IF(SUMPRODUCT(--ISNUMBER(SEARCH('Scoring Model'!$D$16:$D$25,K10)))>0,'Conversion Model'!$B$18,0)+IF(SUMPRODUCT(--ISNUMBER(SEARCH('Scoring Model'!$G$16:$G$23,K10)))>0,'Conversion Model'!$B$19,0))))) -> 0.32431757 | AH10: =IF(OR(O10="Qualified",O10="Won",O10="Lost"),1,IF(O10="Unqualified",0,""))
A11: L-0010 | B11: 45935.827 | C11: Website Contact Form | D11: Ji-woo Brown | E11: noah877@letterdrop.example | F11: Disposable | I11: Brazil | J11: Payments - Card Issuing | K11: Boost your Twitter followers and Telegram members, organic fintech marketing. | L11: 1 | N11: Unassigned | O11: Spam | Q11: =IF(F11="Disposable",1,0) -> 1 | R11: =IF(SUMPRODUCT(--ISNUMBER(SEARCH('Spam Rules'!$A$22:$A$35,K11)))>0,1,0) -> 1 | S11: =IF(AND(F11="Free",G11=""),1,0) -> 0 | T11: =IF(LEN(TRIM(K11))<15,1,0) -> 0 | U11: =IF(COUNTIF($E$2:$E$801,E11)>1,1,0) -> 1 | V11: =Q11*'Spam Rules'!$H$6+R11*'Spam Rules'!$H$7+S11*'Spam Rules'!$H$8+T11*'Spam Rules'!$H$9+U11*'Spam Rules'!$H$10 -> 2 | W11: =IF(V11>='Spam Rules'!$B$3,"Likely Spam","Genuine") -> Likely Spam | X11: =IFERROR(INDEX('Scoring Model'!$B$5:$B$11,MATCH(C11,'Scoring Model'!$A$5:$A$11,0)),0) -> 10 | Y11: =IFERROR(INDEX('Scoring Model'!$E$5:$E$7,MATCH(F11,'Scoring Model'!$D$5:$D$7,0)),0) -> 0 | Z11: =IFERROR(INDEX('Scoring Model'!$H$5:$H$13,MATCH(J11,'Scoring Model'!$G$5:$G$13,0)),0) -> 15 | AA11: =IF(L11>='Scoring Model'!$B$14,'Scoring Model'!$B$15,IF(L11>='Scoring Model'!$B$16,'Scoring Model'!$B$17,0)) -> 0 | AB11: =IF(SUMPRODUCT(--ISNUMBER(SEARCH('Scoring Model'!$D$16:$D$25,K11)))>0,'Scoring Model'!$B$18,0) -> 0 | AC11: =IF(SUMPRODUCT(--ISNUMBER(SEARCH('Scoring Model'!$G$16:$G$23,K11)))>0,'Scoring Model'!$B$19,0) -> 0 | AD11: =IF(W11="Likely Spam","",SUM(X11:AC11)) | AE11: =IF(W11="Likely Spam","Spam",IF(AD11>='Scoring Model'!$B$21,"Hot",IF(AD11>='Scoring Model'!$B$22,"Warm","Nurture"))) -> Spam | AF11: =IF(W11="Likely Spam","Flagged by spam rules",TRIM(IF(X11>=20,"Strong source. ","")&IF(Y11>0,"Company email. ","")&IF(Z11>=15,"High-value product. ","")&IF(AA11>='Scoring Model'!$B$15,"High engagement. ","")&IF(AB11>0,"Buying intent in message. ","")&IF(AC11<0,"Negative intent in message. ",""))) -> Flagged by spam rules | AG11: =IF(W11="Likely Spam","",1/(1+EXP(-('Conversion Model'!$B$5+IFERROR(INDEX('Conversion Model'!$B$8:$B$14,MATCH(C11,'Conversion Model'!$A$8:$A$14,0)),0)+IFERROR(INDEX('Conversion Model'!$E$8:$E$9,MATCH(F11,'Conversion Model'!$D$8:$D$9,0)),0)+IFERROR(INDEX('Conversion Model'!$H$8:$H$12,MATCH(IF(LEFT(J11,8)="Payments","Payments",IF(LEFT(J11,7)="Lending","Lending",J11)),'Conversion Model'!$G$8:$G$12,0)),0)+MIN(L11,15)*'Conversion Model'!$B$17+IF(SUMPRODUCT(--ISNUMBER(SEARCH('Scoring Model'!$D$16:$D$25,K11)))>0,'Conversion Model'!$B$18,0)+IF(SUMPRODUCT(--ISNUMBER(SEARCH('Scoring Model'!$G$16:$G$23,K11)))>0,'Conversion Model'!$B$19,0))))) | AH11: =IF(OR(O11="Qualified",O11="Won",O11="Lost"),1,IF(O11="Unqualified",0,""))
A12: L-0011 | B12: 45935.905 | C12: Chat Widget | D12: Zara Kim | E12: zara780@letterdrop.example | F12: Free | I12: UK | J12: KYC Verification | K12: hi | L12: 2 | N12: Unassigned | O12: Spam | Q12: =IF(F12="Disposable",1,0) -> 0 | R12: =IF(SUMPRODUCT(--ISNUMBER(SEARCH('Spam Rules'!$A$22:$A$35,K12)))>0,1,0) -> 0 | S12: =IF(AND(F12="Free",G12=""),1,0) -> 1 | T12: =IF(LEN(TRIM(K12))<15,1,0) -> 1 | U12: =IF(COUNTIF($E$2:$E$801,E12)>1,1,0) -> 0 | V12: =Q12*'Spam Rules'!$H$6+R12*'Spam Rules'!$H$7+S12*'Spam Rules'!$H$8+T12*'Spam Rules'!$H$9+U12*'Spam Rules'!$H$10 -> 1 | W12: =IF(V12>='Spam Rules'!$B$3,"Likely Spam","Genuine") -> Likely Spam | X12: =IFERROR(INDEX('Scoring Model'!$B$5:$B$11,MATCH(C12,'Scoring Model'!$A$5:$A$11,0)),0) -> 0 | Y12: =IFERROR(INDEX('Scoring Model'!$E$5:$E$7,MATCH(F12,'Scoring Model'!$D$5:$D$7,0)),0) -> 0 | Z12: =IFERROR(INDEX('Scoring Model'!$H$5:$H$13,MATCH(J12,'Scoring Model'!$G$5:$G$13,0)),0) -> 5 | AA12: =IF(L12>='Scoring Model'!$B$14,'Scoring Model'!$B$15,IF(L12>='Scoring Model'!$B$16,'Scoring Model'!$B$17,0)) -> 0 | AB12: =IF(SUMPRODUCT(--ISNUMBER(SEARCH('Scoring Model'!$D$16:$D$25,K12)))>0,'Scoring Model'!$B$18,0) -> 0 | AC12: =IF(SUMPRODUCT(--ISNUMBER(SEARCH('Scoring Model'!$G$16:$G$23,K12)))>0,'Scoring Model'!$B$19,0) -> 0 | AD12: =IF(W12="Likely Spam","",SUM(X12:AC12)) | AE12: =IF(W12="Likely Spam","Spam",IF(AD12>='Scoring Model'!$B$21,"Hot",IF(AD12>='Scoring Model'!$B$22,"Warm","Nurture"))) -> Spam | AF12: =IF(W12="Likely Spam","Flagged by spam rules",TRIM(IF(X12>=20,"Strong source. ","")&IF(Y12>0,"Company email. ","")&IF(Z12>=15,"High-value product. ","")&IF(AA12>='Scoring Model'!$B$15,"High engagement. ","")&IF(AB12>0,"Buying intent in message. ","")&IF(AC12<0,"Negative intent in message. ",""))) -> Flagged by spam rules | AG12: =IF(W12="Likely Spam","",1/(1+EXP(-('Conversion Model'!$B$5+IFERROR(INDEX('Conversion Model'!$B$8:$B$14,MATCH(C12,'Conversion Model'!$A$8:$A$14,0)),0)+IFERROR(INDEX('Conversion Model'!$E$8:$E$9,MATCH(F12,'Conversion Model'!$D$8:$D$9,0)),0)+IFERROR(INDEX('Conversion Model'!$H$8:$H$12,MATCH(IF(LEFT(J12,8)="Payments","Payments",IF(LEFT(J12,7)="Lending","Lending",J12)),'Conversion Model'!$G$8:$G$12,0)),0)+MIN(L12,15)*'Conversion Model'!$B$17+IF(SUMPRODUCT(--ISNUMBER(SEARCH('Scoring Model'!$D$16:$D$25,K12)))>0,'Conversion Model'!$B$18,0)+IF(SUMPRODUCT(--ISNUMBER(SEARCH('Scoring Model'!$G$16:$G$23,K12)))>0,'Conversion Model'!$B$19,0))))) | AH12: =IF(OR(O12="Qualified",O12="Won",O12="Lost"),1,IF(O12="Unqualified",0,""))
A13: L-0012 | B13: 45936.767 | C13: Partner Referral | D13: Mateo Garcia | E13: mateo.garcia@juniperholtcommerce.example | F13: Company | G13: Juniperholt Commerce | H13: https://juniperholtcommerce.example | I13: Japan | J13: KYC Verification | K13: Looking for pricing on KYC verification across 5 countries. Our current vendor keeps missing checks. | L13: 3 | M13: 66.2 | N13: Rahul | O13: Open | Q13: =IF(F13="Disposable",1,0) -> 0 | R13: =IF(SUMPRODUCT(--ISNUMBER(SEARCH('Spam Rules'!$A$22:$A$35,K13)))>0,1,0) -> 0 | S13: =IF(AND(F13="Free",G13=""),1,0) -> 0 | T13: =IF(LEN(TRIM(K13))<15,1,0) -> 0 | U13: =IF(COUNTIF($E$2:$E$801,E13)>1,1,0) -> 0 | V13: =Q13*'Spam Rules'!$H$6+R13*'Spam Rules'!$H$7+S13*'Spam Rules'!$H$8+T13*'Spam Rules'!$H$9+U13*'Spam Rules'!$H$10 -> 0 | W13: =IF(V13>='Spam Rules'!$B$3,"Likely Spam","Genuine") -> Genuine | X13: =IFERROR(INDEX('Scoring Model'!$B$5:$B$11,MATCH(C13,'Scoring Model'!$A$5:$A$11,0)),0) -> 30 | Y13: =IFERROR(INDEX('Scoring Model'!$E$5:$E$7,MATCH(F13,'Scoring Model'!$D$5:$D$7,0)),0) -> 20 | Z13: =IFERROR(INDEX('Scoring Model'!$H$5:$H$13,MATCH(J13,'Scoring Model'!$G$5:$G$13,0)),0) -> 5 | AA13: =IF(L13>='Scoring Model'!$B$14,'Scoring Model'!$B$15,IF(L13>='Scoring Model'!$B$16,'Scoring Model'!$B$17,0)) -> 0 | AB13: =IF(SUMPRODUCT(--ISNUMBER(SEARCH('Scoring Model'!$D$16:$D$25,K13)))>0,'Scoring Model'!$B$18,0) -> 15 | AC13: =IF(SUMPRODUCT(--ISNUMBER(SEARCH('Scoring Model'!$G$16:$G$23,K13)))>0,'Scoring Model'!$B$19,0) -> 0 | AD13: =IF(W13="Likely Spam","",SUM(X13:AC13)) -> 70 | AE13: =IF(W13="Likely Spam","Spam",IF(AD13>='Scoring Model'!$B$21,"Hot",IF(AD13>='Scoring Model'!$B$22,"Warm","Nurture"))) -> Hot | AF13: =IF(W13="Likely Spam","Flagged by spam rules",TRIM(IF(X13>=20,"Strong source. ","")&IF(Y13>0,"Company email. ","")&IF(Z13>=15,"High-value product. ","")&IF(AA13>='Scoring Model'!$B$15,"High engagement. ","")&IF(AB13>0,"Buying intent in message. ","")&IF(AC13<0,"Negative intent in message. ",""))) -> Strong source. Company email. Buying intent in message. | AG13: =IF(W13="Likely Spam","",1/(1+EXP(-('Conversion Model'!$B$5+IFERROR(INDEX('Conversion Model'!$B$8:$B$14,MATCH(C13,'Conversion Model'!$A$8:$A$14,0)),0)+IFERROR(INDEX('Conversion Model'!$E$8:$E$9,MATCH(F13,'Conversion Model'!$D$8:$D$9,0)),0)+IFERROR(INDEX('Conversion Model'!$H$8:$H$12,MATCH(IF(LEFT(J13,8)="Payments","Payments",IF(LEFT(J13,7)="Lending","Lending",J13)),'Conversion Model'!$G$8:$G$12,0)),0)+MIN(L13,15)*'Conversion Model'!$B$17+IF(SUMPRODUCT(--ISNUMBER(SEARCH('Scoring Model'!$D$16:$D$25,K13)))>0,'Conversion Model'!$B$18,0)+IF(SUMPRODUCT(--ISNUMBER(SEARCH('Scoring Model'!$G$16:$G$23,K13)))>0,'Conversion Model'!$B$19,0))))) -> 0.49775002 | AH13: =IF(OR(O13="Qualified",O13="Won",O13="Lost"),1,IF(O13="Unqualified",0,""))
A14: L-0013 | B14: 45937.351 | C14: LinkedIn ABM | D14: Ananya Lee | E14: ananya.lee@webmail.example | F14: Free | G14: Brindlewick Pay | I14: Germany | J14: Payments - Virtual Accounts | K14: We raised a seed round and plan to launch a digital savings platform for SMEs. Want to discuss infrastructure. | L14: 2 | M14: 3 | N14: Vikram | O14: Open | Q14: =IF(F14="Disposable",1,0) -> 0 | R14: =IF(SUMPRODUCT(--ISNUMBER(SEARCH('Spam Rules'!$A$22:$A$35,K14)))>0,1,0) -> 0 | S14: =IF(AND(F14="Free",G14=""),1,0) -> 0 | T14: =IF(LEN(TRIM(K14))<15,1,0) -> 0 | U14: =IF(COUNTIF($E$2:$E$801,E14)>1,1,0) -> 0 | V14: =Q14*'Spam Rules'!$H$6+R14*'Spam Rules'!$H$7+S14*'Spam Rules'!$H$8+T14*'Spam Rules'!$H$9+U14*'Spam Rules'!$H$10 -> 0 | W14: =IF(V14>='Spam Rules'!$B$3,"Likely Spam","Genuine") -> Genuine | X14: =IFERROR(INDEX('Scoring Model'!$B$5:$B$11,MATCH(C14,'Scoring Model'!$A$5:$A$11,0)),0) -> 20 | Y14: =IFERROR(INDEX('Scoring Model'!$E$5:$E$7,MATCH(F14,'Scoring Model'!$D$5:$D$7,0)),0) -> 0 | Z14: =IFERROR(INDEX('Scoring Model'!$H$5:$H$13,MATCH(J14,'Scoring Model'!$G$5:$G$13,0)),0) -> 15 | AA14: =IF(L14>='Scoring Model'!$B$14,'Scoring Model'!$B$15,IF(L14>='Scoring Model'!$B$16,'Scoring Model'!$B$17,0)) -> 0 | AB14: =IF(SUMPRODUCT(--ISNUMBER(SEARCH('Scoring Model'!$D$16:$D$25,K14)))>0,'Scoring Model'!$B$18,0) -> 15 | AC14: =IF(SUMPRODUCT(--ISNUMBER(SEARCH('Scoring Model'!$G$16:$G$23,K14)))>0,'Scoring Model'!$B$19,0) -> 0 | AD14: =IF(W14="Likely Spam","",SUM(X14:AC14)) -> 50 | AE14: =IF(W14="Likely Spam","Spam",IF(AD14>='Scoring Model'!$B$21,"Hot",IF(AD14>='Scoring Model'!$B$22,"Warm","Nurture"))) -> Warm | AF14: =IF(W14="Likely Spam","Flagged by spam rules",TRIM(IF(X14>=20,"Strong source. ","")&IF(Y14>0,"Company email. ","")&IF(Z14>=15,"High-value product. ","")&IF(AA14>='Scoring Model'!$B$15,"High engagement. ","")&IF(AB14>0,"Buying intent in message. ","")&IF(AC14<0,"Negative intent in message. ",""))) -> Strong source. High-value product. Buying intent in message. | AG14: =IF(W14="Likely Spam","",1/(1+EXP(-('Conversion Model'!$B$5+IFERROR(INDEX('Conversion Model'!$B$8:$B$14,MATCH(C14,'Conversion Model'!$A$8:$A$14,0)),0)+IFERROR(INDEX('Conversion Model'!$E$8:$E$9,MATCH(F14,'Conversion Model'!$D$8:$D$9,0)),0)+IFERROR(INDEX('Conversion Model'!$H$8:$H$12,MATCH(IF(LEFT(J14,8)="Payments","Payments",IF(LEFT(J14,7)="Lending","Lending",J14)),'Conversion Model'!$G$8:$G$12,0)),0)+MIN(L14,15)*'Conversion Model'!$B$17+IF(SUMPRODUCT(--ISNUMBER(SEARCH('Scoring Model'!$D$16:$D$25,K14)))>0,'Conversion Model'!$B$18,0)+IF(SUMPRODUCT(--ISNUMBER(SEARCH('Scoring Model'!$G$16:$G$23,K14)))>0,'Conversion Model'!$B$19,0))))) -> 0.16437906 | AH14: =IF(OR(O14="Qualified",O14="Won",O14="Lost"),1,IF(O14="Unqualified",0,""))
A15: L-0014 | B15: 45937.691 | C15: Event | D15: Zara Garcia | E15: zara.garcia@dunmarrowcapital.example | F15: Company | G15: Dunmarrow Capital | H15: https://dunmarrowcapital.example | I15: Singapore | J15: Banking Data API | K15: We are launching a loyalty product and need a managed card issuing setup with go-live in Q2. | L15: 11 | M15: 18.9 | N15: Unassigned | O15: Won | P15: 48000 | Q15: =IF(F15="Disposable",1,0) -> 0 | R15: =IF(SUMPRODUCT(--ISNUMBER(SEARCH('Spam Rules'!$A$22:$A$35,K15)))>0,1,0) -> 0 | S15: =IF(AND(F15="Free",G15=""),1,0) -> 0 | T15: =IF(LEN(TRIM(K15))<15,1,0) -> 0 | U15: =IF(COUNTIF($E$2:$E$801,E15)>1,1,0) -> 0 | V15: =Q15*'Spam Rules'!$H$6+R15*'Spam Rules'!$H$7+S15*'Spam Rules'!$H$8+T15*'Spam Rules'!$H$9+U15*'Spam Rules'!$H$10 -> 0 | W15: =IF(V15>='Spam Rules'!$B$3,"Likely Spam","Genuine") -> Genuine | X15: =IFERROR(INDEX('Scoring Model'!$B$5:$B$11,MATCH(C15,'Scoring Model'!$A$5:$A$11,0)),0) -> 15 | Y15: =IFERROR(INDEX('Scoring Model'!$E$5:$E$7,MATCH(F15,'Scoring Model'!$D$5:$D$7,0)),0) -> 20 | Z15: =IFERROR(INDEX('Scoring Model'!$H$5:$H$13,MATCH(J15,'Scoring Model'!$G$5:$G$13,0)),0) -> 5 | AA15: =IF(L15>='Scoring Model'!$B$14,'Scoring Model'!$B$15,IF(L15>='Scoring Model'!$B$16,'Scoring Model'!$B$17,0)) -> 15 | AB15: =IF(SUMPRODUCT(--ISNUMBER(SEARCH('Scoring Model'!$D$16:$D$25,K15)))>0,'Scoring Model'!$B$18,0) -> 15 | AC15: =IF(SUMPRODUCT(--ISNUMBER(SEARCH('Scoring Model'!$G$16:$G$23,K15)))>0,'Scoring Model'!$B$19,0) -> 0 | AD15: =IF(W15="Likely Spam","",SUM(X15:AC15)) -> 70 | AE15: =IF(W15="Likely Spam","Spam",IF(AD15>='Scoring Model'!$B$21,"Hot",IF(AD15>='Scoring Model'!$B$22,"Warm","Nurture"))) -> Hot | AF15: =IF(W15="Likely Spam","Flagged by spam rules",TRIM(IF(X15>=20,"Strong source. ","")&IF(Y15>0,"Company email. ","")&IF(Z15>=15,"High-value product. ","")&IF(AA15>='Scoring Model'!$B$15,"High engagement. ","")&IF(AB15>0,"Buying intent in message. ","")&IF(AC15<0,"Negative intent in message. ",""))) -> Company email. High engagement. Buying intent in message. | AG15: =IF(W15="Likely Spam","",1/(1+EXP(-('Conversion Model'!$B$5+IFERROR(INDEX('Conversion Model'!$B$8:$B$14,MATCH(C15,'Conversion Model'!$A$8:$A$14,0)),0)+IFERROR(INDEX('Conversion Model'!$E$8:$E$9,MATCH(F15,'Conversion Model'!$D$8:$D$9,0)),0)+IFERROR(INDEX('Conversion Model'!$H$8:$H$12,MATCH(IF(LEFT(J15,8)="Payments","Payments",IF(LEFT(J15,7)="Lending","Lending",J15)),'Conversion Model'!$G$8:$G$12,0)),0)+MIN(L15,15)*'Conversion Model'!$B$17+IF(SUMPRODUCT(--ISNUMBER(SEARCH('Scoring Model'!$D$16:$D$25,K15)))>0,'Conversion Model'!$B$18,0)+IF(SUMPRODUCT(--ISNUMBER(SEARCH('Scoring Model'!$G$16:$G$23,K15)))>0,'Conversion Model'!$B$19,0))))) -> 0.99695438 | AH15: =IF(OR(O15="Qualified",O15="Won",O15="Lost"),1,IF(O15="Unqualified",0,"")) -> 1
A16: L-0015 | B16: 45939.477 | C16: LinkedIn ABM | D16: Ravi Lee | E16: ravi.lee@quarrytidefinance.example | F16: Company | G16: Quarrytide Finance | H16: https://quarrytidefinance.example | I16: Japan | J16: KYC Verification | K16: We are launching a marketplace product and need a managed card issuing setup with go-live in Q2. | L16: 10 | M16: 155.4 | N16: Rahul | O16: Lost | Q16: =IF(F16="Disposable",1,0) -> 0 | R16: =IF(SUMPRODUCT(--ISNUMBER(SEARCH('Spam Rules'!$A$22:$A$35,K16)))>0,1,0) -> 0 | S16: =IF(AND(F16="Free",G16=""),1,0) -> 0 | T16: =IF(LEN(TRIM(K16))<15,1,0) -> 0 | U16: =IF(COUNTIF($E$2:$E$801,E16)>1,1,0) -> 0 | V16: =Q16*'Spam Rules'!$H$6+R16*'Spam Rules'!$H$7+S16*'Spam Rules'!$H$8+T16*'Spam Rules'!$H$9+U16*'Spam Rules'!$H$10 -> 0 | W16: =IF(V16>='Spam Rules'!$B$3,"Likely Spam","Genuine") -> Genuine | X16: =IFERROR(INDEX('Scoring Model'!$B$5:$B$11,MATCH(C16,'Scoring Model'!$A$5:$A$11,0)),0) -> 20 | Y16: =IFERROR(INDEX('Scoring Model'!$E$5:$E$7,MATCH(F16,'Scoring Model'!$D$5:$D$7,0)),0) -> 20 | Z16: =IFERROR(INDEX('Scoring Model'!$H$5:$H$13,MATCH(J16,'Scoring Model'!$G$5:$G$13,0)),0) -> 5 | AA16: =IF(L16>='Scoring Model'!$B$14,'Scoring Model'!$B$15,IF(L16>='Scoring Model'!$B$16,'Scoring Model'!$B$17,0)) -> 15 | AB16: =IF(SUMPRODUCT(--ISNUMBER(SEARCH('Scoring Model'!$D$16:$D$25,K16)))>0,'Scoring Model'!$B$18,0) -> 15 | AC16: =IF(SUMPRODUCT(--ISNUMBER(SEARCH('Scoring Model'!$G$16:$G$23,K16)))>0,'Scoring Model'!$B$19,0) -> 0 | AD16: =IF(W16="Likely Spam","",SUM(X16:AC16)) -> 75 | AE16: =IF(W16="Likely Spam","Spam",IF(AD16>='Scoring Model'!$B$21,"Hot",IF(AD16>='Scoring Model'!$B$22,"Warm","Nurture"))) -> Hot | AF16: =IF(W16="Likely Spam","Flagged by spam rules",TRIM(IF(X16>=20,"Strong source. ","")&IF(Y16>0,"Company email. ","")&IF(Z16>=15,"High-value product. ","")&IF(AA16>='Scoring Model'!$B$15,"High engagement. ","")&IF(AB16>0,"Buying intent in message. ","")&IF(AC16<0,"Negative intent in message. ",""))) -> Strong source. Company email. High engagement. Buying intent in message. | AG16: =IF(W16="Likely Spam","",1/(1+EXP(-('Conversion Model'!$B$5+IFERROR(INDEX('Conversion Model'!$B$8:$B$14,MATCH(C16,'Conversion Model'!$A$8:$A$14,0)),0)+IFERROR(INDEX('Conversion Model'!$E$8:$E$9,MATCH(F16,'Conversion Model'!$D$8:$D$9,0)),0)+IFERROR(INDEX('Conversion Model'!$H$8:$H$12,MATCH(IF(LEFT(J16,8)="Payments","Payments",IF(LEFT(J16,7)="Lending","Lending",J16)),'Conversion Model'!$G$8:$G$12,0)),0)+MIN(L16,15)*'Conversion Model'!$B$17+IF(SUMPRODUCT(--ISNUMBER(SEARCH('Scoring Model'!$D$16:$D$25,K16)))>0,'Conversion Model'!$B$18,0)+IF(SUMPRODUCT(--ISNUMBER(SEARCH('Scoring Model'!$G$16:$G$23,K16)))>0,'Conversion Model'!$B$19,0))))) -> 0.99495851 | AH16: =IF(OR(O16="Qualified",O16="Won",O16="Lost"),1,IF(O16="Unqualified",0,"")) -> 1
A17: L-0016 | B17: 45939.549 | C17: LinkedIn ABM | D17: Lucas Costa | E17: lucas.costa@pellowinstudio.example | F17: Company | G17: Pellowin Studio | H17: https://pellowinstudio.example | I17: Brazil | J17: Payments - Virtual Accounts | K17: We raised a seed round and plan to launch a digital savings platform for SMEs. Want to discuss infrastructure. | L17: 12 | M17: 8.9 | N17: Rahul | O17: Lost | Q17: =IF(F17="Disposable",1,0) -> 0 | R17: =IF(SUMPRODUCT(--ISNUMBER(SEARCH('Spam Rules'!$A$22:$A$35,K17)))>0,1,0) -> 0 | S17: =IF(AND(F17="Free",G17=""),1,0) -> 0 | T17: =IF(LEN(TRIM(K17))<15,1,0) -> 0 | U17: =IF(COUNTIF($E$2:$E$801,E17)>1,1,0) -> 0 | V17: =Q17*'Spam Rules'!$H$6+R17*'Spam Rules'!$H$7+S17*'Spam Rules'!$H$8+T17*'Spam Rules'!$H$9+U17*'Spam Rules'!$H$10 -> 0 | W17: =IF(V17>='Spam Rules'!$B$3,"Likely Spam","Genuine") -> Genuine | X17: =IFERROR(INDEX('Scoring Model'!$B$5:$B$11,MATCH(C17,'Scoring Model'!$A$5:$A$11,0)),0) -> 20 | Y17: =IFERROR(INDEX('Scoring Model'!$E$5:$E$7,MATCH(F17,'Scoring Model'!$D$5:$D$7,0)),0) -> 20 | Z17: =IFERROR(INDEX('Scoring Model'!$H$5:$H$13,MATCH(J17,'Scoring Model'!$G$5:$G$13,0)),0) -> 15 | AA17: =IF(L17>='Scoring Model'!$B$14,'Scoring Model'!$B$15,IF(L17>='Scoring Model'!$B$16,'Scoring Model'!$B$17,0)) -> 15 | AB17: =IF(SUMPRODUCT(--ISNUMBER(SEARCH('Scoring Model'!$D$16:$D$25,K17)))>0,'Scoring Model'!$B$18,0) -> 15 | AC17: =IF(SUMPRODUCT(--ISNUMBER(SEARCH('Scoring Model'!$G$16:$G$23,K17)))>0,'Scoring Model'!$B$19,0) -> 0 | AD17: =IF(W17="Likely Spam","",SUM(X17:AC17)) -> 85 | AE17: =IF(W17="Likely Spam","Spam",IF(AD17>='Scoring Model'!$B$21,"Hot",IF(AD17>='Scoring Model'!$B$22,"Warm","Nurture"))) -> Hot | AF17: =IF(W17="Likely Spam","Flagged by spam rules",TRIM(IF(X17>=20,"Strong source. ","")&IF(Y17>0,"Company email. ","")&IF(Z17>=15,"High-value product. ","")&IF(AA17>='Scoring Model'!$B$15,"High engagement. ","")&IF(AB17>0,"Buying intent in message. ","")&IF(AC17<0,"Negative intent in message. ",""))) -> Strong source. Company email. High-value product. High engagement. Buying intent in message. | AG17: =IF(W17="Likely Spam","",1/(1+EXP(-('Conversion Model'!$B$5+IFERROR(INDEX('Conversion Model'!$B$8:$B$14,MATCH(C17,'Conversion Model'!$A$8:$A$14,0)),0)+IFERROR(INDEX('Conversion Model'!$E$8:$E$9,MATCH(F17,'Conversion Model'!$D$8:$D$9,0)),0)+IFERROR(INDEX('Conversion Model'!$H$8:$H$12,MATCH(IF(LEFT(J17,8)="Payments","Payments",IF(LEFT(J17,7)="Lending","Lending",J17)),'Conversion Model'!$G$8:$G$12,0)),0)+MIN(L17,15)*'Conversion Model'!$B$17+IF(SUMPRODUCT(--ISNUMBER(SEARCH('Scoring Model'!$D$16:$D$25,K17)))>0,'Conversion Model'!$B$18,0)+IF(SUMPRODUCT(--ISNUMBER(SEARCH('Scoring Model'!$G$16:$G$23,K17)))>0,'Conversion Model'!$B$19,0))))) -> 0.99930784 | AH17: =IF(OR(O17="Qualified",O17="Won",O17="Lost"),1,IF(O17="Unqualified",0,"")) -> 1
A18: L-0017 | B18: 45939.909 | C18: Pricing Page Form | D18: Chloe Mehta | E18: chloe.mehta@rushbarrowpay.example | F18: Company | G18: Rushbarrow Pay | H18: https://rushbarrowpay.example | I18: UAE | J18: Payments - Cross-Border | K18: We are launching a loyalty product and need a managed cross-border setup with go-live in Q2. | L18: 12 | M18: 13.7 | N18: Unassigned | Q18: =IF(F18="Disposable",1,0) -> 0 | R18: =IF(SUMPRODUCT(--ISNUMBER(SEARCH('Spam Rules'!$A$22:$A$35,K18)))>0,1,0) -> 0 | S18: =IF(AND(F18="Free",G18=""),1,0) -> 0 | T18: =IF(LEN(TRIM(K18))<15,1,0) -> 0 | U18: =IF(COUNTIF($E$2:$E$801,E18)>1,1,0) -> 0 | V18: =Q18*'Spam Rules'!$H$6+R18*'Spam Rules'!$H$7+S18*'Spam Rules'!$H$8+T18*'Spam Rules'!$H$9+U18*'Spam Rules'!$H$10 -> 0 | W18: =IF(V18>='Spam Rules'!$B$3,"Likely Spam","Genuine") -> Genuine | X18: =IFERROR(INDEX('Scoring Model'!$B$5:$B$11,MATCH(C18,'Scoring Model'!$A$5:$A$11,0)),0) -> 25 | Y18: =IFERROR(INDEX('Scoring Model'!$E$5:$E$7,MATCH(F18,'Scoring Model'!$D$5:$D$7,0)),0) -> 20 | Z18: =IFERROR(INDEX('Scoring Model'!$H$5:$H$13,MATCH(J18,'Scoring Model'!$G$5:$G$13,0)),0) -> 15 | AA18: =IF(L18>='Scoring Model'!$B$14,'Scoring Model'!$B$15,IF(L18>='Scoring Model'!$B$16,'Scoring Model'!$B$17,0)) -> 15 | AB18: =IF(SUMPRODUCT(--ISNUMBER(SEARCH('Scoring Model'!$D$16:$D$25,K18)))>0,'Scoring Model'!$B$18,0) -> 15 | AC18: =IF(SUMPRODUCT(--ISNUMBER(SEARCH('Scoring Model'!$G$16:$G$23,K18)))>0,'Scoring Model'!$B$19,0) -> 0 | AD18: =IF(W18="Likely Spam","",SUM(X18:AC18)) -> 90 | AE18: =IF(W18="Likely Spam","Spam",IF(AD18>='Scoring Model'!$B$21,"Hot",IF(AD18>='Scoring Model'!$B$22,"Warm","Nurture"))) -> Hot | AF18: =IF(W18="Likely Spam","Flagged by spam rules",TRIM(IF(X18>=20,"Strong source. ","")&IF(Y18>0,"Company email. ","")&IF(Z18>=15,"High-value product. ","")&IF(AA18>='Scoring Model'!$B$15,"High engagement. ","")&IF(AB18>0,"Buying intent in message. ","")&IF(AC18<0,"Negative intent in message. ",""))) -> Strong source. Company email. High-value product. High engagement. Buying intent in message. | AG18: =IF(W18="Likely Spam","",1/(1+EXP(-('Conversion Model'!$B$5+IFERROR(INDEX('Conversion Model'!$B$8:$B$14,MATCH(C18,'Conversion Model'!$A$8:$A$14,0)),0)+IFERROR(INDEX('Conversion Model'!$E$8:$E$9,MATCH(F18,'Conversion Model'!$D$8:$D$9,0)),0)+IFERROR(INDEX('Conversion Model'!$H$8:$H$12,MATCH(IF(LEFT(J18,8)="Payments","Payments",IF(LEFT(J18,7)="Lending","Lending",J18)),'Conversion Model'!$G$8:$G$12,0)),0)+MIN(L18,15)*'Conversion Model'!$B$17+IF(SUMPRODUCT(--ISNUMBER(SEARCH('Scoring Model'!$D$16:$D$25,K18)))>0,'Conversion Model'!$B$18,0)+IF(SUMPRODUCT(--ISNUMBER(SEARCH('Scoring Model'!$G$16:$G$23,K18)))>0,'Conversion Model'!$B$19,0))))) -> 0.99900919 | AH18: =IF(OR(O18="Qualified",O18="Won",O18="Lost"),1,IF(O18="Unqualified",0,""))
A19: L-0018 | B19: 45939.928 | C19: Docs Signup | D19: Lucas Garcia | E19: lucas96@letterdrop.example | F19: Free | I19: India | J19: KYC Verification | K19: test | L19: 1 | M19: 36.5 | N19: Neha | Q19: =IF(F19="Disposable",1,0) -> 0 | R19: =IF(SUMPRODUCT(--ISNUMBER(SEARCH('Spam Rules'!$A$22:$A$35,K19)))>0,1,0) -> 0 | S19: =IF(AND(F19="Free",G19=""),1,0) -> 1 | T19: =IF(LEN(TRIM(K19))<15,1,0) -> 1 | U19: =IF(COUNTIF($E$2:$E$801,E19)>1,1,0) -> 1 | V19: =Q19*'Spam Rules'!$H$6+R19*'Spam Rules'!$H$7+S19*'Spam Rules'!$H$8+T19*'Spam Rules'!$H$9+U19*'Spam Rules'!$H$10 -> 1 | W19: =IF(V19>='Spam Rules'!$B$3,"Likely Spam","Genuine") -> Likely Spam | X19: =IFERROR(INDEX('Scoring Model'!$B$5:$B$11,MATCH(C19,'Scoring Model'!$A$5:$A$11,0)),0) -> 5 | Y19: =IFERROR(INDEX('Scoring Model'!$E$5:$E$7,MATCH(F19,'Scoring Model'!$D$5:$D$7,0)),0) -> 0 | Z19: =IFERROR(INDEX('Scoring Model'!$H$5:$H$13,MATCH(J19,'Scoring Model'!$G$5:$G$13,0)),0) -> 5 | AA19: =IF(L19>='Scoring Model'!$B$14,'Scoring Model'!$B$15,IF(L19>='Scoring Model'!$B$16,'Scoring Model'!$B$17,0)) -> 0 | AB19: =IF(SUMPRODUCT(--ISNUMBER(SEARCH('Scoring Model'!$D$16:$D$25,K19)))>0,'Scoring Model'!$B$18,0) -> 0 | AC19: =IF(SUMPRODUCT(--ISNUMBER(SEARCH('Scoring Model'!$G$16:$G$23,K19)))>0,'Scoring Model'!$B$19,0) -> 0 | AD19: =IF(W19="Likely Spam","",SUM(X19:AC19)) | AE19: =IF(W19="Likely Spam","Spam",IF(AD19>='Scoring Model'!$B$21,"Hot",IF(AD19>='Scoring Model'!$B$22,"Warm","Nurture"))) -> Spam | AF19: =IF(W19="Likely Spam","Flagged by spam rules",TRIM(IF(X19>=20,"Strong source. ","")&IF(Y19>0,"Company email. ","")&IF(Z19>=15,"High-value product. ","")&IF(AA19>='Scoring Model'!$B$15,"High engagement. ","")&IF(AB19>0,"Buying intent in message. ","")&IF(AC19<0,"Negative intent in message. ",""))) -> Flagged by spam rules | AG19: =IF(W19="Likely Spam","",1/(1+EXP(-('Conversion Model'!$B$5+IFERROR(INDEX('Conversion Model'!$B$8:$B$14,MATCH(C19,'Conversion Model'!$A$8:$A$14,0)),0)+IFERROR(INDEX('Conversion Model'!$E$8:$E$9,MATCH(F19,'Conversion Model'!$D$8:$D$9,0)),0)+IFERROR(INDEX('Conversion Model'!$H$8:$H$12,MATCH(IF(LEFT(J19,8)="Payments","Payments",IF(LEFT(J19,7)="Lending","Lending",J19)),'Conversion Model'!$G$8:$G$12,0)),0)+MIN(L19,15)*'Conversion Model'!$B$17+IF(SUMPRODUCT(--ISNUMBER(SEARCH('Scoring Model'!$D$16:$D$25,K19)))>0,'Conversion Model'!$B$18,0)+IF(SUMPRODUCT(--ISNUMBER(SEARCH('Scoring Model'!$G$16:$G$23,K19)))>0,'Conversion Model'!$B$19,0))))) | AH19: =IF(OR(O19="Qualified",O19="Won",O19="Lost"),1,IF(O19="Unqualified",0,""))
A20: L-0019 | B20: 45940.322 | C20: Event | D20: Mei Novak | E20: mei.novak@juniperholtsystems.example | F20: Company | G20: Juniperholt Systems | H20: https://juniperholtsystems.example | I20: Switzerland | J20: Payments - Card Issuing | K20: We are launching a BNPL product and need a managed card issuing setup with go-live in Q4. | L20: 12 | M20: 5.9 | N20: Rahul | Q20: =IF(F20="Disposable",1,0) -> 0 | R20: =IF(SUMPRODUCT(--ISNUMBER(SEARCH('Spam Rules'!$A$22:$A$35,K20)))>0,1,0) -> 0 | S20: =IF(AND(F20="Free",G20=""),1,0) -> 0 | T20: =IF(LEN(TRIM(K20))<15,1,0) -> 0 | U20: =IF(COUNTIF($E$2:$E$801,E20)>1,1,0) -> 0 | V20: =Q20*'Spam Rules'!$H$6+R20*'Spam Rules'!$H$7+S20*'Spam Rules'!$H$8+T20*'Spam Rules'!$H$9+U20*'Spam Rules'!$H$10 -> 0 | W20: =IF(V20>='Spam Rules'!$B$3,"Likely Spam","Genuine") -> Genuine | X20: =IFERROR(INDEX('Scoring Model'!$B$5:$B$11,MATCH(C20,'Scoring Model'!$A$5:$A$11,0)),0) -> 15 | Y20: =IFERROR(INDEX('Scoring Model'!$E$5:$E$7,MATCH(F20,'Scoring Model'!$D$5:$D$7,0)),0) -> 20 | Z20: =IFERROR(INDEX('Scoring Model'!$H$5:$H$13,MATCH(J20,'Scoring Model'!$G$5:$G$13,0)),0) -> 15 | AA20: =IF(L20>='Scoring Model'!$B$14,'Scoring Model'!$B$15,IF(L20>='Scoring Model'!$B$16,'Scoring Model'!$B$17,0)) -> 15 | AB20: =IF(SUMPRODUCT(--ISNUMBER(SEARCH('Scoring Model'!$D$16:$D$25,K20)))>0,'Scoring Model'!$B$18,0) -> 15 | AC20: =IF(SUMPRODUCT(--ISNUMBER(SEARCH('Scoring Model'!$G$16:$G$23,K20)))>0,'Scoring Model'!$B$19,0) -> 0 | AD20: =IF(W20="Likely Spam","",SUM(X20:AC20)) -> 80 | AE20: =IF(W20="Likely Spam","Spam",IF(AD20>='Scoring Model'!$B$21,"Hot",IF(AD20>='Scoring Model'!$B$22,"Warm","Nurture"))) -> Hot | AF20: =IF(W20="Likely Spam","Flagged by spam rules",TRIM(IF(X20>=20,"Strong source. ","")&IF(Y20>0,"Company email. ","")&IF(Z20>=15,"High-value product. ","")&IF(AA20>='Scoring Model'!$B$15,"High engagement. ","")&IF(AB20>0,"Buying intent in message. ","")&IF(AC20<0,"Negative intent in message. ",""))) -> Company email. High-value product. High engagement. Buying intent in message. | AG20: =IF(W20="Likely Spam","",1/(1+EXP(-('Conversion Model'!$B$5+IFERROR(INDEX('Conversion Model'!$B$8:$B$14,MATCH(C20,'Conversion Model'!$A$8:$A$14,0)),0)+IFERROR(INDEX('Conversion Model'!$E$8:$E$9,MATCH(F20,'Conversion Model'!$D$8:$D$9,0)),0)+IFERROR(INDEX('Conversion Model'!$H$8:$H$12,MATCH(IF(LEFT(J20,8)="Payments","Payments",IF(LEFT(J20,7)="Lending","Lending",J20)),'Conversion Model'!$G$8:$G$12,0)),0)+MIN(L20,15)*'Conversion Model'!$B$17+IF(SUMPRODUCT(--ISNUMBER(SEARCH('Scoring Model'!$D$16:$D$25,K20)))>0,'Conversion Model'!$B$18,0)+IF(SUMPRODUCT(--ISNUMBER(SEARCH('Scoring Model'!$G$16:$G$23,K20)))>0,'Conversion Model'!$B$19,0))))) -> 0.99839014 | AH20: =IF(OR(O20="Qualified",O20="Won",O20="Lost"),1,IF(O20="Unqualified",0,""))
A21: L-0020 | B21: 45940.399 | C21: LinkedIn ABM | D21: Noah Lee | E21: noah.lee@plumeridgesystems.example | F21: Company | G21: Plumeridge Systems | H21: https://plumeridgesystems.example | I21: Germany | J21: Banking Data API | K21: Evaluating card issuing providers for our BNPL app. Can we get a demo and a cost comparison? | L21: 5 | M21: 33.6 | N21: Vikram | O21: Won | P21: 96000 | Q21: =IF(F21="Disposable",1,0) -> 0 | R21: =IF(SUMPRODUCT(--ISNUMBER(SEARCH('Spam Rules'!$A$22:$A$35,K21)))>0,1,0) -> 0 | S21: =IF(AND(F21="Free",G21=""),1,0) -> 0 | T21: =IF(LEN(TRIM(K21))<15,1,0) -> 0 | U21: =IF(COUNTIF($E$2:$E$801,E21)>1,1,0) -> 0 | V21: =Q21*'Spam Rules'!$H$6+R21*'Spam Rules'!$H$7+S21*'Spam Rules'!$H$8+T21*'Spam Rules'!$H$9+U21*'Spam Rules'!$H$10 -> 0 | W21: =IF(V21>='Spam Rules'!$B$3,"Likely Spam","Genuine") -> Genuine | X21: =IFERROR(INDEX('Scoring Model'!$B$5:$B$11,MATCH(C21,'Scoring Model'!$A$5:$A$11,0)),0) -> 20 | Y21: =IFERROR(INDEX('Scoring Model'!$E$5:$E$7,MATCH(F21,'Scoring Model'!$D$5:$D$7,0)),0) -> 20 | Z21: =IFERROR(INDEX('Scoring Model'!$H$5:$H$13,MATCH(J21,'Scoring Model'!$G$5:$G$13,0)),0) -> 5 | AA21: =IF(L21>='Scoring Model'!$B$14,'Scoring Model'!$B$15,IF(L21>='Scoring Model'!$B$16,'Scoring Model'!$B$17,0)) -> 8 | AB21: =IF(SUMPRODUCT(--ISNUMBER(SEARCH('Scoring Model'!$D$16:$D$25,K21)))>0,'Scoring Model'!$B$18,0) -> 15 | AC21: =IF(SUMPRODUCT(--ISNUMBER(SEARCH('Scoring Model'!$G$16:$G$23,K21)))>0,'Scoring Model'!$B$19,0) -> 0 | AD21: =IF(W21="Likely Spam","",SUM(X21:AC21)) -> 68 | AE21: =IF(W21="Likely Spam","Spam",IF(AD21>='Scoring Model'!$B$21,"Hot",IF(AD21>='Scoring Model'!$B$22,"Warm","Nurture"))) -> Warm | AF21: =IF(W21="Likely Spam","Flagged by spam rules",TRIM(IF(X21>=20,"Strong source. ","")&IF(Y21>0,"Company email. ","")&IF(Z21>=15,"High-value product. ","")&IF(AA21>='Scoring Model'!$B$15,"High engagement. ","")&IF(AB21>0,"Buying intent in message. ","")&IF(AC21<0,"Negative intent in message. ",""))) -> Strong source. Company email. Buying intent in message. | AG21: =IF(W21="Likely Spam","",1/(1+EXP(-('Conversion Model'!$B$5+IFERROR(INDEX('Conversion Model'!$B$8:$B$14,MATCH(C21,'Conversion Model'!$A$8:$A$14,0)),0)+IFERROR(INDEX('Conversion Model'!$E$8:$E$9,MATCH(F21,'Conversion Model'!$D$8:$D$9,0)),0)+IFERROR(INDEX('Conversion Model'!$H$8:$H$12,MATCH(IF(LEFT(J21,8)="Payments","Payments",IF(LEFT(J21,7)="Lending","Lending",J21)),'Conversion Model'!$G$8:$G$12,0)),0)+MIN(L21,15)*'Conversion Model'!$B$17+IF(SUMPRODUCT(--ISNUMBER(SEARCH('Scoring Model'!$D$16:$D$25,K21)))>0,'Conversion Model'!$B$18,0)+IF(SUMPRODUCT(--ISNUMBER(SEARCH('Scoring Model'!$G$16:$G$23,K21)))>0,'Conversion Model'!$B$19,0))))) -> 0.8610454 | AH21: =IF(OR(O21="Qualified",O21="Won",O21="Lost"),1,IF(O21="Unqualified",0,"")) -> 1
A22: L-0021 | B22: 45940.549 | C22: Pricing Page Form | D22: Zara Kim | E22: zara.kim@plumeridgebank.example | F22: Company | G22: Plumeridge Bank | H22: https://plumeridgebank.example | I22: Nigeria | J22: Banking Data API | K22: Migrating from another provider for our card program, need a quote this month. | L22: 10 | M22: 6.8 | N22: Vikram | Q22: =IF(F22="Disposable",1,0) -> 0 | R22: =IF(SUMPRODUCT(--ISNUMBER(SEARCH('Spam Rules'!$A$22:$A$35,K22)))>0,1,0) -> 0 | S22: =IF(AND(F22="Free",G22=""),1,0) -> 0 | T22: =IF(LEN(TRIM(K22))<15,1,0) -> 0 | U22: =IF(COUNTIF($E$2:$E$801,E22)>1,1,0) -> 0 | V22: =Q22*'Spam Rules'!$H$6+R22*'Spam Rules'!$H$7+S22*'Spam Rules'!$H$8+T22*'Spam Rules'!$H$9+U22*'Spam Rules'!$H$10 -> 0 | W22: =IF(V22>='Spam Rules'!$B$3,"Likely Spam","Genuine") -> Genuine | X22: =IFERROR(INDEX('Scoring Model'!$B$5:$B$11,MATCH(C22,'Scoring Model'!$A$5:$A$11,0)),0) -> 25 | Y22: =IFERROR(INDEX('Scoring Model'!$E$5:$E$7,MATCH(F22,'Scoring Model'!$D$5:$D$7,0)),0) -> 20 | Z22: =IFERROR(INDEX('Scoring Model'!$H$5:$H$13,MATCH(J22,'Scoring Model'!$G$5:$G$13,0)),0) -> 5 | AA22: =IF(L22>='Scoring Model'!$B$14,'Scoring Model'!$B$15,IF(L22>='Scoring Model'!$B$16,'Scoring Model'!$B$17,0)) -> 15 | AB22: =IF(SUMPRODUCT(--ISNUMBER(SEARCH('Scoring Model'!$D$16:$D$25,K22)))>0,'Scoring Model'!$B$18,0) -> 15 | AC22: =IF(SUMPRODUCT(--ISNUMBER(SEARCH('Scoring Model'!$G$16:$G$23,K22)))>0,'Scoring Model'!$B$19,0) -> 0 | AD22: =IF(W22="Likely Spam","",SUM(X22:AC22)) -> 80 | AE22: =IF(W22="Likely Spam","Spam",IF(AD22>='Scoring Model'!$B$21,"Hot",IF(AD22>='Scoring Model'!$B$22,"Warm","Nurture"))) -> Hot | AF22: =IF(W22="Likely Spam","Flagged by spam rules",TRIM(IF(X22>=20,"Strong source. ","")&IF(Y22>0,"Company email. ","")&IF(Z22>=15,"High-value product. ","")&IF(AA22>='Scoring Model'!$B$15,"High engagement. ","")&IF(AB22>0,"Buying intent in message. ","")&IF(AC22<0,"Negative intent in message. ",""))) -> Strong source. Company email. High engagement. Buying intent in message. | AG22: =IF(W22="Likely Spam","",1/(1+EXP(-('Conversion Model'!$B$5+IFERROR(INDEX('Conversion Model'!$B$8:$B$14,MATCH(C22,'Conversion Model'!$A$8:$A$14,0)),0)+IFERROR(INDEX('Conversion Model'!$E$8:$E$9,MATCH(F22,'Conversion Model'!$D$8:$D$9,0)),0)+IFERROR(INDEX('Conversion Model'!$H$8:$H$12,MATCH(IF(LEFT(J22,8)="Payments","Payments",IF(LEFT(J22,7)="Lending","Lending",J22)),'Conversion Model'!$G$8:$G$12,0)),0)+MIN(L22,15)*'Conversion Model'!$B$17+IF(SUMPRODUCT(--ISNUMBER(SEARCH('Scoring Model'!$D$16:$D$25,K22)))>0,'Conversion Model'!$B$18,0)+IF(SUMPRODUCT(--ISNUMBER(SEARCH('Scoring Model'!$G$16:$G$23,K22)))>0,'Conversion Model'!$B$19,0))))) -> 0.99582726 | AH22: =IF(OR(O22="Qualified",O22="Won",O22="Lost"),1,IF(O22="Unqualified",0,""))
A23: L-0022 | B23: 45940.752 | C23: Pricing Page Form | D23: Sofia Berg | E23: sofia.berg@inboxly.example | F23: Free | I23: UAE | J23: Banking Data API | K23: Are you hiring fintech developers? Please share openings. | L23: 1 | M23: 10.9 | N23: Neha | O23: Unqualified | Q23: =IF(F23="Disposable",1,0) -> 0 | R23: =IF(SUMPRODUCT(--ISNUMBER(SEARCH('Spam Rules'!$A$22:$A$35,K23)))>0,1,0) -> 0 | S23: =IF(AND(F23="Free",G23=""),1,0) -> 1 | T23: =IF(LEN(TRIM(K23))<15,1,0) -> 0 | U23: =IF(COUNTIF($E$2:$E$801,E23)>1,1,0) -> 0 | V23: =Q23*'Spam Rules'!$H$6+R23*'Spam Rules'!$H$7+S23*'Spam Rules'!$H$8+T23*'Spam Rules'!$H$9+U23*'Spam Rules'!$H$10 -> 0 | W23: =IF(V23>='Spam Rules'!$B$3,"Likely Spam","Genuine") -> Genuine | X23: =IFERROR(INDEX('Scoring Model'!$B$5:$B$11,MATCH(C23,'Scoring Model'!$A$5:$A$11,0)),0) -> 25 | Y23: =IFERROR(INDEX('Scoring Model'!$E$5:$E$7,MATCH(F23,'Scoring Model'!$D$5:$D$7,0)),0) -> 0 | Z23: =IFERROR(INDEX('Scoring Model'!$H$5:$H$13,MATCH(J23,'Scoring Model'!$G$5:$G$13,0)),0) -> 5 | AA23: =IF(L23>='Scoring Model'!$B$14,'Scoring Model'!$B$15,IF(L23>='Scoring Model'!$B$16,'Scoring Model'!$B$17,0)) -> 0 | AB23: =IF(SUMPRODUCT(--ISNUMBER(SEARCH('Scoring Model'!$D$16:$D$25,K23)))>0,'Scoring Model'!$B$18,0) -> 0 | AC23: =IF(SUMPRODUCT(--ISNUMBER(SEARCH('Scoring Model'!$G$16:$G$23,K23)))>0,'Scoring Model'!$B$19,0) -> -30 | AD23: =IF(W23="Likely Spam","",SUM(X23:AC23)) -> 0 | AE23: =IF(W23="Likely Spam","Spam",IF(AD23>='Scoring Model'!$B$21,"Hot",IF(AD23>='Scoring Model'!$B$22,"Warm","Nurture"))) -> Nurture | AF23: =IF(W23="Likely Spam","Flagged by spam rules",TRIM(IF(X23>=20,"Strong source. ","")&IF(Y23>0,"Company email. ","")&IF(Z23>=15,"High-value product. ","")&IF(AA23>='Scoring Model'!$B$15,"High engagement. ","")&IF(AB23>0,"Buying intent in message. ","")&IF(AC23<0,"Negative intent in message. ",""))) -> Strong source. Negative intent in message. | AG23: =IF(W23="Likely Spam","",1/(1+EXP(-('Conversion Model'!$B$5+IFERROR(INDEX('Conversion Model'!$B$8:$B$14,MATCH(C23,'Conversion Model'!$A$8:$A$14,0)),0)+IFERROR(INDEX('Conversion Model'!$E$8:$E$9,MATCH(F23,'Conversion Model'!$D$8:$D$9,0)),0)+IFERROR(INDEX('Conversion Model'!$H$8:$H$12,MATCH(IF(LEFT(J23,8)="Payments","Payments",IF(LEFT(J23,7)="Lending","Lending",J23)),'Conversion Model'!$G$8:$G$12,0)),0)+MIN(L23,15)*'Conversion Model'!$B$17+IF(SUMPRODUCT(--ISNUMBER(SEARCH('Scoring Model'!$D$16:$D$25,K23)))>0,'Conversion Model'!$B$18,0)+IF(SUMPRODUCT(--ISNUMBER(SEARCH('Scoring Model'!$G$16:$G$23,K23)))>0,'Conversion Model'!$B$19,0))))) -> 0.002165362 | AH23: =IF(OR(O23="Qualified",O23="Won",O23="Lost"),1,IF(O23="Unqualified",0,"")) -> 0
A24: L-0023 | B24: 45940.789 | C24: LinkedIn ABM | D24: Noah Garcia | E24: noah.garcia@webmail.example | F24: Free | G24: Larkspindle Labs | I24: Brazil | J24: Lending - Credit Scoring | K24: We are launching a BNPL product and need a managed card issuing setup with go-live in Q4. | L24: 2 | M24: 88.4 | N24: Neha | O24: Unqualified | Q24: =IF(F24="Disposable",1,0) -> 0 | R24: =IF(SUMPRODUCT(--ISNUMBER(SEARCH('Spam Rules'!$A$22:$A$35,K24)))>0,1,0) -> 0 | S24: =IF(AND(F24="Free",G24=""),1,0) -> 0 | T24: =IF(LEN(TRIM(K24))<15,1,0) -> 0 | U24: =IF(COUNTIF($E$2:$E$801,E24)>1,1,0) -> 1 | V24: =Q24*'Spam Rules'!$H$6+R24*'Spam Rules'!$H$7+S24*'Spam Rules'!$H$8+T24*'Spam Rules'!$H$9+U24*'Spam Rules'!$H$10 -> 0 | W24: =IF(V24>='Spam Rules'!$B$3,"Likely Spam","Genuine") -> Genuine | X24: =IFERROR(INDEX('Scoring Model'!$B$5:$B$11,MATCH(C24,'Scoring Model'!$A$5:$A$11,0)),0) -> 20 | Y24: =IFERROR(INDEX('Scoring Model'!$E$5:$E$7,MATCH(F24,'Scoring Model'!$D$5:$D$7,0)),0) -> 0 | Z24: =IFERROR(INDEX('Scoring Model'!$H$5:$H$13,MATCH(J24,'Scoring Model'!$G$5:$G$13,0)),0) -> 15 | AA24: =IF(L24>='Scoring Model'!$B$14,'Scoring Model'!$B$15,IF(L24>='Scoring Model'!$B$16,'Scoring Model'!$B$17,0)) -> 0 | AB24: =IF(SUMPRODUCT(--ISNUMBER(SEARCH('Scoring Model'!$D$16:$D$25,K24)))>0,'Scoring Model'!$B$18,0) -> 15 | AC24: =IF(SUMPRODUCT(--ISNUMBER(SEARCH('Scoring Model'!$G$16:$G$23,K24)))>0,'Scoring Model'!$B$19,0) -> 0 | AD24: =IF(W24="Likely Spam","",SUM(X24:AC24)) -> 50 | AE24: =IF(W24="Likely Spam","Spam",IF(AD24>='Scoring Model'!$B$21,"Hot",IF(AD24>='Scoring Model'!$B$22,"Warm","Nurture"))) -> Warm | AF24: =IF(W24="Likely Spam","Flagged by spam rules",TRIM(IF(X24>=20,"Strong source. ","")&IF(Y24>0,"Company email. ","")&IF(Z24>=15,"High-value product. ","")&IF(AA24>='Scoring Model'!$B$15,"High engagement. ","")&IF(AB24>0,"Buying intent in message. ","")&IF(AC24<0,"Negative intent in message. ",""))) -> Strong source. High-value product. Buying intent in message. | AG24: =IF(W24="Likely Spam","",1/(1+EXP(-('Conversion Model'!$B$5+IFERROR(INDEX('Conversion Model'!$B$8:$B$14,MATCH(C24,'Conversion Model'!$A$8:$A$14,0)),0)+IFERROR(INDEX('Conversion Model'!$E$8:$E$9,MATCH(F24,'Conversion Model'!$D$8:$D$9,0)),0)+IFERROR(INDEX('Conversion Model'!$H$8:$H$12,MATCH(IF(LEFT(J24,8)="Payments","Payments",IF(LEFT(J24,7)="Lending","Lending",J24)),'Conversion Model'!$G$8:$G$12,0)),0)+MIN(L24,15)*'Conversion Model'!$B$17+IF(SUMPRODUCT(--ISNUMBER(SEARCH('Scoring Model'!$D$16:$D$25,K24)))>0,'Conversion Model'!$B$18,0)+IF(SUMPRODUCT(--ISNUMBER(SEARCH('Scoring Model'!$G$16:$G$23,K24)))>0,'Conversion Model'!$B$19,0))))) -> 0.33381066 | AH24: =IF(OR(O24="Qualified",O24="Won",O24="Lost"),1,IF(O24="Unqualified",0,"")) -> 0
A25: L-0024 | B25: 45943.288 | C25: Event | D25: Yuki Chen | E25: yuki.chen@quarrytidestudio.example | F25: Company | G25: Quarrytide Studio | H25: https://quarrytidestudio.example | I25: USA | J25: Payments - Cross-Border | K25: We are launching a remittance product and need a managed cross-border setup with go-live in Q2. | L25: 1 | M25: 11.9 | N25: Unassigned | O25: Open | Q25: =IF(F25="Disposable",1,0) -> 0 | R25: =IF(SUMPRODUCT(--ISNUMBER(SEARCH('Spam Rules'!$A$22:$A$35,K25)))>0,1,0) -> 0 | S25: =IF(AND(F25="Free",G25=""),1,0) -> 0 | T25: =IF(LEN(TRIM(K25))<15,1,0) -> 0 | U25: =IF(COUNTIF($E$2:$E$801,E25)>1,1,0) -> 0 | V25: =Q25*'Spam Rules'!$H$6+R25*'Spam Rules'!$H$7+S25*'Spam Rules'!$H$8+T25*'Spam Rules'!$H$9+U25*'Spam Rules'!$H$10 -> 0 | W25: =IF(V25>='Spam Rules'!$B$3,"Likely Spam","Genuine") -> Genuine | X25: =IFERROR(INDEX('Scoring Model'!$B$5:$B$11,MATCH(C25,'Scoring Model'!$A$5:$A$11,0)),0) -> 15 | Y25: =IFERROR(INDEX('Scoring Model'!$E$5:$E$7,MATCH(F25,'Scoring Model'!$D$5:$D$7,0)),0) -> 20 | Z25: =IFERROR(INDEX('Scoring Model'!$H$5:$H$13,MATCH(J25,'Scoring Model'!$G$5:$G$13,0)),0) -> 15 | AA25: =IF(L25>='Scoring Model'!$B$14,'Scoring Model'!$B$15,IF(L25>='Scoring Model'!$B$16,'Scoring Model'!$B$17,0)) -> 0 | AB25: =IF(SUMPRODUCT(--ISNUMBER(SEARCH('Scoring Model'!$D$16:$D$25,K25)))>0,'Scoring Model'!$B$18,0) -> 15 | AC25: =IF(SUMPRODUCT(--ISNUMBER(SEARCH('Scoring Model'!$G$16:$G$23,K25)))>0,'Scoring Model'!$B$19,0) -> 0 | AD25: =IF(W25="Likely Spam","",SUM(X25:AC25)) -> 65 | AE25: =IF(W25="Likely Spam","Spam",IF(AD25>='Scoring Model'!$B$21,"Hot",IF(AD25>='Scoring Model'!$B$22,"Warm","Nurture"))) -> Warm | AF25: =IF(W25="Likely Spam","Flagged by spam rules",TRIM(IF(X25>=20,"Strong source. ","")&IF(Y25>0,"Company email. ","")&IF(Z25>=15,"High-value product. ","")&IF(AA25>='Scoring Model'!$B$15,"High engagement. ","")&IF(AB25>0,"Buying intent in message. ","")&IF(AC25<0,"Negative intent in message. ",""))) -> Company email. High-value product. Buying intent in message. | AG25: =IF(W25="Likely Spam","",1/(1+EXP(-('Conversion Model'!$B$5+IFERROR(INDEX('Conversion Model'!$B$8:$B$14,MATCH(C25,'Conversion Model'!$A$8:$A$14,0)),0)+IFERROR(INDEX('Conversion Model'!$E$8:$E$9,MATCH(F25,'Conversion Model'!$D$8:$D$9,0)),0)+IFERROR(INDEX('Conversion Model'!$H$8:$H$12,MATCH(IF(LEFT(J25,8)="Payments","Payments",IF(LEFT(J25,7)="Lending","Lending",J25)),'Conversion Model'!$G$8:$G$12,0)),0)+MIN(L25,15)*'Conversion Model'!$B$17+IF(SUMPRODUCT(--ISNUMBER(SEARCH('Scoring Model'!$D$16:$D$25,K25)))>0,'Conversion Model'!$B$18,0)+IF(SUMPRODUCT(--ISNUMBER(SEARCH('Scoring Model'!$G$16:$G$23,K25)))>0,'Conversion Model'!$B$19,0))))) -> 0.083784774 | AH25: =IF(OR(O25="Qualified",O25="Won",O25="Lost"),1,IF(O25="Unqualified",0,""))
A26: L-0025 | B26: 45944.116 | C26: Chat Widget | D26: Sofia Muller | E26: sofia706@inboxly.example | F26: Free | I26: Germany | J26: KYC Verification | K26: Boost your Twitter followers and Telegram members, organic fintech marketing. | L26: 2 | N26: Rahul | O26: Spam | Q26: =IF(F26="Disposable",1,0) -> 0 | R26: =IF(SUMPRODUCT(--ISNUMBER(SEARCH('Spam Rules'!$A$22:$A$35,K26)))>0,1,0) -> 1 | S26: =IF(AND(F26="Free",G26=""),1,0) -> 1 | T26: =IF(LEN(TRIM(K26))<15,1,0) -> 0 | U26: =IF(COUNTIF($E$2:$E$801,E26)>1,1,0) -> 0 | V26: =Q26*'Spam Rules'!$H$6+R26*'Spam Rules'!$H$7+S26*'Spam Rules'!$H$8+T26*'Spam Rules'!$H$9+U26*'Spam Rules'!$H$10 -> 1 | W26: =IF(V26>='Spam Rules'!$B$3,"Likely Spam","Genuine") -> Likely Spam | X26: =IFERROR(INDEX('Scoring Model'!$B$5:$B$11,MATCH(C26,'Scoring Model'!$A$5:$A$11,0)),0) -> 0 | Y26: =IFERROR(INDEX('Scoring Model'!$E$5:$E$7,MATCH(F26,'Scoring Model'!$D$5:$D$7,0)),0) -> 0 | Z26: =IFERROR(INDEX('Scoring Model'!$H$5:$H$13,MATCH(J26,'Scoring Model'!$G$5:$G$13,0)),0) -> 5 | AA26: =IF(L26>='Scoring Model'!$B$14,'Scoring Model'!$B$15,IF(L26>='Scoring Model'!$B$16,'Scoring Model'!$B$17,0)) -> 0 | AB26: =IF(SUMPRODUCT(--ISNUMBER(SEARCH('Scoring Model'!$D$16:$D$25,K26)))>0,'Scoring Model'!$B$18,0) -> 0 | AC26: =IF(SUMPRODUCT(--ISNUMBER(SEARCH('Scoring Model'!$G$16:$G$23,K26)))>0,'Scoring Model'!$B$19,0) -> 0 | AD26: =IF(W26="Likely Spam","",SUM(X26:AC26)) | AE26: =IF(W26="Likely Spam","Spam",IF(AD26>='Scoring Model'!$B$21,"Hot",IF(AD26>='Scoring Model'!$B$22,"Warm","Nurture"))) -> Spam | AF26: =IF(W26="Likely Spam","Flagged by spam rules",TRIM(IF(X26>=20,"Strong source. ","")&IF(Y26>0,"Company email. ","")&IF(Z26>=15,"High-value product. ","")&IF(AA26>='Scoring Model'!$B$15,"High engagement. ","")&IF(AB26>0,"Buying intent in message. ","")&IF(AC26<0,"Negative intent in message. ",""))) -> Flagged by spam rules | AG26: =IF(W26="Likely Spam","",1/(1+EXP(-('Conversion Model'!$B$5+IFERROR(INDEX('Conversion Model'!$B$8:$B$14,MATCH(C26,'Conversion Model'!$A$8:$A$14,0)),0)+IFERROR(INDEX('Conversion Model'!$E$8:$E$9,MATCH(F26,'Conversion Model'!$D$8:$D$9,0)),0)+IFERROR(INDEX('Conversion Model'!$H$8:$H$12,MATCH(IF(LEFT(J26,8)="Payments","Payments",IF(LEFT(J26,7)="Lending","Lending",J26)),'Conversion Model'!$G$8:$G$12,0)),0)+MIN(L26,15)*'Conversion Model'!$B$17+IF(SUMPRODUCT(--ISNUMBER(SEARCH('Scoring Model'!$D$16:$D$25,K26)))>0,'Conversion Model'!$B$18,0)+IF(SUMPRODUCT(--ISNUMBER(SEARCH('Scoring Model'!$G$16:$G$23,K26)))>0,'Conversion Model'!$B$19,0))))) | AH26: =IF(OR(O26="Qualified",O26="Won",O26="Lost"),1,IF(O26="Unqualified",0,""))
A27: L-0026 | B27: 45944.906 | C27: Docs Signup | D27: Mateo Ivanova | E27: mateo.ivanova@dunmarrowcommerce.example | F27: Company | G27: Dunmarrow Commerce | H27: https://dunmarrowcommerce.example | I27: UK | J27: Banking Data API | K27: Interested in learning about fintech, where do I start? | L27: 2 | M27: 9.7 | N27: Unassigned | O27: Unqualified | Q27: =IF(F27="Disposable",1,0) -> 0 | R27: =IF(SUMPRODUCT(--ISNUMBER(SEARCH('Spam Rules'!$A$22:$A$35,K27)))>0,1,0) -> 0 | S27: =IF(AND(F27="Free",G27=""),1,0) -> 0 | T27: =IF(LEN(TRIM(K27))<15,1,0) -> 0 | U27: =IF(COUNTIF($E$2:$E$801,E27)>1,1,0) -> 0 | V27: =Q27*'Spam Rules'!$H$6+R27*'Spam Rules'!$H$7+S27*'Spam Rules'!$H$8+T27*'Spam Rules'!$H$9+U27*'Spam Rules'!$H$10 -> 0 | W27: =IF(V27>='Spam Rules'!$B$3,"Likely Spam","Genuine") -> Genuine | X27: =IFERROR(INDEX('Scoring Model'!$B$5:$B$11,MATCH(C27,'Scoring Model'!$A$5:$A$11,0)),0) -> 5 | Y27: =IFERROR(INDEX('Scoring Model'!$E$5:$E$7,MATCH(F27,'Scoring Model'!$D$5:$D$7,0)),0) -> 20 | Z27: =IFERROR(INDEX('Scoring Model'!$H$5:$H$13,MATCH(J27,'Scoring Model'!$G$5:$G$13,0)),0) -> 5 | AA27: =IF(L27>='Scoring Model'!$B$14,'Scoring Model'!$B$15,IF(L27>='Scoring Model'!$B$16,'Scoring Model'!$B$17,0)) -> 0 | AB27: =IF(SUMPRODUCT(--ISNUMBER(SEARCH('Scoring Model'!$D$16:$D$25,K27)))>0,'Scoring Model'!$B$18,0) -> 0 | AC27: =IF(SUMPRODUCT(--ISNUMBER(SEARCH('Scoring Model'!$G$16:$G$23,K27)))>0,'Scoring Model'!$B$19,0) -> -30 | AD27: =IF(W27="Likely Spam","",SUM(X27:AC27)) -> 0 | AE27: =IF(W27="Likely Spam","Spam",IF(AD27>='Scoring Model'!$B$21,"Hot",IF(AD27>='Scoring Model'!$B$22,"Warm","Nurture"))) -> Nurture | AF27: =IF(W27="Likely Spam","Flagged by spam rules",TRIM(IF(X27>=20,"Strong source. ","")&IF(Y27>0,"Company email. ","")&IF(Z27>=15,"High-value product. ","")&IF(AA27>='Scoring Model'!$B$15,"High engagement. ","")&IF(AB27>0,"Buying intent in message. ","")&IF(AC27<0,"Negative intent in message. ",""))) -> Company email. Negative intent in message. | AG27: =IF(W27="Likely Spam","",1/(1+EXP(-('Conversion Model'!$B$5+IFERROR(INDEX('Conversion Model'!$B$8:$B$14,MATCH(C27,'Conversion Model'!$A$8:$A$14,0)),0)+IFERROR(INDEX('Conversion Model'!$E$8:$E$9,MATCH(F27,'Conversion Model'!$D$8:$D$9,0)),0)+IFERROR(INDEX('Conversion Model'!$H$8:$H$12,MATCH(IF(LEFT(J27,8)="Payments","Payments",IF(LEFT(J27,7)="Lending","Lending",J27)),'Conversion Model'!$G$8:$G$12,0)),0)+MIN(L27,15)*'Conversion Model'!$B$17+IF(SUMPRODUCT(--ISNUMBER(SEARCH('Scoring Model'!$D$16:$D$25,K27)))>0,'Conversion Model'!$B$18,0)+IF(SUMPRODUCT(--ISNUMBER(SEARCH('Scoring Model'!$G$16:$G$23,K27)))>0,'Conversion Model'!$B$19,0))))) -> 0.0050716728 | AH27: =IF(OR(O27="Qualified",O27="Won",O27="Lost"),1,IF(O27="Unqualified",0,"")) -> 0
A28: L-0027 | B28: 45945.492 | C28: Event | D28: Daniel Khan | E28: daniel.khan@webmail.example | F28: Free | G28: Juniperholt Finance | I28: India | J28: Banking Data API | K28: Are you hiring fintech developers? Please share openings. | L28: 4 | M28: 22.5 | N28: Vikram | Q28: =IF(F28="Disposable",1,0) -> 0 | R28: =IF(SUMPRODUCT(--ISNUMBER(SEARCH('Spam Rules'!$A$22:$A$35,K28)))>0,1,0) -> 0 | S28: =IF(AND(F28="Free",G28=""),1,0) -> 0 | T28: =IF(LEN(TRIM(K28))<15,1,0) -> 0 | U28: =IF(COUNTIF($E$2:$E$801,E28)>1,1,0) -> 1 | V28: =Q28*'Spam Rules'!$H$6+R28*'Spam Rules'!$H$7+S28*'Spam Rules'!$H$8+T28*'Spam Rules'!$H$9+U28*'Spam Rules'!$H$10 -> 0 | W28: =IF(V28>='Spam Rules'!$B$3,"Likely Spam","Genuine") -> Genuine | X28: =IFERROR(INDEX('Scoring Model'!$B$5:$B$11,MATCH(C28,'Scoring Model'!$A$5:$A$11,0)),0) -> 15 | Y28: =IFERROR(INDEX('Scoring Model'!$E$5:$E$7,MATCH(F28,'Scoring Model'!$D$5:$D$7,0)),0) -> 0 | Z28: =IFERROR(INDEX('Scoring Model'!$H$5:$H$13,MATCH(J28,'Scoring Model'!$G$5:$G$13,0)),0) -> 5 | AA28: =IF(L28>='Scoring Model'!$B$14,'Scoring Model'!$B$15,IF(L28>='Scoring Model'!$B$16,'Scoring Model'!$B$17,0)) -> 8 | AB28: =IF(SUMPRODUCT(--ISNUMBER(SEARCH('Scoring Model'!$D$16:$D$25,K28)))>0,'Scoring Model'!$B$18,0) -> 0 | AC28: =IF(SUMPRODUCT(--ISNUMBER(SEARCH('Scoring Model'!$G$16:$G$23,K28)))>0,'Scoring Model'!$B$19,0) -> -30 | AD28: =IF(W28="Likely Spam","",SUM(X28:AC28)) -> -2 | AE28: =IF(W28="Likely Spam","Spam",IF(AD28>='Scoring Model'!$B$21,"Hot",IF(AD28>='Scoring Model'!$B$22,"Warm","Nurture"))) -> Nurture | AF28: =IF(W28="Likely Spam","Flagged by spam rules",TRIM(IF(X28>=20,"Strong source. ","")&IF(Y28>0,"Company email. ","")&IF(Z28>=15,"High-value product. ","")&IF(AA28>='Scoring Model'!$B$15,"High engagement. ","")&IF(AB28>0,"Buying intent in message. ","")&IF(AC28<0,"Negative intent in message. ",""))) -> Negative intent in message. | AG28: =IF(W28="Likely Spam","",1/(1+EXP(-('Conversion Model'!$B$5+IFERROR(INDEX('Conversion Model'!$B$8:$B$14,MATCH(C28,'Conversion Model'!$A$8:$A$14,0)),0)+IFERROR(INDEX('Conversion Model'!$E$8:$E$9,MATCH(F28,'Conversion Model'!$D$8:$D$9,0)),0)+IFERROR(INDEX('Conversion Model'!$H$8:$H$12,MATCH(IF(LEFT(J28,8)="Payments","Payments",IF(LEFT(J28,7)="Lending","Lending",J28)),'Conversion Model'!$G$8:$G$12,0)),0)+MIN(L28,15)*'Conversion Model'!$B$17+IF(SUMPRODUCT(--ISNUMBER(SEARCH('Scoring Model'!$D$16:$D$25,K28)))>0,'Conversion Model'!$B$18,0)+IF(SUMPRODUCT(--ISNUMBER(SEARCH('Scoring Model'!$G$16:$G$23,K28)))>0,'Conversion Model'!$B$19,0))))) -> 0.014585996 | AH28: =IF(OR(O28="Qualified",O28="Won",O28="Lost"),1,IF(O28="Unqualified",0,""))
A29: L-0028 | B29: 45945.637 | C29: Website Contact Form | D29: Mei Chen | E29: mei.chen@inboxly.example | F29: Free | G29: Orrowmere Bank | I29: Germany | J29: Other | K29: Can I use your API for a personal budget tracker? | L29: 1 | M29: 23.8 | N29: Neha | O29: Unqualified | Q29: =IF(F29="Disposable",1,0) -> 0 | R29: =IF(SUMPRODUCT(--ISNUMBER(SEARCH('Spam Rules'!$A$22:$A$35,K29)))>0,1,0) -> 0 | S29: =IF(AND(F29="Free",G29=""),1,0) -> 0 | T29: =IF(LEN(TRIM(K29))<15,1,0) -> 0 | U29: =IF(COUNTIF($E$2:$E$801,E29)>1,1,0) -> 0 | V29: =Q29*'Spam Rules'!$H$6+R29*'Spam Rules'!$H$7+S29*'Spam Rules'!$H$8+T29*'Spam Rules'!$H$9+U29*'Spam Rules'!$H$10 -> 0 | W29: =IF(V29>='Spam Rules'!$B$3,"Likely Spam","Genuine") -> Genuine | X29: =IFERROR(INDEX('Scoring Model'!$B$5:$B$11,MATCH(C29,'Scoring Model'!$A$5:$A$11,0)),0) -> 10 | Y29: =IFERROR(INDEX('Scoring Model'!$E$5:$E$7,MATCH(F29,'Scoring Model'!$D$5:$D$7,0)),0) -> 0 | Z29: =IFERROR(INDEX('Scoring Model'!$H$5:$H$13,MATCH(J29,'Scoring Model'!$G$5:$G$13,0)),0) -> 0 | AA29: =IF(L29>='Scoring Model'!$B$14,'Scoring Model'!$B$15,IF(L29>='Scoring Model'!$B$16,'Scoring Model'!$B$17,0)) -> 0 | AB29: =IF(SUMPRODUCT(--ISNUMBER(SEARCH('Scoring Model'!$D$16:$D$25,K29)))>0,'Scoring Model'!$B$18,0) -> 0 | AC29: =IF(SUMPRODUCT(--ISNUMBER(SEARCH('Scoring Model'!$G$16:$G$23,K29)))>0,'Scoring Model'!$B$19,0) -> -30 | AD29: =IF(W29="Likely Spam","",SUM(X29:AC29)) -> -20 | AE29: =IF(W29="Likely Spam","Spam",IF(AD29>='Scoring Model'!$B$21,"Hot",IF(AD29>='Scoring Model'!$B$22,"Warm","Nurture"))) -> Nurture | AF29: =IF(W29="Likely Spam","Flagged by spam rules",TRIM(IF(X29>=20,"Strong source. ","")&IF(Y29>0,"Company email. ","")&IF(Z29>=15,"High-value product. ","")&IF(AA29>='Scoring Model'!$B$15,"High engagement. ","")&IF(AB29>0,"Buying intent in message. ","")&IF(AC29<0,"Negative intent in message. ",""))) -> Negative intent in message. | AG29: =IF(W29="Likely Spam","",1/(1+EXP(-('Conversion Model'!$B$5+IFERROR(INDEX('Conversion Model'!$B$8:$B$14,MATCH(C29,'Conversion Model'!$A$8:$A$14,0)),0)+IFERROR(INDEX('Conversion Model'!$E$8:$E$9,MATCH(F29,'Conversion Model'!$D$8:$D$9,0)),0)+IFERROR(INDEX('Conversion Model'!$H$8:$H$12,MATCH(IF(LEFT(J29,8)="Payments","Payments",IF(LEFT(J29,7)="Lending","Lending",J29)),'Conversion Model'!$G$8:$G$12,0)),0)+MIN(L29,15)*'Conversion Model'!$B$17+IF(SUMPRODUCT(--ISNUMBER(SEARCH('Scoring Model'!$D$16:$D$25,K29)))>0,'Conversion Model'!$B$18,0)+IF(SUMPRODUCT(--ISNUMBER(SEARCH('Scoring Model'!$G$16:$G$23,K29)))>0,'Conversion Model'!$B$19,0))))) -> 0.00092758325 | AH29: =IF(OR(O29="Qualified",O29="Won",O29="Lost"),1,IF(O29="Unqualified",0,"")) -> 0
A30: L-0029 | B30: 45946.641 | C30: LinkedIn ABM | D30: Hana Berg | E30: hana.berg@sallowfennbank.example | F30: Company | G30: Sallowfenn Bank | H30: https://sallowfennbank.example | I30: Vietnam | J30: Payments - Virtual Accounts | K30: Our team is building a lending product for small businesses. Need help with sandbox setup and credit rules. Timeline 2 to 3 months. | L30: 4 | M30: 1 | N30: Unassigned | O30: Open | Q30: =IF(F30="Disposable",1,0) -> 0 | R30: =IF(SUMPRODUCT(--ISNUMBER(SEARCH('Spam Rules'!$A$22:$A$35,K30)))>0,1,0) -> 0 | S30: =IF(AND(F30="Free",G30=""),1,0) -> 0 | T30: =IF(LEN(TRIM(K30))<15,1,0) -> 0 | U30: =IF(COUNTIF($E$2:$E$801,E30)>1,1,0) -> 0 | V30: =Q30*'Spam Rules'!$H$6+R30*'Spam Rules'!$H$7+S30*'Spam Rules'!$H$8+T30*'Spam Rules'!$H$9+U30*'Spam Rules'!$H$10 -> 0 | W30: =IF(V30>='Spam Rules'!$B$3,"Likely Spam","Genuine") -> Genuine | X30: =IFERROR(INDEX('Scoring Model'!$B$5:$B$11,MATCH(C30,'Scoring Model'!$A$5:$A$11,0)),0) -> 20 | Y30: =IFERROR(INDEX('Scoring Model'!$E$5:$E$7,MATCH(F30,'Scoring Model'!$D$5:$D$7,0)),0) -> 20 | Z30: =IFERROR(INDEX('Scoring Model'!$H$5:$H$13,MATCH(J30,'Scoring Model'!$G$5:$G$13,0)),0) -> 15 | AA30: =IF(L30>='Scoring Model'!$B$14,'Scoring Model'!$B$15,IF(L30>='Scoring Model'!$B$16,'Scoring Model'!$B$17,0)) -> 8 | AB30: =IF(SUMPRODUCT(--ISNUMBER(SEARCH('Scoring Model'!$D$16:$D$25,K30)))>0,'Scoring Model'!$B$18,0) -> 15 | AC30: =IF(SUMPRODUCT(--ISNUMBER(SEARCH('Scoring Model'!$G$16:$G$23,K30)))>0,'Scoring Model'!$B$19,0) -> 0 | AD30: =IF(W30="Likely Spam","",SUM(X30:AC30)) -> 78 | AE30: =IF(W30="Likely Spam","Spam",IF(AD30>='Scoring Model'!$B$21,"Hot",IF(AD30>='Scoring Model'!$B$22,"Warm","Nurture"))) -> Hot | AF30: =IF(W30="Likely Spam","Flagged by spam rules",TRIM(IF(X30>=20,"Strong source. ","")&IF(Y30>0,"Company email. ","")&IF(Z30>=15,"High-value product. ","")&IF(AA30>='Scoring Model'!$B$15,"High engagement. ","")&IF(AB30>0,"Buying intent in message. ","")&IF(AC30<0,"Negative intent in message. ",""))) -> Strong source. Company email. High-value product. Buying intent in message. | AG30: =IF(W30="Likely Spam","",1/(1+EXP(-('Conversion Model'!$B$5+IFERROR(INDEX('Conversion Model'!$B$8:$B$14,MATCH(C30,'Conversion Model'!$A$8:$A$14,0)),0)+IFERROR(INDEX('Conversion Model'!$E$8:$E$9,MATCH(F30,'Conversion Model'!$D$8:$D$9,0)),0)+IFERROR(INDEX('Conversion Model'!$H$8:$H$12,MATCH(IF(LEFT(J30,8)="Payments","Payments",IF(LEFT(J30,7)="Lending","Lending",J30)),'Conversion Model'!$G$8:$G$12,0)),0)+MIN(L30,15)*'Conversion Model'!$B$17+IF(SUMPRODUCT(--ISNUMBER(SEARCH('Scoring Model'!$D$16:$D$25,K30)))>0,'Conversion Model'!$B$18,0)+IF(SUMPRODUCT(--ISNUMBER(SEARCH('Scoring Model'!$G$16:$G$23,K30)))>0,'Conversion Model'!$B$19,0))))) -> 0.70245168 | AH30: =IF(OR(O30="Qualified",O30="Won",O30="Lost"),1,IF(O30="Unqualified",0,""))
A31: L-0030 | B31: 45946.753 | C31: Pricing Page Form | D31: Marco Khan | E31: marco.khan@wyndlefossbank.example | F31: Company | G31: Wyndlefoss Bank | H31: https://wyndlefossbank.example | I31: Turkey | J31: KYC Verification | K31: Migrating from another provider for our card program, need a quote this month. | L31: 3 | M31: 18.7 | N31: Unassigned | O31: Lost | Q31: =IF(F31="Disposable",1,0) -> 0 | R31: =IF(SUMPRODUCT(--ISNUMBER(SEARCH('Spam Rules'!$A$22:$A$35,K31)))>0,1,0) -> 0 | S31: =IF(AND(F31="Free",G31=""),1,0) -> 0 | T31: =IF(LEN(TRIM(K31))<15,1,0) -> 0 | U31: =IF(COUNTIF($E$2:$E$801,E31)>1,1,0) -> 0 | V31: =Q31*'Spam Rules'!$H$6+R31*'Spam Rules'!$H$7+S31*'Spam Rules'!$H$8+T31*'Spam Rules'!$H$9+U31*'Spam Rules'!$H$10 -> 0 | W31: =IF(V31>='Spam Rules'!$B$3,"Likely Spam","Genuine") -> Genuine | X31: =IFERROR(INDEX('Scoring Model'!$B$5:$B$11,MATCH(C31,'Scoring Model'!$A$5:$A$11,0)),0) -> 25 | Y31: =IFERROR(INDEX('Scoring Model'!$E$5:$E$7,MATCH(F31,'Scoring Model'!$D$5:$D$7,0)),0) -> 20 | Z31: =IFERROR(INDEX('Scoring Model'!$H$5:$H$13,MATCH(J31,'Scoring Model'!$G$5:$G$13,0)),0) -> 5 | AA31: =IF(L31>='Scoring Model'!$B$14,'Scoring Model'!$B$15,IF(L31>='Scoring Model'!$B$16,'Scoring Model'!$B$17,0)) -> 0 | AB31: =IF(SUMPRODUCT(--ISNUMBER(SEARCH('Scoring Model'!$D$16:$D$25,K31)))>0,'Scoring Model'!$B$18,0) -> 15 | AC31: =IF(SUMPRODUCT(--ISNUMBER(SEARCH('Scoring Model'!$G$16:$G$23,K31)))>0,'Scoring Model'!$B$19,0) -> 0 | AD31: =IF(W31="Likely Spam","",SUM(X31:AC31)) -> 65 | AE31: =IF(W31="Likely Spam","Spam",IF(AD31>='Scoring Model'!$B$21,"Hot",IF(AD31>='Scoring Model'!$B$22,"Warm","Nurture"))) -> Warm | AF31: =IF(W31="Likely Spam","Flagged by spam rules",TRIM(IF(X31>=20,"Strong source. ","")&IF(Y31>0,"Company email. ","")&IF(Z31>=15,"High-value product. ","")&IF(AA31>='Scoring Model'!$B$15,"High engagement. ","")&IF(AB31>0,"Buying intent in message. ","")&IF(AC31<0,"Negative intent in message. ",""))) -> Strong source. Company email. Buying intent in message. | AG31: =IF(W31="Likely Spam","",1/(1+EXP(-('Conversion Model'!$B$5+IFERROR(INDEX('Conversion Model'!$B$8:$B$14,MATCH(C31,'Conversion Model'!$A$8:$A$14,0)),0)+IFERROR(INDEX('Conversion Model'!$E$8:$E$9,MATCH(F31,'Conversion Model'!$D$8:$D$9,0)),0)+IFERROR(INDEX('Conversion Model'!$H$8:$H$12,MATCH(IF(LEFT(J31,8)="Payments","Payments",IF(LEFT(J31,7)="Lending","Lending",J31)),'Conversion Model'!$G$8:$G$12,0)),0)+MIN(L31,15)*'Conversion Model'!$B$17+IF(SUMPRODUCT(--ISNUMBER(SEARCH('Scoring Model'!$D$16:$D$25,K31)))>0,'Conversion Model'!$B$18,0)+IF(SUMPRODUCT(--ISNUMBER(SEARCH('Scoring Model'!$G$16:$G$23,K31)))>0,'Conversion Model'!$B$19,0))))) -> 0.33447813 | AH31: =IF(OR(O31="Qualified",O31="Won",O31="Lost"),1,IF(O31="Unqualified",0,"")) -> 1
A32: L-0031 | B32: 45947.302 | C32: Website Contact Form | D32: Kenji Okafor | E32: kenji844@rankfarrowseoagency.example | F32: Company | G32: Rankfarrow SEO Agency | H32: https://rankfarrowseoagency.example | I32: Switzerland | J32: Payments - Card Issuing | K32: Exclusive investment opportunity with 300% returns, DM on telegram. | L32: 1 | N32: Vikram | Q32: =IF(F32="Disposable",1,0) -> 0 | R32: =IF(SUMPRODUCT(--ISNUMBER(SEARCH('Spam Rules'!$A$22:$A$35,K32)))>0,1,0) -> 1 | S32: =IF(AND(F32="Free",G32=""),1,0) -> 0 | T32: =IF(LEN(TRIM(K32))<15,1,0) -> 0 | U32: =IF(COUNTIF($E$2:$E$801,E32)>1,1,0) -> 0 | V32: =Q32*'Spam Rules'!$H$6+R32*'Spam Rules'!$H$7+S32*'Spam Rules'!$H$8+T32*'Spam Rules'!$H$9+U32*'Spam Rules'!$H$10 -> 1 | W32: =IF(V32>='Spam Rules'!$B$3,"Likely Spam","Genuine") -> Likely Spam | X32: =IFERROR(INDEX('Scoring Model'!$B$5:$B$11,MATCH(C32,'Scoring Model'!$A$5:$A$11,0)),0) -> 10 | Y32: =IFERROR(INDEX('Scoring Model'!$E$5:$E$7,MATCH(F32,'Scoring Model'!$D$5:$D$7,0)),0) -> 20 | Z32: =IFERROR(INDEX('Scoring Model'!$H$5:$H$13,MATCH(J32,'Scoring Model'!$G$5:$G$13,0)),0) -> 15 | AA32: =IF(L32>='Scoring Model'!$B$14,'Scoring Model'!$B$15,IF(L32>='Scoring Model'!$B$16,'Scoring Model'!$B$17,0)) -> 0 | AB32: =IF(SUMPRODUCT(--ISNUMBER(SEARCH('Scoring Model'!$D$16:$D$25,K32)))>0,'Scoring Model'!$B$18,0) -> 0 | AC32: =IF(SUMPRODUCT(--ISNUMBER(SEARCH('Scoring Model'!$G$16:$G$23,K32)))>0,'Scoring Model'!$B$19,0) -> 0 | AD32: =IF(W32="Likely Spam","",SUM(X32:AC32)) | AE32: =IF(W32="Likely Spam","Spam",IF(AD32>='Scoring Model'!$B$21,"Hot",IF(AD32>='Scoring Model'!$B$22,"Warm","Nurture"))) -> Spam | AF32: =IF(W32="Likely Spam","Flagged by spam rules",TRIM(IF(X32>=20,"Strong source. ","")&IF(Y32>0,"Company email. ","")&IF(Z32>=15,"High-value product. ","")&IF(AA32>='Scoring Model'!$B$15,"High engagement. ","")&IF(AB32>0,"Buying intent in message. ","")&IF(AC32<0,"Negative intent in message. ",""))) -> Flagged by spam rules | AG32: =IF(W32="Likely Spam","",1/(1+EXP(-('Conversion Model'!$B$5+IFERROR(INDEX('Conversion Model'!$B$8:$B$14,MATCH(C32,'Conversion Model'!$A$8:$A$14,0)),0)+IFERROR(INDEX('Conversion Model'!$E$8:$E$9,MATCH(F32,'Conversion Model'!$D$8:$D$9,0)),0)+IFERROR(INDEX('Conversion Model'!$H$8:$H$12,MATCH(IF(LEFT(J32,8)="Payments","Payments",IF(LEFT(J32,7)="Lending","Lending",J32)),'Conversion Model'!$G$8:$G$12,0)),0)+MIN(L32,15)*'Conversion Model'!$B$17+IF(SUMPRODUCT(--ISNUMBER(SEARCH('Scoring Model'!$D$16:$D$25,K32)))>0,'Conversion Model'!$B$18,0)+IF(SUMPRODUCT(--ISNUMBER(SEARCH('Scoring Model'!$G$16:$G$23,K32)))>0,'Conversion Model'!$B$19,0))))) | AH32: =IF(OR(O32="Qualified",O32="Won",O32="Lost"),1,IF(O32="Unqualified",0,""))
A33: L-0032 | B33: 45947.523 | C33: Website Contact Form | D33: Aisha Lee | E33: aisha.lee@nettlebriskmoney.example | F33: Company | G33: Nettlebrisk Money | H33: https://nettlebriskmoney.example | I33: India | J33: Lending - Loan Origination | K33: Evaluating card issuing providers for our loyalty app. Can we get a demo and a cost comparison? | L33: 2 | M33: 8.1 | N33: Vikram | Q33: =IF(F33="Disposable",1,0) -> 0 | R33: =IF(SUMPRODUCT(--ISNUMBER(SEARCH('Spam Rules'!$A$22:$A$35,K33)))>0,1,0) -> 0 | S33: =IF(AND(F33="Free",G33=""),1,0) -> 0 | T33: =IF(LEN(TRIM(K33))<15,1,0) -> 0 | U33: =IF(COUNTIF($E$2:$E$801,E33)>1,1,0) -> 0 | V33: =Q33*'Spam Rules'!$H$6+R33*'Spam Rules'!$H$7+S33*'Spam Rules'!$H$8+T33*'Spam Rules'!$H$9+U33*'Spam Rules'!$H$10 -> 0 | W33: =IF(V33>='Spam Rules'!$B$3,"Likely Spam","Genuine") -> Genuine | X33: =IFERROR(INDEX('Scoring Model'!$B$5:$B$11,MATCH(C33,'Scoring Model'!$A$5:$A$11,0)),0) -> 10 | Y33: =IFERROR(INDEX('Scoring Model'!$E$5:$E$7,MATCH(F33,'Scoring Model'!$D$5:$D$7,0)),0) -> 20 | Z33: =IFERROR(INDEX('Scoring Model'!$H$5:$H$13,MATCH(J33,'Scoring Model'!$G$5:$G$13,0)),0) -> 15 | AA33: =IF(L33>='Scoring Model'!$B$14,'Scoring Model'!$B$15,IF(L33>='Scoring Model'!$B$16,'Scoring Model'!$B$17,0)) -> 0 | AB33: =IF(SUMPRODUCT(--ISNUMBER(SEARCH('Scoring Model'!$D$16:$D$25,K33)))>0,'Scoring Model'!$B$18,0) -> 15 | AC33: =IF(SUMPRODUCT(--ISNUMBER(SEARCH('Scoring Model'!$G$16:$G$23,K33)))>0,'Scoring Model'!$B$19,0) -> 0 | AD33: =IF(W33="Likely Spam","",SUM(X33:AC33)) -> 60 | AE33: =IF(W33="Likely Spam","Spam",IF(AD33>='Scoring Model'!$B$21,"Hot",IF(AD33>='Scoring Model'!$B$22,"Warm","Nurture"))) -> Warm | AF33: =IF(W33="Likely Spam","Flagged by spam rules",TRIM(IF(X33>=20,"Strong source. ","")&IF(Y33>0,"Company email. ","")&IF(Z33>=15,"High-value product. ","")&IF(AA33>='Scoring Model'!$B$15,"High engagement. ","")&IF(AB33>0,"Buying intent in message. ","")&IF(AC33<0,"Negative intent in message. ",""))) -> Company email. High-value product. Buying intent in message. | AG33: =IF(W33="Likely Spam","",1/(1+EXP(-('Conversion Model'!$B$5+IFERROR(INDEX('Conversion Model'!$B$8:$B$14,MATCH(C33,'Conversion Model'!$A$8:$A$14,0)),0)+IFERROR(INDEX('Conversion Model'!$E$8:$E$9,MATCH(F33,'Conversion Model'!$D$8:$D$9,0)),0)+IFERROR(INDEX('Conversion Model'!$H$8:$H$12,MATCH(IF(LEFT(J33,8)="Payments","Payments",IF(LEFT(J33,7)="Lending","Lending",J33)),'Conversion Model'!$G$8:$G$12,0)),0)+MIN(L33,15)*'Conversion Model'!$B$17+IF(SUMPRODUCT(--ISNUMBER(SEARCH('Scoring Model'!$D$16:$D$25,K33)))>0,'Conversion Model'!$B$18,0)+IF(SUMPRODUCT(--ISNUMBER(SEARCH('Scoring Model'!$G$16:$G$23,K33)))>0,'Conversion Model'!$B$19,0))))) -> 0.33492348 | AH33: =IF(OR(O33="Qualified",O33="Won",O33="Lost"),1,IF(O33="Unqualified",0,""))
A34: L-0033 | B34: 45949.83 | C34: Docs Signup | D34: Lina Mehta | E34: lina.mehta@yarrowtunstudio.example | F34: Company | G34: Yarrowtun Studio | H34: https://yarrowtunstudio.example | I34: Nigeria | J34: KYC Verification | K34: Interested in learning about fintech, where do I start? | L34: 1 | M34: 13 | N34: Unassigned | Q34: =IF(F34="Disposable",1,0) -> 0 | R34: =IF(SUMPRODUCT(--ISNUMBER(SEARCH('Spam Rules'!$A$22:$A$35,K34)))>0,1,0) -> 0 | S34: =IF(AND(F34="Free",G34=""),1,0) -> 0 | T34: =IF(LEN(TRIM(K34))<15,1,0) -> 0 | U34: =IF(COUNTIF($E$2:$E$801,E34)>1,1,0) -> 0 | V34: =Q34*'Spam Rules'!$H$6+R34*'Spam Rules'!$H$7+S34*'Spam Rules'!$H$8+T34*'Spam Rules'!$H$9+U34*'Spam Rules'!$H$10 -> 0 | W34: =IF(V34>='Spam Rules'!$B$3,"Likely Spam","Genuine") -> Genuine | X34: =IFERROR(INDEX('Scoring Model'!$B$5:$B$11,MATCH(C34,'Scoring Model'!$A$5:$A$11,0)),0) -> 5 | Y34: =IFERROR(INDEX('Scoring Model'!$E$5:$E$7,MATCH(F34,'Scoring Model'!$D$5:$D$7,0)),0) -> 20 | Z34: =IFERROR(INDEX('Scoring Model'!$H$5:$H$13,MATCH(J34,'Scoring Model'!$G$5:$G$13,0)),0) -> 5 | AA34: =IF(L34>='Scoring Model'!$B$14,'Scoring Model'!$B$15,IF(L34>='Scoring Model'!$B$16,'Scoring Model'!$B$17,0)) -> 0 | AB34: =IF(SUMPRODUCT(--ISNUMBER(SEARCH('Scoring Model'!$D$16:$D$25,K34)))>0,'Scoring Model'!$B$18,0) -> 0 | AC34: =IF(SUMPRODUCT(--ISNUMBER(SEARCH('Scoring Model'!$G$16:$G$23,K34)))>0,'Scoring Model'!$B$19,0) -> -30 | AD34: =IF(W34="Likely Spam","",SUM(X34:AC34)) -> 0 | AE34: =IF(W34="Likely Spam","Spam",IF(AD34>='Scoring Model'!$B$21,"Hot",IF(AD34>='Scoring Model'!$B$22,"Warm","Nurture"))) -> Nurture | AF34: =IF(W34="Likely Spam","Flagged by spam rules",TRIM(IF(X34>=20,"Strong source. ","")&IF(Y34>0,"Company email. ","")&IF(Z34>=15,"High-value product. ","")&IF(AA34>='Scoring Model'!$B$15,"High engagement. ","")&IF(AB34>0,"Buying intent in message. ","")&IF(AC34<0,"Negative intent in message. ",""))) -> Company email. Negative intent in message. | AG34: =IF(W34="Likely Spam","",1/(1+EXP(-('Conversion Model'!$B$5+IFERROR(INDEX('Conversion Model'!$B$8:$B$14,MATCH(C34,'Conversion Model'!$A$8:$A$14,0)),0)+IFERROR(INDEX('Conversion Model'!$E$8:$E$9,MATCH(F34,'Conversion Model'!$D$8:$D$9,0)),0)+IFERROR(INDEX('Conversion Model'!$H$8:$H$12,MATCH(IF(LEFT(J34,8)="Payments","Payments",IF(LEFT(J34,7)="Lending","Lending",J34)),'Conversion Model'!$G$8:$G$12,0)),0)+MIN(L34,15)*'Conversion Model'!$B$17+IF(SUMPRODUCT(--ISNUMBER(SEARCH('Scoring Model'!$D$16:$D$25,K34)))>0,'Conversion Model'!$B$18,0)+IF(SUMPRODUCT(--ISNUMBER(SEARCH('Scoring Model'!$G$16:$G$23,K34)))>0,'Conversion Model'!$B$19,0))))) -> 0.0013184226 | AH34: =IF(OR(O34="Qualified",O34="Won",O34="Lost"),1,IF(O34="Unqualified",0,""))
A35: L-0034 | B35: 45950.283 | C35: Partner Referral | D35: Grace Berg | E35: grace.berg@dunmarrowcommerce.example | F35: Company | G35: Dunmarrow Commerce | H35: https://dunmarrowcommerce.example | I35: Japan | J35: Payments - Virtual Accounts | K35: Our team is building a lending product for small businesses. Need help with sandbox setup and credit rules. Timeline 2 to 3 months. | L35: 5 | M35: 19.8 | N35: Vikram | O35: Won | P35: 48000 | Q35: =IF(F35="Disposable",1,0) -> 0 | R35: =IF(SUMPRODUCT(--ISNUMBER(SEARCH('Spam Rules'!$A$22:$A$35,K35)))>0,1,0) -> 0 | S35: =IF(AND(F35="Free",G35=""),1,0) -> 0 | T35: =IF(LEN(TRIM(K35))<15,1,0) -> 0 | U35: =IF(COUNTIF($E$2:$E$801,E35)>1,1,0) -> 0 | V35: =Q35*'Spam Rules'!$H$6+R35*'Spam Rules'!$H$7+S35*'Spam Rules'!$H$8+T35*'Spam Rules'!$H$9+U35*'Spam Rules'!$H$10 -> 0 | W35: =IF(V35>='Spam Rules'!$B$3,"Likely Spam","Genuine") -> Genuine | X35: =IFERROR(INDEX('Scoring Model'!$B$5:$B$11,MATCH(C35,'Scoring Model'!$A$5:$A$11,0)),0) -> 30 | Y35: =IFERROR(INDEX('Scoring Model'!$E$5:$E$7,MATCH(F35,'Scoring Model'!$D$5:$D$7,0)),0) -> 20 | Z35: =IFERROR(INDEX('Scoring Model'!$H$5:$H$13,MATCH(J35,'Scoring Model'!$G$5:$G$13,0)),0) -> 15 | AA35: =IF(L35>='Scoring Model'!$B$14,'Scoring Model'!$B$15,IF(L35>='Scoring Model'!$B$16,'Scoring Model'!$B$17,0)) -> 8 | AB35: =IF(SUMPRODUCT(--ISNUMBER(SEARCH('Scoring Model'!$D$16:$D$25,K35)))>0,'Scoring Model'!$B$18,0) -> 15 | AC35: =IF(SUMPRODUCT(--ISNUMBER(SEARCH('Scoring Model'!$G$16:$G$23,K35)))>0,'Scoring Model'!$B$19,0) -> 0 | AD35: =IF(W35="Likely Spam","",SUM(X35:AC35)) -> 88 | AE35: =IF(W35="Likely Spam","Spam",IF(AD35>='Scoring Model'!$B$21,"Hot",IF(AD35>='Scoring Model'!$B$22,"Warm","Nurture"))) -> Hot | AF35: =IF(W35="Likely Spam","Flagged by spam rules",TRIM(IF(X35>=20,"Strong source. ","")&IF(Y35>0,"Company email. ","")&IF(Z35>=15,"High-value product. ","")&IF(AA35>='Scoring Model'!$B$15,"High engagement. ","")&IF(AB35>0,"Buying intent in message. ","")&IF(AC35<0,"Negative intent in message. ",""))) -> Strong source. Company email. High-value product. Buying intent in message. | AG35: =IF(W35="Likely Spam","",1/(1+EXP(-('Conversion Model'!$B$5+IFERROR(INDEX('Conversion Model'!$B$8:$B$14,MATCH(C35,'Conversion Model'!$A$8:$A$14,0)),0)+IFERROR(INDEX('Conversion Model'!$E$8:$E$9,MATCH(F35,'Conversion Model'!$D$8:$D$9,0)),0)+IFERROR(INDEX('Conversion Model'!$H$8:$H$12,MATCH(IF(LEFT(J35,8)="Payments","Payments",IF(LEFT(J35,7)="Lending","Lending",J35)),'Conversion Model'!$G$8:$G$12,0)),0)+MIN(L35,15)*'Conversion Model'!$B$17+IF(SUMPRODUCT(--ISNUMBER(SEARCH('Scoring Model'!$D$16:$D$25,K35)))>0,'Conversion Model'!$B$18,0)+IF(SUMPRODUCT(--ISNUMBER(SEARCH('Scoring Model'!$G$16:$G$23,K35)))>0,'Conversion Model'!$B$19,0))))) -> 0.87878772 | AH35: =IF(OR(O35="Qualified",O35="Won",O35="Lost"),1,IF(O35="Unqualified",0,"")) -> 1
A36: L-0035 | B36: 45950.527 | C36: Website Contact Form | D36: Lina Rossi | E36: lina.rossi@brindlewickcommerce.example | F36: Company | G36: Brindlewick Commerce | H36: https://brindlewickcommerce.example | I36: Canada | J36: Payments - Card Issuing | K36: Our team is building a lending product for small businesses. Need help with sandbox setup and credit rules. Timeline 2 to 3 months. | L36: 11 | M36: 112.4 | N36: Unassigned | Q36: =IF(F36="Disposable",1,0) -> 0 | R36: =IF(SUMPRODUCT(--ISNUMBER(SEARCH('Spam Rules'!$A$22:$A$35,K36)))>0,1,0) -> 0 | S36: =IF(AND(F36="Free",G36=""),1,0) -> 0 | T36: =IF(LEN(TRIM(K36))<15,1,0) -> 0 | U36: =IF(COUNTIF($E$2:$E$801,E36)>1,1,0) -> 0 | V36: =Q36*'Spam Rules'!$H$6+R36*'Spam Rules'!$H$7+S36*'Spam Rules'!$H$8+T36*'Spam Rules'!$H$9+U36*'Spam Rules'!$H$10 -> 0 | W36: =IF(V36>='Spam Rules'!$B$3,"Likely Spam","Genuine") -> Genuine | X36: =IFERROR(INDEX('Scoring Model'!$B$5:$B$11,MATCH(C36,'Scoring Model'!$A$5:$A$11,0)),0) -> 10 | Y36: =IFERROR(INDEX('Scoring Model'!$E$5:$E$7,MATCH(F36,'Scoring Model'!$D$5:$D$7,0)),0) -> 20 | Z36: =IFERROR(INDEX('Scoring Model'!$H$5:$H$13,MATCH(J36,'Scoring Model'!$G$5:$G$13,0)),0) -> 15 | AA36: =IF(L36>='Scoring Model'!$B$14,'Scoring Model'!$B$15,IF(L36>='Scoring Model'!$B$16,'Scoring Model'!$B$17,0)) -> 15 | AB36: =IF(SUMPRODUCT(--ISNUMBER(SEARCH('Scoring Model'!$D$16:$D$25,K36)))>0,'Scoring Model'!$B$18,0) -> 15 | AC36: =IF(SUMPRODUCT(--ISNUMBER(SEARCH('Scoring Model'!$G$16:$G$23,K36)))>0,'Scoring Model'!$B$19,0) -> 0 | AD36: =IF(W36="Likely Spam","",SUM(X36:AC36)) -> 75 | AE36: =IF(W36="Likely Spam","Spam",IF(AD36>='Scoring Model'!$B$21,"Hot",IF(AD36>='Scoring Model'!$B$22,"Warm","Nurture"))) -> Hot | AF36: =IF(W36="Likely Spam","Flagged by spam rules",TRIM(IF(X36>=20,"Strong source. ","")&IF(Y36>0,"Company email. ","")&IF(Z36>=15,"High-value product. ","")&IF(AA36>='Scoring Model'!$B$15,"High engagement. ","")&IF(AB36>0,"Buying intent in message. ","")&IF(AC36<0,"Negative intent in message. ",""))) -> Company email. High-value product. High engagement. Buying intent in message. | AG36: =IF(W36="Likely Spam","",1/(1+EXP(-('Conversion Model'!$B$5+IFERROR(INDEX('Conversion Model'!$B$8:$B$14,MATCH(C36,'Conversion Model'!$A$8:$A$14,0)),0)+IFERROR(INDEX('Conversion Model'!$E$8:$E$9,MATCH(F36,'Conversion Model'!$D$8:$D$9,0)),0)+IFERROR(INDEX('Conversion Model'!$H$8:$H$12,MATCH(IF(LEFT(J36,8)="Payments","Payments",IF(LEFT(J36,7)="Lending","Lending",J36)),'Conversion Model'!$G$8:$G$12,0)),0)+MIN(L36,15)*'Conversion Model'!$B$17+IF(SUMPRODUCT(--ISNUMBER(SEARCH('Scoring Model'!$D$16:$D$25,K36)))>0,'Conversion Model'!$B$18,0)+IF(SUMPRODUCT(--ISNUMBER(SEARCH('Scoring Model'!$G$16:$G$23,K36)))>0,'Conversion Model'!$B$19,0))))) -> 0.99630473 | AH36: =IF(OR(O36="Qualified",O36="Won",O36="Lost"),1,IF(O36="Unqualified",0,""))
A37: L-0036 | B37: 45951.025 | C37: Partner Referral | D37: Hana Khan | E37: hana.khan@yarrowtunmoney.example | F37: Company | G37: Yarrowtun Money | H37: https://yarrowtunmoney.example | I37: Japan | J37: Banking Data API | K37: Looking for pricing on KYC verification across 6 countries. Our current vendor keeps missing checks. | L37: 4 | M37: 2.3 | N37: Rahul | Q37: =IF(F37="Disposable",1,0) -> 0 | R37: =IF(SUMPRODUCT(--ISNUMBER(SEARCH('Spam Rules'!$A$22:$A$35,K37)))>0,1,0) -> 0 | S37: =IF(AND(F37="Free",G37=""),1,0) -> 0 | T37: =IF(LEN(TRIM(K37))<15,1,0) -> 0 | U37: =IF(COUNTIF($E$2:$E$801,E37)>1,1,0) -> 0 | V37: =Q37*'Spam Rules'!$H$6+R37*'Spam Rules'!$H$7+S37*'Spam Rules'!$H$8+T37*'Spam Rules'!$H$9+U37*'Spam Rules'!$H$10 -> 0 | W37: =IF(V37>='Spam Rules'!$B$3,"Likely Spam","Genuine") -> Genuine | X37: =IFERROR(INDEX('Scoring Model'!$B$5:$B$11,MATCH(C37,'Scoring Model'!$A$5:$A$11,0)),0) -> 30 | Y37: =IFERROR(INDEX('Scoring Model'!$E$5:$E$7,MATCH(F37,'Scoring Model'!$D$5:$D$7,0)),0) -> 20 | Z37: =IFERROR(INDEX('Scoring Model'!$H$5:$H$13,MATCH(J37,'Scoring Model'!$G$5:$G$13,0)),0) -> 5 | AA37: =IF(L37>='Scoring Model'!$B$14,'Scoring Model'!$B$15,IF(L37>='Scoring Model'!$B$16,'Scoring Model'!$B$17,0)) -> 8 | AB37: =IF(SUMPRODUCT(--ISNUMBER(SEARCH('Scoring Model'!$D$16:$D$25,K37)))>0,'Scoring Model'!$B$18,0) -> 15 | AC37: =IF(SUMPRODUCT(--ISNUMBER(SEARCH('Scoring Model'!$G$16:$G$23,K37)))>0,'Scoring Model'!$B$19,0) -> 0 | AD37: =IF(W37="Likely Spam","",SUM(X37:AC37)) -> 78 | AE37: =IF(W37="Likely Spam","Spam",IF(AD37>='Scoring Model'!$B$21,"Hot",IF(AD37>='Scoring Model'!$B$22,"Warm","Nurture"))) -> Hot | AF37: =IF(W37="Likely Spam","Flagged by spam rules",TRIM(IF(X37>=20,"Strong source. ","")&IF(Y37>0,"Company email. ","")&IF(Z37>=15,"High-value product. ","")&IF(AA37>='Scoring Model'!$B$15,"High engagement. ","")&IF(AB37>0,"Buying intent in message. ","")&IF(AC37<0,"Negative intent in message. ",""))) -> Strong source. Company email. Buying intent in message. | AG37: =IF(W37="Likely Spam","",1/(1+EXP(-('Conversion Model'!$B$5+IFERROR(INDEX('Conversion Model'!$B$8:$B$14,MATCH(C37,'Conversion Model'!$A$8:$A$14,0)),0)+IFERROR(INDEX('Conversion Model'!$E$8:$E$9,MATCH(F37,'Conversion Model'!$D$8:$D$9,0)),0)+IFERROR(INDEX('Conversion Model'!$H$8:$H$12,MATCH(IF(LEFT(J37,8)="Payments","Payments",IF(LEFT(J37,7)="Lending","Lending",J37)),'Conversion Model'!$G$8:$G$12,0)),0)+MIN(L37,15)*'Conversion Model'!$B$17+IF(SUMPRODUCT(--ISNUMBER(SEARCH('Scoring Model'!$D$16:$D$25,K37)))>0,'Conversion Model'!$B$18,0)+IF(SUMPRODUCT(--ISNUMBER(SEARCH('Scoring Model'!$G$16:$G$23,K37)))>0,'Conversion Model'!$B$19,0))))) -> 0.79281865 | AH37: =IF(OR(O37="Qualified",O37="Won",O37="Lost"),1,IF(O37="Unqualified",0,""))
A38: L-0037 | B38: 45951.474 | C38: Chat Widget | D38: Elena Garcia | E38: elena.garcia@inboxly.example | F38: Free | G38: Brindlewick Wallet | I38: Germany | J38: Payments - Payouts | K38: We are launching a loyalty product and need a managed payouts setup with go-live in Q1. | L38: 6 | M38: 14.5 | N38: Unassigned | Q38: =IF(F38="Disposable",1,0) -> 0 | R38: =IF(SUMPRODUCT(--ISNUMBER(SEARCH('Spam Rules'!$A$22:$A$35,K38)))>0,1,0) -> 0 | S38: =IF(AND(F38="Free",G38=""),1,0) -> 0 | T38: =IF(LEN(TRIM(K38))<15,1,0) -> 0 | U38: =IF(COUNTIF($E$2:$E$801,E38)>1,1,0) -> 0 | V38: =Q38*'Spam Rules'!$H$6+R38*'Spam Rules'!$H$7+S38*'Spam Rules'!$H$8+T38*'Spam Rules'!$H$9+U38*'Spam Rules'!$H$10 -> 0 | W38: =IF(V38>='Spam Rules'!$B$3,"Likely Spam","Genuine") -> Genuine | X38: =IFERROR(INDEX('Scoring Model'!$B$5:$B$11,MATCH(C38,'Scoring Model'!$A$5:$A$11,0)),0) -> 0 | Y38: =IFERROR(INDEX('Scoring Model'!$E$5:$E$7,MATCH(F38,'Scoring Model'!$D$5:$D$7,0)),0) -> 0 | Z38: =IFERROR(INDEX('Scoring Model'!$H$5:$H$13,MATCH(J38,'Scoring Model'!$G$5:$G$13,0)),0) -> 15 | AA38: =IF(L38>='Scoring Model'!$B$14,'Scoring Model'!$B$15,IF(L38>='Scoring Model'!$B$16,'Scoring Model'!$B$17,0)) -> 8 | AB38: =IF(SUMPRODUCT(--ISNUMBER(SEARCH('Scoring Model'!$D$16:$D$25,K38)))>0,'Scoring Model'!$B$18,0) -> 15 | AC38: =IF(SUMPRODUCT(--ISNUMBER(SEARCH('Scoring Model'!$G$16:$G$23,K38)))>0,'Scoring Model'!$B$19,0) -> 0 | AD38: =IF(W38="Likely Spam","",SUM(X38:AC38)) -> 38 | AE38: =IF(W38="Likely Spam","Spam",IF(AD38>='Scoring Model'!$B$21,"Hot",IF(AD38>='Scoring Model'!$B$22,"Warm","Nurture"))) -> Nurture | AF38: =IF(W38="Likely Spam","Flagged by spam rules",TRIM(IF(X38>=20,"Strong source. ","")&IF(Y38>0,"Company email. ","")&IF(Z38>=15,"High-value product. ","")&IF(AA38>='Scoring Model'!$B$15,"High engagement. ","")&IF(AB38>0,"Buying intent in message. ","")&IF(AC38<0,"Negative intent in message. ",""))) -> High-value product. Buying intent in message. | AG38: =IF(W38="Likely Spam","",1/(1+EXP(-('Conversion Model'!$B$5+IFERROR(INDEX('Conversion Model'!$B$8:$B$14,MATCH(C38,'Conversion Model'!$A$8:$A$14,0)),0)+IFERROR(INDEX('Conversion Model'!$E$8:$E$9,MATCH(F38,'Conversion Model'!$D$8:$D$9,0)),0)+IFERROR(INDEX('Conversion Model'!$H$8:$H$12,MATCH(IF(LEFT(J38,8)="Payments","Payments",IF(LEFT(J38,7)="Lending","Lending",J38)),'Conversion Model'!$G$8:$G$12,0)),0)+MIN(L38,15)*'Conversion Model'!$B$17+IF(SUMPRODUCT(--ISNUMBER(SEARCH('Scoring Model'!$D$16:$D$25,K38)))>0,'Conversion Model'!$B$18,0)+IF(SUMPRODUCT(--ISNUMBER(SEARCH('Scoring Model'!$G$16:$G$23,K38)))>0,'Conversion Model'!$B$19,0))))) -> 0.59748577 | AH38: =IF(OR(O38="Qualified",O38="Won",O38="Lost"),1,IF(O38="Unqualified",0,""))
A39: L-0038 | B39: 45951.599 | C39: Pricing Page Form | D39: Felix Okafor | E39: felix.okafor@webmail.example | F39: Free | G39: Tarnvale Commerce | I39: Japan | J39: Banking Data API | K39: Interested in learning about fintech, where do I start? | L39: 1 | M39: 0.9 | N39: Neha | O39: Unqualified | Q39: =IF(F39="Disposable",1,0) -> 0 | R39: =IF(SUMPRODUCT(--ISNUMBER(SEARCH('Spam Rules'!$A$22:$A$35,K39)))>0,1,0) -> 0 | S39: =IF(AND(F39="Free",G39=""),1,0) -> 0 | T39: =IF(LEN(TRIM(K39))<15,1,0) -> 0 | U39: =IF(COUNTIF($E$2:$E$801,E39)>1,1,0) -> 0 | V39: =Q39*'Spam Rules'!$H$6+R39*'Spam Rules'!$H$7+S39*'Spam Rules'!$H$8+T39*'Spam Rules'!$H$9+U39*'Spam Rules'!$H$10 -> 0 | W39: =IF(V39>='Spam Rules'!$B$3,"Likely Spam","Genuine") -> Genuine | X39: =IFERROR(INDEX('Scoring Model'!$B$5:$B$11,MATCH(C39,'Scoring Model'!$A$5:$A$11,0)),0) -> 25 | Y39: =IFERROR(INDEX('Scoring Model'!$E$5:$E$7,MATCH(F39,'Scoring Model'!$D$5:$D$7,0)),0) -> 0 | Z39: =IFERROR(INDEX('Scoring Model'!$H$5:$H$13,MATCH(J39,'Scoring Model'!$G$5:$G$13,0)),0) -> 5 | AA39: =IF(L39>='Scoring Model'!$B$14,'Scoring Model'!$B$15,IF(L39>='Scoring Model'!$B$16,'Scoring Model'!$B$17,0)) -> 0 | AB39: =IF(SUMPRODUCT(--ISNUMBER(SEARCH('Scoring Model'!$D$16:$D$25,K39)))>0,'Scoring Model'!$B$18,0) -> 0 | AC39: =IF(SUMPRODUCT(--ISNUMBER(SEARCH('Scoring Model'!$G$16:$G$23,K39)))>0,'Scoring Model'!$B$19,0) -> -30 | AD39: =IF(W39="Likely Spam","",SUM(X39:AC39)) -> 0 | AE39: =IF(W39="Likely Spam","Spam",IF(AD39>='Scoring Model'!$B$21,"Hot",IF(AD39>='Scoring Model'!$B$22,"Warm","Nurture"))) -> Nurture | AF39: =IF(W39="Likely Spam","Flagged by spam rules",TRIM(IF(X39>=20,"Strong source. ","")&IF(Y39>0,"Company email. ","")&IF(Z39>=15,"High-value product. ","")&IF(AA39>='Scoring Model'!$B$15,"High engagement. ","")&IF(AB39>0,"Buying intent in message. ","")&IF(AC39<0,"Negative intent in message. ",""))) -> Strong source. Negative intent in message. | AG39: =IF(W39="Likely Spam","",1/(1+EXP(-('Conversion Model'!$B$5+IFERROR(INDEX('Conversion Model'!$B$8:$B$14,MATCH(C39,'Conversion Model'!$A$8:$A$14,0)),0)+IFERROR(INDEX('Conversion Model'!$E$8:$E$9,MATCH(F39,'Conversion Model'!$D$8:$D$9,0)),0)+IFERROR(INDEX('Conversion Model'!$H$8:$H$12,MATCH(IF(LEFT(J39,8)="Payments","Payments",IF(LEFT(J39,7)="Lending","Lending",J39)),'Conversion Model'!$G$8:$G$12,0)),0)+MIN(L39,15)*'Conversion Model'!$B$17+IF(SUMPRODUCT(--ISNUMBER(SEARCH('Scoring Model'!$D$16:$D$25,K39)))>0,'Conversion Model'!$B$18,0)+IF(SUMPRODUCT(--ISNUMBER(SEARCH('Scoring Model'!$G$16:$G$23,K39)))>0,'Conversion Model'!$B$19,0))))) -> 0.002165362 | AH39: =IF(OR(O39="Qualified",O39="Won",O39="Lost"),1,IF(O39="Unqualified",0,"")) -> 0
A40: L-0039 | B40: 45951.694 | C40: Event | D40: Elena Costa | E40: elena.costa@freemail.example | F40: Free | G40: Glimmerfen Studio | I40: Turkey | J40: Banking Data API | K40: Interested in learning about fintech, where do I start? | L40: 3 | M40: 32.2 | N40: Neha | Q40: =IF(F40="Disposable",1,0) -> 0 | R40: =IF(SUMPRODUCT(--ISNUMBER(SEARCH('Spam Rules'!$A$22:$A$35,K40)))>0,1,0) -> 0 | S40: =IF(AND(F40="Free",G40=""),1,0) -> 0 | T40: =IF(LEN(TRIM(K40))<15,1,0) -> 0 | U40: =IF(COUNTIF($E$2:$E$801,E40)>1,1,0) -> 0 | V40: =Q40*'Spam Rules'!$H$6+R40*'Spam Rules'!$H$7+S40*'Spam Rules'!$H$8+T40*'Spam Rules'!$H$9+U40*'Spam Rules'!$H$10 -> 0 | W40: =IF(V40>='Spam Rules'!$B$3,"Likely Spam","Genuine") -> Genuine | X40: =IFERROR(INDEX('Scoring Model'!$B$5:$B$11,MATCH(C40,'Scoring Model'!$A$5:$A$11,0)),0) -> 15 | Y40: =IFERROR(INDEX('Scoring Model'!$E$5:$E$7,MATCH(F40,'Scoring Model'!$D$5:$D$7,0)),0) -> 0 | Z40: =IFERROR(INDEX('Scoring Model'!$H$5:$H$13,MATCH(J40,'Scoring Model'!$G$5:$G$13,0)),0) -> 5 | AA40: =IF(L40>='Scoring Model'!$B$14,'Scoring Model'!$B$15,IF(L40>='Scoring Model'!$B$16,'Scoring Model'!$B$17,0)) -> 0 | AB40: =IF(SUMPRODUCT(--ISNUMBER(SEARCH('Scoring Model'!$D$16:$D$25,K40)))>0,'Scoring Model'!$B$18,0) -> 0 | AC40: =IF(SUMPRODUCT(--ISNUMBER(SEARCH('Scoring Model'!$G$16:$G$23,K40)))>0,'Scoring Model'!$B$19,0) -> -30 | AD40: =IF(W40="Likely Spam","",SUM(X40:AC40)) -> -10 | AE40: =IF(W40="Likely Spam","Spam",IF(AD40>='Scoring Model'!$B$21,"Hot",IF(AD40>='Scoring Model'!$B$22,"Warm","Nurture"))) -> Nurture | AF40: =IF(W40="Likely Spam","Flagged by spam rules",TRIM(IF(X40>=20,"Strong source. ","")&IF(Y40>0,"Company email. ","")&IF(Z40>=15,"High-value product. ","")&IF(AA40>='Scoring Model'!$B$15,"High engagement. ","")&IF(AB40>0,"Buying intent in message. ","")&IF(AC40<0,"Negative intent in message. ",""))) -> Negative intent in message. | AG40: =IF(W40="Likely Spam","",1/(1+EXP(-('Conversion Model'!$B$5+IFERROR(INDEX('Conversion Model'!$B$8:$B$14,MATCH(C40,'Conversion Model'!$A$8:$A$14,0)),0)+IFERROR(INDEX('Conversion Model'!$E$8:$E$9,MATCH(F40,'Conversion Model'!$D$8:$D$9,0)),0)+IFERROR(INDEX('Conversion Model'!$H$8:$H$12,MATCH(IF(LEFT(J40,8)="Payments","Payments",IF(LEFT(J40,7)="Lending","Lending",J40)),'Conversion Model'!$G$8:$G$12,0)),0)+MIN(L40,15)*'Conversion Model'!$B$17+IF(SUMPRODUCT(--ISNUMBER(SEARCH('Scoring Model'!$D$16:$D$25,K40)))>0,'Conversion Model'!$B$18,0)+IF(SUMPRODUCT(--ISNUMBER(SEARCH('Scoring Model'!$G$16:$G$23,K40)))>0,'Conversion Model'!$B$19,0))))) -> 0.0065938644 | AH40: =IF(OR(O40="Qualified",O40="Won",O40="Lost"),1,IF(O40="Unqualified",0,""))
A41: L-0040 | B41: 45953.076 | C41: Website Contact Form | D41: Lucas Silva | E41: lucas.silva@larkspindlecommerce.example | F41: Company | G41: Larkspindle Commerce | H41: https://larkspindlecommerce.example | I41: Vietnam | J41: KYC Verification | K41: Migrating from another provider for our card program, need a quote this month. | L41: 6 | M41: 6.8 | N41: Vikram | O41: Unqualified | Q41: =IF(F41="Disposable",1,0) -> 0 | R41: =IF(SUMPRODUCT(--ISNUMBER(SEARCH('Spam Rules'!$A$22:$A$35,K41)))>0,1,0) -> 0 | S41: =IF(AND(F41="Free",G41=""),1,0) -> 0 | T41: =IF(LEN(TRIM(K41))<15,1,0) -> 0 | U41: =IF(COUNTIF($E$2:$E$801,E41)>1,1,0) -> 0 | V41: =Q41*'Spam Rules'!$H$6+R41*'Spam Rules'!$H$7+S41*'Spam Rules'!$H$8+T41*'Spam Rules'!$H$9+U41*'Spam Rules'!$H$10 -> 0 | W41: =IF(V41>='Spam Rules'!$B$3,"Likely Spam","Genuine") -> Genuine | X41: =IFERROR(INDEX('Scoring Model'!$B$5:$B$11,MATCH(C41,'Scoring Model'!$A$5:$A$11,0)),0) -> 10 | Y41: =IFERROR(INDEX('Scoring Model'!$E$5:$E$7,MATCH(F41,'Scoring Model'!$D$5:$D$7,0)),0) -> 20 | Z41: =IFERROR(INDEX('Scoring Model'!$H$5:$H$13,MATCH(J41,'Scoring Model'!$G$5:$G$13,0)),0) -> 5 | AA41: =IF(L41>='Scoring Model'!$B$14,'Scoring Model'!$B$15,IF(L41>='Scoring Model'!$B$16,'Scoring Model'!$B$17,0)) -> 8 | AB41: =IF(SUMPRODUCT(--ISNUMBER(SEARCH('Scoring Model'!$D$16:$D$25,K41)))>0,'Scoring Model'!$B$18,0) -> 15 | AC41: =IF(SUMPRODUCT(--ISNUMBER(SEARCH('Scoring Model'!$G$16:$G$23,K41)))>0,'Scoring Model'!$B$19,0) -> 0 | AD41: =IF(W41="Likely Spam","",SUM(X41:AC41)) -> 58 | AE41: =IF(W41="Likely Spam","Spam",IF(AD41>='Scoring Model'!$B$21,"Hot",IF(AD41>='Scoring Model'!$B$22,"Warm","Nurture"))) -> Warm | AF41: =IF(W41="Likely Spam","Flagged by spam rules",TRIM(IF(X41>=20,"Strong source. ","")&IF(Y41>0,"Company email. ","")&IF(Z41>=15,"High-value product. ","")&IF(AA41>='Scoring Model'!$B$15,"High engagement. ","")&IF(AB41>0,"Buying intent in message. ","")&IF(AC41<0,"Negative intent in message. ",""))) -> Company email. Buying intent in message. | AG41: =IF(W41="Likely Spam","",1/(1+EXP(-('Conversion Model'!$B$5+IFERROR(INDEX('Conversion Model'!$B$8:$B$14,MATCH(C41,'Conversion Model'!$A$8:$A$14,0)),0)+IFERROR(INDEX('Conversion Model'!$E$8:$E$9,MATCH(F41,'Conversion Model'!$D$8:$D$9,0)),0)+IFERROR(INDEX('Conversion Model'!$H$8:$H$12,MATCH(IF(LEFT(J41,8)="Payments","Payments",IF(LEFT(J41,7)="Lending","Lending",J41)),'Conversion Model'!$G$8:$G$12,0)),0)+MIN(L41,15)*'Conversion Model'!$B$17+IF(SUMPRODUCT(--ISNUMBER(SEARCH('Scoring Model'!$D$16:$D$25,K41)))>0,'Conversion Model'!$B$18,0)+IF(SUMPRODUCT(--ISNUMBER(SEARCH('Scoring Model'!$G$16:$G$23,K41)))>0,'Conversion Model'!$B$19,0))))) -> 0.76870263 | AH41: =IF(OR(O41="Qualified",O41="Won",O41="Lost"),1,IF(O41="Unqualified",0,"")) -> 0
A42: L-0041 | B42: 45953.289 | C42: Website Contact Form | D42: Omar Berg | E42: omar434@vanishmail.example | F42: Disposable | I42: Brazil | J42: KYC Verification | K42: hi | L42: 2 | N42: Rahul | O42: Spam | Q42: =IF(F42="Disposable",1,0) -> 1 | R42: =IF(SUMPRODUCT(--ISNUMBER(SEARCH('Spam Rules'!$A$22:$A$35,K42)))>0,1,0) -> 0 | S42: =IF(AND(F42="Free",G42=""),1,0) -> 0 | T42: =IF(LEN(TRIM(K42))<15,1,0) -> 1 | U42: =IF(COUNTIF($E$2:$E$801,E42)>1,1,0) -> 0 | V42: =Q42*'Spam Rules'!$H$6+R42*'Spam Rules'!$H$7+S42*'Spam Rules'!$H$8+T42*'Spam Rules'!$H$9+U42*'Spam Rules'!$H$10 -> 2 | W42: =IF(V42>='Spam Rules'!$B$3,"Likely Spam","Genuine") -> Likely Spam | X42: =IFERROR(INDEX('Scoring Model'!$B$5:$B$11,MATCH(C42,'Scoring Model'!$A$5:$A$11,0)),0) -> 10 | Y42: =IFERROR(INDEX('Scoring Model'!$E$5:$E$7,MATCH(F42,'Scoring Model'!$D$5:$D$7,0)),0) -> 0 | Z42: =IFERROR(INDEX('Scoring Model'!$H$5:$H$13,MATCH(J42,'Scoring Model'!$G$5:$G$13,0)),0) -> 5 | AA42: =IF(L42>='Scoring Model'!$B$14,'Scoring Model'!$B$15,IF(L42>='Scoring Model'!$B$16,'Scoring Model'!$B$17,0)) -> 0 | AB42: =IF(SUMPRODUCT(--ISNUMBER(SEARCH('Scoring Model'!$D$16:$D$25,K42)))>0,'Scoring Model'!$B$18,0) -> 0 | AC42: =IF(SUMPRODUCT(--ISNUMBER(SEARCH('Scoring Model'!$G$16:$G$23,K42)))>0,'Scoring Model'!$B$19,0) -> 0 | AD42: =IF(W42="Likely Spam","",SUM(X42:AC42)) | AE42: =IF(W42="Likely Spam","Spam",IF(AD42>='Scoring Model'!$B$21,"Hot",IF(AD42>='Scoring Model'!$B$22,"Warm","Nurture"))) -> Spam | AF42: =IF(W42="Likely Spam","Flagged by spam rules",TRIM(IF(X42>=20,"Strong source. ","")&IF(Y42>0,"Company email. ","")&IF(Z42>=15,"High-value product. ","")&IF(AA42>='Scoring Model'!$B$15,"High engagement. ","")&IF(AB42>0,"Buying intent in message. ","")&IF(AC42<0,"Negative intent in message. ",""))) -> Flagged by spam rules | AG42: =IF(W42="Likely Spam","",1/(1+EXP(-('Conversion Model'!$B$5+IFERROR(INDEX('Conversion Model'!$B$8:$B$14,MATCH(C42,'Conversion Model'!$A$8:$A$14,0)),0)+IFERROR(INDEX('Conversion Model'!$E$8:$E$9,MATCH(F42,'Conversion Model'!$D$8:$D$9,0)),0)+IFERROR(INDEX('Conversion Model'!$H$8:$H$12,MATCH(IF(LEFT(J42,8)="Payments","Payments",IF(LEFT(J42,7)="Lending","Lending",J42)),'Conversion Model'!$G$8:$G$12,0)),0)+MIN(L42,15)*'Conversion Model'!$B$17+IF(SUMPRODUCT(--ISNUMBER(SEARCH('Scoring Model'!$D$16:$D$25,K42)))>0,'Conversion Model'!$B$18,0)+IF(SUMPRODUCT(--ISNUMBER(SEARCH('Scoring Model'!$G$16:$G$23,K42)))>0,'Conversion Model'!$B$19,0))))) | AH42: =IF(OR(O42="Qualified",O42="Won",O42="Lost"),1,IF(O42="Unqualified",0,""))
A43: L-0042 | B43: 45953.617 | C43: LinkedIn ABM | D43: Priya Rossi | E43: priya.rossi@kestralithlabs.example | F43: Company | G43: Kestralith Labs | H43: https://kestralithlabs.example | I43: UAE | J43: KYC Verification | K43: Evaluating card issuing providers for our BNPL app. Can we get a demo and a cost comparison? | L43: 6 | M43: 10.8 | N43: Rahul | Q43: =IF(F43="Disposable",1,0) -> 0 | R43: =IF(SUMPRODUCT(--ISNUMBER(SEARCH('Spam Rules'!$A$22:$A$35,K43)))>0,1,0) -> 0 | S43: =IF(AND(F43="Free",G43=""),1,0) -> 0 | T43: =IF(LEN(TRIM(K43))<15,1,0) -> 0 | U43: =IF(COUNTIF($E$2:$E$801,E43)>1,1,0) -> 0 | V43: =Q43*'Spam Rules'!$H$6+R43*'Spam Rules'!$H$7+S43*'Spam Rules'!$H$8+T43*'Spam Rules'!$H$9+U43*'Spam Rules'!$H$10 -> 0 | W43: =IF(V43>='Spam Rules'!$B$3,"Likely Spam","Genuine") -> Genuine | X43: =IFERROR(INDEX('Scoring Model'!$B$5:$B$11,MATCH(C43,'Scoring Model'!$A$5:$A$11,0)),0) -> 20 | Y43: =IFERROR(INDEX('Scoring Model'!$E$5:$E$7,MATCH(F43,'Scoring Model'!$D$5:$D$7,0)),0) -> 20 | Z43: =IFERROR(INDEX('Scoring Model'!$H$5:$H$13,MATCH(J43,'Scoring Model'!$G$5:$G$13,0)),0) -> 5 | AA43: =IF(L43>='Scoring Model'!$B$14,'Scoring Model'!$B$15,IF(L43>='Scoring Model'!$B$16,'Scoring Model'!$B$17,0)) -> 8 | AB43: =IF(SUMPRODUCT(--ISNUMBER(SEARCH('Scoring Model'!$D$16:$D$25,K43)))>0,'Scoring Model'!$B$18,0) -> 15 | AC43: =IF(SUMPRODUCT(--ISNUMBER(SEARCH('Scoring Model'!$G$16:$G$23,K43)))>0,'Scoring Model'!$B$19,0) -> 0 | AD43: =IF(W43="Likely Spam","",SUM(X43:AC43)) -> 68 | AE43: =IF(W43="Likely Spam","Spam",IF(AD43>='Scoring Model'!$B$21,"Hot",IF(AD43>='Scoring Model'!$B$22,"Warm","Nurture"))) -> Warm | AF43: =IF(W43="Likely Spam","Flagged by spam rules",TRIM(IF(X43>=20,"Strong source. ","")&IF(Y43>0,"Company email. ","")&IF(Z43>=15,"High-value product. ","")&IF(AA43>='Scoring Model'!$B$15,"High engagement. ","")&IF(AB43>0,"Buying intent in message. ","")&IF(AC43<0,"Negative intent in message. ",""))) -> Strong source. Company email. Buying intent in message. | AG43: =IF(W43="Likely Spam","",1/(1+EXP(-('Conversion Model'!$B$5+IFERROR(INDEX('Conversion Model'!$B$8:$B$14,MATCH(C43,'Conversion Model'!$A$8:$A$14,0)),0)+IFERROR(INDEX('Conversion Model'!$E$8:$E$9,MATCH(F43,'Conversion Model'!$D$8:$D$9,0)),0)+IFERROR(INDEX('Conversion Model'!$H$8:$H$12,MATCH(IF(LEFT(J43,8)="Payments","Payments",IF(LEFT(J43,7)="Lending","Lending",J43)),'Conversion Model'!$G$8:$G$12,0)),0)+MIN(L43,15)*'Conversion Model'!$B$17+IF(SUMPRODUCT(--ISNUMBER(SEARCH('Scoring Model'!$D$16:$D$25,K43)))>0,'Conversion Model'!$B$18,0)+IF(SUMPRODUCT(--ISNUMBER(SEARCH('Scoring Model'!$G$16:$G$23,K43)))>0,'Conversion Model'!$B$19,0))))) -> 0.88864752 | AH43: =IF(OR(O43="Qualified",O43="Won",O43="Lost"),1,IF(O43="Unqualified",0,""))
A44: L-0043 | B44: 45954.43 | C44: Event | D44: Sofia Sharma | E44: sofia.sharma@quarrytidecommerce.example | F44: Company | G44: Quarrytide Commerce | H44: https://quarrytidecommerce.example | I44: India | J44: Payments - Card Issuing | K44: Interested in learning about fintech, where do I start? | L44: 3 | M44: 9.8 | N44: Rahul | O44: Unqualified | Q44: =IF(F44="Disposable",1,0) -> 0 | R44: =IF(SUMPRODUCT(--ISNUMBER(SEARCH('Spam Rules'!$A$22:$A$35,K44)))>0,1,0) -> 0 | S44: =IF(AND(F44="Free",G44=""),1,0) -> 0 | T44: =IF(LEN(TRIM(K44))<15,1,0) -> 0 | U44: =IF(COUNTIF($E$2:$E$801,E44)>1,1,0) -> 0 | V44: =Q44*'Spam Rules'!$H$6+R44*'Spam Rules'!$H$7+S44*'Spam Rules'!$H$8+T44*'Spam Rules'!$H$9+U44*'Spam Rules'!$H$10 -> 0 | W44: =IF(V44>='Spam Rules'!$B$3,"Likely Spam","Genuine") -> Genuine | X44: =IFERROR(INDEX('Scoring Model'!$B$5:$B$11,MATCH(C44,'Scoring Model'!$A$5:$A$11,0)),0) -> 15 | Y44: =IFERROR(INDEX('Scoring Model'!$E$5:$E$7,MATCH(F44,'Scoring Model'!$D$5:$D$7,0)),0) -> 20 | Z44: =IFERROR(INDEX('Scoring Model'!$H$5:$H$13,MATCH(J44,'Scoring Model'!$G$5:$G$13,0)),0) -> 15 | AA44: =IF(L44>='Scoring Model'!$B$14,'Scoring Model'!$B$15,IF(L44>='Scoring Model'!$B$16,'Scoring Model'!$B$17,0)) -> 0 | AB44: =IF(SUMPRODUCT(--ISNUMBER(SEARCH('Scoring Model'!$D$16:$D$25,K44)))>0,'Scoring Model'!$B$18,0) -> 0 | AC44: =IF(SUMPRODUCT(--ISNUMBER(SEARCH('Scoring Model'!$G$16:$G$23,K44)))>0,'Scoring Model'!$B$19,0) -> -30 | AD44: =IF(W44="Likely Spam","",SUM(X44:AC44)) -> 20 | AE44: =IF(W44="Likely Spam","Spam",IF(AD44>='Scoring Model'!$B$21,"Hot",IF(AD44>='Scoring Model'!$B$22,"Warm","Nurture"))) -> Nurture | AF44: =IF(W44="Likely Spam","Flagged by spam rules",TRIM(IF(X44>=20,"Strong source. ","")&IF(Y44>0,"Company email. ","")&IF(Z44>=15,"High-value product. ","")&IF(AA44>='Scoring Model'!$B$15,"High engagement. ","")&IF(AB44>0,"Buying intent in message. ","")&IF(AC44<0,"Negative intent in message. ",""))) -> Company email. High-value product. Negative intent in message. | AG44: =IF(W44="Likely Spam","",1/(1+EXP(-('Conversion Model'!$B$5+IFERROR(INDEX('Conversion Model'!$B$8:$B$14,MATCH(C44,'Conversion Model'!$A$8:$A$14,0)),0)+IFERROR(INDEX('Conversion Model'!$E$8:$E$9,MATCH(F44,'Conversion Model'!$D$8:$D$9,0)),0)+IFERROR(INDEX('Conversion Model'!$H$8:$H$12,MATCH(IF(LEFT(J44,8)="Payments","Payments",IF(LEFT(J44,7)="Lending","Lending",J44)),'Conversion Model'!$G$8:$G$12,0)),0)+MIN(L44,15)*'Conversion Model'!$B$17+IF(SUMPRODUCT(--ISNUMBER(SEARCH('Scoring Model'!$D$16:$D$25,K44)))>0,'Conversion Model'!$B$18,0)+IF(SUMPRODUCT(--ISNUMBER(SEARCH('Scoring Model'!$G$16:$G$23,K44)))>0,'Conversion Model'!$B$19,0))))) -> 0.013426599 | AH44: =IF(OR(O44="Qualified",O44="Won",O44="Lost"),1,IF(O44="Unqualified",0,"")) -> 0
A45: L-0044 | B45: 45955.441 | C45: Pricing Page Form | D45: Felix Berg | E45: felix.berg@plumeridgewallet.example | F45: Company | G45: Plumeridge Wallet | H45: https://plumeridgewallet.example | I45: Japan | J45: Payments - Card Issuing | K45: Evaluating card issuing providers for our marketplace app. Can we get a demo and a cost comparison? | L45: 5 | M45: 105.7 | N45: Rahul | Q45: =IF(F45="Disposable",1,0) -> 0 | R45: =IF(SUMPRODUCT(--ISNUMBER(SEARCH('Spam Rules'!$A$22:$A$35,K45)))>0,1,0) -> 0 | S45: =IF(AND(F45="Free",G45=""),1,0) -> 0 | T45: =IF(LEN(TRIM(K45))<15,1,0) -> 0 | U45: =IF(COUNTIF($E$2:$E$801,E45)>1,1,0) -> 0 | V45: =Q45*'Spam Rules'!$H$6+R45*'Spam Rules'!$H$7+S45*'Spam Rules'!$H$8+T45*'Spam Rules'!$H$9+U45*'Spam Rules'!$H$10 -> 0 | W45: =IF(V45>='Spam Rules'!$B$3,"Likely Spam","Genuine") -> Genuine | X45: =IFERROR(INDEX('Scoring Model'!$B$5:$B$11,MATCH(C45,'Scoring Model'!$A$5:$A$11,0)),0) -> 25 | Y45: =IFERROR(INDEX('Scoring Model'!$E$5:$E$7,MATCH(F45,'Scoring Model'!$D$5:$D$7,0)),0) -> 20 | Z45: =IFERROR(INDEX('Scoring Model'!$H$5:$H$13,MATCH(J45,'Scoring Model'!$G$5:$G$13,0)),0) -> 15 | AA45: =IF(L45>='Scoring Model'!$B$14,'Scoring Model'!$B$15,IF(L45>='Scoring Model'!$B$16,'Scoring Model'!$B$17,0)) -> 8 | AB45: =IF(SUMPRODUCT(--ISNUMBER(SEARCH('Scoring Model'!$D$16:$D$25,K45)))>0,'Scoring Model'!$B$18,0) -> 15 | AC45: =IF(SUMPRODUCT(--ISNUMBER(SEARCH('Scoring Model'!$G$16:$G$23,K45)))>0,'Scoring Model'!$B$19,0) -> 0 | AD45: =IF(W45="Likely Spam","",SUM(X45:AC45)) -> 83 | AE45: =IF(W45="Likely Spam","Spam",IF(AD45>='Scoring Model'!$B$21,"Hot",IF(AD45>='Scoring Model'!$B$22,"Warm","Nurture"))) -> Hot | AF45: =IF(W45="Likely Spam","Flagged by spam rules",TRIM(IF(X45>=20,"Strong source. ","")&IF(Y45>0,"Company email. ","")&IF(Z45>=15,"High-value product. ","")&IF(AA45>='Scoring Model'!$B$15,"High engagement. ","")&IF(AB45>0,"Buying intent in message. ","")&IF(AC45<0,"Negative intent in message. ",""))) -> Strong source. Company email. High-value product. Buying intent in message. | AG45: =IF(W45="Likely Spam","",1/(1+EXP(-('Conversion Model'!$B$5+IFERROR(INDEX('Conversion Model'!$B$8:$B$14,MATCH(C45,'Conversion Model'!$A$8:$A$14,0)),0)+IFERROR(INDEX('Conversion Model'!$E$8:$E$9,MATCH(F45,'Conversion Model'!$D$8:$D$9,0)),0)+IFERROR(INDEX('Conversion Model'!$H$8:$H$12,MATCH(IF(LEFT(J45,8)="Payments","Payments",IF(LEFT(J45,7)="Lending","Lending",J45)),'Conversion Model'!$G$8:$G$12,0)),0)+MIN(L45,15)*'Conversion Model'!$B$17+IF(SUMPRODUCT(--ISNUMBER(SEARCH('Scoring Model'!$D$16:$D$25,K45)))>0,'Conversion Model'!$B$18,0)+IF(SUMPRODUCT(--ISNUMBER(SEARCH('Scoring Model'!$G$16:$G$23,K45)))>0,'Conversion Model'!$B$19,0))))) -> 0.78617139 | AH45: =IF(OR(O45="Qualified",O45="Won",O45="Lost"),1,IF(O45="Unqualified",0,""))
A46: L-0045 | B46: 45955.642 | C46: Docs Signup | D46: Mei Sharma | E46: mei.sharma@kestralithcapital.example | F46: Company | G46: Kestralith Capital | H46: https://kestralithcapital.example | I46: Nigeria | J46: Payments - Payouts | K46: Evaluating payouts providers for our marketplace app. Can we get a demo and a cost comparison? | L46: 5 | M46: 35 | N46: Unassigned | O46: Unqualified | Q46: =IF(F46="Disposable",1,0) -> 0 | R46: =IF(SUMPRODUCT(--ISNUMBER(SEARCH('Spam Rules'!$A$22:$A$35,K46)))>0,1,0) -> 0 | S46: =IF(AND(F46="Free",G46=""),1,0) -> 0 | T46: =IF(LEN(TRIM(K46))<15,1,0) -> 0 | U46: =IF(COUNTIF($E$2:$E$801,E46)>1,1,0) -> 0 | V46: =Q46*'Spam Rules'!$H$6+R46*'Spam Rules'!$H$7+S46*'Spam Rules'!$H$8+T46*'Spam Rules'!$H$9+U46*'Spam Rules'!$H$10 -> 0 | W46: =IF(V46>='Spam Rules'!$B$3,"Likely Spam","Genuine") -> Genuine | X46: =IFERROR(INDEX('Scoring Model'!$B$5:$B$11,MATCH(C46,'Scoring Model'!$A$5:$A$11,0)),0) -> 5 | Y46: =IFERROR(INDEX('Scoring Model'!$E$5:$E$7,MATCH(F46,'Scoring Model'!$D$5:$D$7,0)),0) -> 20 | Z46: =IFERROR(INDEX('Scoring Model'!$H$5:$H$13,MATCH(J46,'Scoring Model'!$G$5:$G$13,0)),0) -> 15 | AA46: =IF(L46>='Scoring Model'!$B$14,'Scoring Model'!$B$15,IF(L46>='Scoring Model'!$B$16,'Scoring Model'!$B$17,0)) -> 8 | AB46: =IF(SUMPRODUCT(--ISNUMBER(SEARCH('Scoring Model'!$D$16:$D$25,K46)))>0,'Scoring Model'!$B$18,0) -> 15 | AC46: =IF(SUMPRODUCT(--ISNUMBER(SEARCH('Scoring Model'!$G$16:$G$23,K46)))>0,'Scoring Model'!$B$19,0) -> 0 | AD46: =IF(W46="Likely Spam","",SUM(X46:AC46)) -> 63 | AE46: =IF(W46="Likely Spam","Spam",IF(AD46>='Scoring Model'!$B$21,"Hot",IF(AD46>='Scoring Model'!$B$22,"Warm","Nurture"))) -> Warm | AF46: =IF(W46="Likely Spam","Flagged by spam rules",TRIM(IF(X46>=20,"Strong source. ","")&IF(Y46>0,"Company email. ","")&IF(Z46>=15,"High-value product. ","")&IF(AA46>='Scoring Model'!$B$15,"High engagement. ","")&IF(AB46>0,"Buying intent in message. ","")&IF(AC46<0,"Negative intent in message. ",""))) -> Company email. High-value product. Buying intent in message. | AG46: =IF(W46="Likely Spam","",1/(1+EXP(-('Conversion Model'!$B$5+IFERROR(INDEX('Conversion Model'!$B$8:$B$14,MATCH(C46,'Conversion Model'!$A$8:$A$14,0)),0)+IFERROR(INDEX('Conversion Model'!$E$8:$E$9,MATCH(F46,'Conversion Model'!$D$8:$D$9,0)),0)+IFERROR(INDEX('Conversion Model'!$H$8:$H$12,MATCH(IF(LEFT(J46,8)="Payments","Payments",IF(LEFT(J46,7)="Lending","Lending",J46)),'Conversion Model'!$G$8:$G$12,0)),0)+MIN(L46,15)*'Conversion Model'!$B$17+IF(SUMPRODUCT(--ISNUMBER(SEARCH('Scoring Model'!$D$16:$D$25,K46)))>0,'Conversion Model'!$B$18,0)+IF(SUMPRODUCT(--ISNUMBER(SEARCH('Scoring Model'!$G$16:$G$23,K46)))>0,'Conversion Model'!$B$19,0))))) -> 0.61609357 | AH46: =IF(OR(O46="Qualified",O46="Won",O46="Lost"),1,IF(O46="Unqualified",0,"")) -> 0
A47: L-0046 | B47: 45957.085 | C47: Website Contact Form | D47: Yuki Mehta | E47: yuki354@postbox.example | F47: Free | G47: Rankfarrow SEO Agency | I47: Japan | J47: Payments - Card Issuing | K47: Exclusive investment opportunity with 300% returns, DM on telegram. | L47: 2 | M47: 26.5 | N47: Rahul | Q47: =IF(F47="Disposable",1,0) -> 0 | R47: =IF(SUMPRODUCT(--ISNUMBER(SEARCH('Spam Rules'!$A$22:$A$35,K47)))>0,1,0) -> 1 | S47: =IF(AND(F47="Free",G47=""),1,0) -> 0 | T47: =IF(LEN(TRIM(K47))<15,1,0) -> 0 | U47: =IF(COUNTIF($E$2:$E$801,E47)>1,1,0) -> 0 | V47: =Q47*'Spam Rules'!$H$6+R47*'Spam Rules'!$H$7+S47*'Spam Rules'!$H$8+T47*'Spam Rules'!$H$9+U47*'Spam Rules'!$H$10 -> 1 | W47: =IF(V47>='Spam Rules'!$B$3,"Likely Spam","Genuine") -> Likely Spam | X47: =IFERROR(INDEX('Scoring Model'!$B$5:$B$11,MATCH(C47,'Scoring Model'!$A$5:$A$11,0)),0) -> 10 | Y47: =IFERROR(INDEX('Scoring Model'!$E$5:$E$7,MATCH(F47,'Scoring Model'!$D$5:$D$7,0)),0) -> 0 | Z47: =IFERROR(INDEX('Scoring Model'!$H$5:$H$13,MATCH(J47,'Scoring Model'!$G$5:$G$13,0)),0) -> 15 | AA47: =IF(L47>='Scoring Model'!$B$14,'Scoring Model'!$B$15,IF(L47>='Scoring Model'!$B$16,'Scoring Model'!$B$17,0)) -> 0 | AB47: =IF(SUMPRODUCT(--ISNUMBER(SEARCH('Scoring Model'!$D$16:$D$25,K47)))>0,'Scoring Model'!$B$18,0) -> 0 | AC47: =IF(SUMPRODUCT(--ISNUMBER(SEARCH('Scoring Model'!$G$16:$G$23,K47)))>0,'Scoring Model'!$B$19,0) -> 0 | AD47: =IF(W47="Likely Spam","",SUM(X47:AC47)) | AE47: =IF(W47="Likely Spam","Spam",IF(AD47>='Scoring Model'!$B$21,"Hot",IF(AD47>='Scoring Model'!$B$22,"Warm","Nurture"))) -> Spam | AF47: =IF(W47="Likely Spam","Flagged by spam rules",TRIM(IF(X47>=20,"Strong source. ","")&IF(Y47>0,"Company email. ","")&IF(Z47>=15,"High-value product. ","")&IF(AA47>='Scoring Model'!$B$15,"High engagement. ","")&IF(AB47>0,"Buying intent in message. ","")&IF(AC47<0,"Negative intent in message. ",""))) -> Flagged by spam rules | AG47: =IF(W47="Likely Spam","",1/(1+EXP(-('Conversion Model'!$B$5+IFERROR(INDEX('Conversion Model'!$B$8:$B$14,MATCH(C47,'Conversion Model'!$A$8:$A$14,0)),0)+IFERROR(INDEX('Conversion Model'!$E$8:$E$9,MATCH(F47,'Conversion Model'!$D$8:$D$9,0)),0)+IFERROR(INDEX('Conversion Model'!$H$8:$H$12,MATCH(IF(LEFT(J47,8)="Payments","Payments",IF(LEFT(J47,7)="Lending","Lending",J47)),'Conversion Model'!$G$8:$G$12,0)),0)+MIN(L47,15)*'Conversion Model'!$B$17+IF(SUMPRODUCT(--ISNUMBER(SEARCH('Scoring Model'!$D$16:$D$25,K47)))>0,'Conversion Model'!$B$18,0)+IF(SUMPRODUCT(--ISNUMBER(SEARCH('Scoring Model'!$G$16:$G$23,K47)))>0,'Conversion Model'!$B$19,0))))) | AH47: =IF(OR(O47="Qualified",O47="Won",O47="Lost"),1,IF(O47="Unqualified",0,""))
A48: L-0047 | B48: 45957.108 | C48: Website Contact Form | D48: Felix Chen | E48: felix.chen@freemail.example | F48: Free | G48: Juniperholt Pay | I48: Vietnam | J48: Payments - Cross-Border | K48: Evaluating cross-border providers for our BNPL app. Can we get a demo and a cost comparison? | L48: 1 | M48: 9.2 | N48: Unassigned | O48: Open | Q48: =IF(F48="Disposable",1,0) -> 0 | R48: =IF(SUMPRODUCT(--ISNUMBER(SEARCH('Spam Rules'!$A$22:$A$35,K48)))>0,1,0) -> 0 | S48: =IF(AND(F48="Free",G48=""),1,0) -> 0 | T48: =IF(LEN(TRIM(K48))<15,1,0) -> 0 | U48: =IF(COUNTIF($E$2:$E$801,E48)>1,1,0) -> 0 | V48: =Q48*'Spam Rules'!$H$6+R48*'Spam Rules'!$H$7+S48*'Spam Rules'!$H$8+T48*'Spam Rules'!$H$9+U48*'Spam Rules'!$H$10 -> 0 | W48: =IF(V48>='Spam Rules'!$B$3,"Likely Spam","Genuine") -> Genuine | X48: =IFERROR(INDEX('Scoring Model'!$B$5:$B$11,MATCH(C48,'Scoring Model'!$A$5:$A$11,0)),0) -> 10 | Y48: =IFERROR(INDEX('Scoring Model'!$E$5:$E$7,MATCH(F48,'Scoring Model'!$D$5:$D$7,0)),0) -> 0 | Z48: =IFERROR(INDEX('Scoring Model'!$H$5:$H$13,MATCH(J48,'Scoring Model'!$G$5:$G$13,0)),0) -> 15 | AA48: =IF(L48>='Scoring Model'!$B$14,'Scoring Model'!$B$15,IF(L48>='Scoring Model'!$B$16,'Scoring Model'!$B$17,0)) -> 0 | AB48: =IF(SUMPRODUCT(--ISNUMBER(SEARCH('Scoring Model'!$D$16:$D$25,K48)))>0,'Scoring Model'!$B$18,0) -> 15 | AC48: =IF(SUMPRODUCT(--ISNUMBER(SEARCH('Scoring Model'!$G$16:$G$23,K48)))>0,'Scoring Model'!$B$19,0) -> 0 | AD48: =IF(W48="Likely Spam","",SUM(X48:AC48)) -> 40 | AE48: =IF(W48="Likely Spam","Spam",IF(AD48>='Scoring Model'!$B$21,"Hot",IF(AD48>='Scoring Model'!$B$22,"Warm","Nurture"))) -> Nurture | AF48: =IF(W48="Likely Spam","Flagged by spam rules",TRIM(IF(X48>=20,"Strong source. ","")&IF(Y48>0,"Company email. ","")&IF(Z48>=15,"High-value product. ","")&IF(AA48>='Scoring Model'!$B$15,"High engagement. ","")&IF(AB48>0,"Buying intent in message. ","")&IF(AC48<0,"Negative intent in message. ",""))) -> High-value product. Buying intent in message. | AG48: =IF(W48="Likely Spam","",1/(1+EXP(-('Conversion Model'!$B$5+IFERROR(INDEX('Conversion Model'!$B$8:$B$14,MATCH(C48,'Conversion Model'!$A$8:$A$14,0)),0)+IFERROR(INDEX('Conversion Model'!$E$8:$E$9,MATCH(F48,'Conversion Model'!$D$8:$D$9,0)),0)+IFERROR(INDEX('Conversion Model'!$H$8:$H$12,MATCH(IF(LEFT(J48,8)="Payments","Payments",IF(LEFT(J48,7)="Lending","Lending",J48)),'Conversion Model'!$G$8:$G$12,0)),0)+MIN(L48,15)*'Conversion Model'!$B$17+IF(SUMPRODUCT(--ISNUMBER(SEARCH('Scoring Model'!$D$16:$D$25,K48)))>0,'Conversion Model'!$B$18,0)+IF(SUMPRODUCT(--ISNUMBER(SEARCH('Scoring Model'!$G$16:$G$23,K48)))>0,'Conversion Model'!$B$19,0))))) -> 0.03543422 | AH48: =IF(OR(O48="Qualified",O48="Won",O48="Lost"),1,IF(O48="Unqualified",0,""))
A49: L-0048 | B49: 45957.196 | C49: Docs Signup | D49: Mei Silva | E49: mei72@webmail.example | F49: Free | G49: Boostquill Media | I49: USA | J49: Other | K49: asdf qwer | L49: 1 | M49: 57 | N49: Vikram | Q49: =IF(F49="Disposable",1,0) -> 0 | R49: =IF(SUMPRODUCT(--ISNUMBER(SEARCH('Spam Rules'!$A$22:$A$35,K49)))>0,1,0) -> 0 | S49: =IF(AND(F49="Free",G49=""),1,0) -> 0 | T49: =IF(LEN(TRIM(K49))<15,1,0) -> 1 | U49: =IF(COUNTIF($E$2:$E$801,E49)>1,1,0) -> 0 | V49: =Q49*'Spam Rules'!$H$6+R49*'Spam Rules'!$H$7+S49*'Spam Rules'!$H$8+T49*'Spam Rules'!$H$9+U49*'Spam Rules'!$H$10 -> 1 | W49: =IF(V49>='Spam Rules'!$B$3,"Likely Spam","Genuine") -> Likely Spam | X49: =IFERROR(INDEX('Scoring Model'!$B$5:$B$11,MATCH(C49,'Scoring Model'!$A$5:$A$11,0)),0) -> 5 | Y49: =IFERROR(INDEX('Scoring Model'!$E$5:$E$7,MATCH(F49,'Scoring Model'!$D$5:$D$7,0)),0) -> 0 | Z49: =IFERROR(INDEX('Scoring Model'!$H$5:$H$13,MATCH(J49,'Scoring Model'!$G$5:$G$13,0)),0) -> 0 | AA49: =IF(L49>='Scoring Model'!$B$14,'Scoring Model'!$B$15,IF(L49>='Scoring Model'!$B$16,'Scoring Model'!$B$17,0)) -> 0 | AB49: =IF(SUMPRODUCT(--ISNUMBER(SEARCH('Scoring Model'!$D$16:$D$25,K49)))>0,'Scoring Model'!$B$18,0) -> 0 | AC49: =IF(SUMPRODUCT(--ISNUMBER(SEARCH('Scoring Model'!$G$16:$G$23,K49)))>0,'Scoring Model'!$B$19,0) -> 0 | AD49: =IF(W49="Likely Spam","",SUM(X49:AC49)) | AE49: =IF(W49="Likely Spam","Spam",IF(AD49>='Scoring Model'!$B$21,"Hot",IF(AD49>='Scoring Model'!$B$22,"Warm","Nurture"))) -> Spam | AF49: =IF(W49="Likely Spam","Flagged by spam rules",TRIM(IF(X49>=20,"Strong source. ","")&IF(Y49>0,"Company email. ","")&IF(Z49>=15,"High-value product. ","")&IF(AA49>='Scoring Model'!$B$15,"High engagement. ","")&IF(AB49>0,"Buying intent in message. ","")&IF(AC49<0,"Negative intent in message. ",""))) -> Flagged by spam rules | AG49: =IF(W49="Likely Spam","",1/(1+EXP(-('Conversion Model'!$B$5+IFERROR(INDEX('Conversion Model'!$B$8:$B$14,MATCH(C49,'Conversion Model'!$A$8:$A$14,0)),0)+IFERROR(INDEX('Conversion Model'!$E$8:$E$9,MATCH(F49,'Conversion Model'!$D$8:$D$9,0)),0)+IFERROR(INDEX('Conversion Model'!$H$8:$H$12,MATCH(IF(LEFT(J49,8)="Payments","Payments",IF(LEFT(J49,7)="Lending","Lending",J49)),'Conversion Model'!$G$8:$G$12,0)),0)+MIN(L49,15)*'Conversion Model'!$B$17+IF(SUMPRODUCT(--ISNUMBER(SEARCH('Scoring Model'!$D$16:$D$25,K49)))>0,'Conversion Model'!$B$18,0)+IF(SUMPRODUCT(--ISNUMBER(SEARCH('Scoring Model'!$G$16:$G$23,K49)))>0,'Conversion Model'!$B$19,0))))) | AH49: =IF(OR(O49="Qualified",O49="Won",O49="Lost"),1,IF(O49="Unqualified",0,""))
A50: L-0049 | B50: 45957.492 | C50: Event | D50: Tariq Okafor | E50: tariq.okafor@letterdrop.example | F50: Free | G50: Plumeridge Systems | I50: Nigeria | J50: Payments - Card Issuing | K50: Are you hiring fintech developers? Please share openings. | L50: 2 | M50: 15 | N50: Vikram | O50: Unqualified | Q50: =IF(F50="Disposable",1,0) -> 0 | R50: =IF(SUMPRODUCT(--ISNUMBER(SEARCH('Spam Rules'!$A$22:$A$35,K50)))>0,1,0) -> 0 | S50: =IF(AND(F50="Free",G50=""),1,0) -> 0 | T50: =IF(LEN(TRIM(K50))<15,1,0) -> 0 | U50: =IF(COUNTIF($E$2:$E$801,E50)>1,1,0) -> 0 | V50: =Q50*'Spam Rules'!$H$6+R50*'Spam Rules'!$H$7+S50*'Spam Rules'!$H$8+T50*'Spam Rules'!$H$9+U50*'Spam Rules'!$H$10 -> 0 | W50: =IF(V50>='Spam Rules'!$B$3,"Likely Spam","Genuine") -> Genuine | X50: =IFERROR(INDEX('Scoring Model'!$B$5:$B$11,MATCH(C50,'Scoring Model'!$A$5:$A$11,0)),0) -> 15 | Y50: =IFERROR(INDEX('Scoring Model'!$E$5:$E$7,MATCH(F50,'Scoring Model'!$D$5:$D$7,0)),0) -> 0 | Z50: =IFERROR(INDEX('Scoring Model'!$H$5:$H$13,MATCH(J50,'Scoring Model'!$G$5:$G$13,0)),0) -> 15 | AA50: =IF(L50>='Scoring Model'!$B$14,'Scoring Model'!$B$15,IF(L50>='Scoring Model'!$B$16,'Scoring Model'!$B$17,0)) -> 0 | AB50: =IF(SUMPRODUCT(--ISNUMBER(SEARCH('Scoring Model'!$D$16:$D$25,K50)))>0,'Scoring Model'!$B$18,0) -> 0 | AC50: =IF(SUMPRODUCT(--ISNUMBER(SEARCH('Scoring Model'!$G$16:$G$23,K50)))>0,'Scoring Model'!$B$19,0) -> -30 | AD50: =IF(W50="Likely Spam","",SUM(X50:AC50)) -> 0 | AE50: =IF(W50="Likely Spam","Spam",IF(AD50>='Scoring Model'!$B$21,"Hot",IF(AD50>='Scoring Model'!$B$22,"Warm","Nurture"))) -> Nurture | AF50: =IF(W50="Likely Spam","Flagged by spam rules",TRIM(IF(X50>=20,"Strong source. ","")&IF(Y50>0,"Company email. ","")&IF(Z50>=15,"High-value product. ","")&IF(AA50>='Scoring Model'!$B$15,"High engagement. ","")&IF(AB50>0,"Buying intent in message. ","")&IF(AC50<0,"Negative intent in message. ",""))) -> High-value product. Negative intent in message. | AG50: =IF(W50="Likely Spam","",1/(1+EXP(-('Conversion Model'!$B$5+IFERROR(INDEX('Conversion Model'!$B$8:$B$14,MATCH(C50,'Conversion Model'!$A$8:$A$14,0)),0)+IFERROR(INDEX('Conversion Model'!$E$8:$E$9,MATCH(F50,'Conversion Model'!$D$8:$D$9,0)),0)+IFERROR(INDEX('Conversion Model'!$H$8:$H$12,MATCH(IF(LEFT(J50,8)="Payments","Payments",IF(LEFT(J50,7)="Lending","Lending",J50)),'Conversion Model'!$G$8:$G$12,0)),0)+MIN(L50,15)*'Conversion Model'!$B$17+IF(SUMPRODUCT(--ISNUMBER(SEARCH('Scoring Model'!$D$16:$D$25,K50)))>0,'Conversion Model'!$B$18,0)+IF(SUMPRODUCT(--ISNUMBER(SEARCH('Scoring Model'!$G$16:$G$23,K50)))>0,'Conversion Model'!$B$19,0))))) -> 0.0025224475 | AH50: =IF(OR(O50="Qualified",O50="Won",O50="Lost"),1,IF(O50="Unqualified",0,"")) -> 0
A51: L-0050 | B51: 45959.039 | C51: Pricing Page Form | D51: Hana Mehta | E51: hana.mehta@thornlaceypay.example | F51: Company | G51: Thornlacey Pay | H51: https://thornlaceypay.example | I51: Vietnam | J51: Payments - Card Issuing | K51: Our team is building a lending product for small businesses. Need help with sandbox setup and credit rules. Timeline 2 to 3 months. | L51: 11 | M51: 24.2 | N51: Vikram | O51: Qualified | Q51: =IF(F51="Disposable",1,0) -> 0 | R51: =IF(SUMPRODUCT(--ISNUMBER(SEARCH('Spam Rules'!$A$22:$A$35,K51)))>0,1,0) -> 0 | S51: =IF(AND(F51="Free",G51=""),1,0) -> 0 | T51: =IF(LEN(TRIM(K51))<15,1,0) -> 0 | U51: =IF(COUNTIF($E$2:$E$801,E51)>1,1,0) -> 0 | V51: =Q51*'Spam Rules'!$H$6+R51*'Spam Rules'!$H$7+S51*'Spam Rules'!$H$8+T51*'Spam Rules'!$H$9+U51*'Spam Rules'!$H$10 -> 0 | W51: =IF(V51>='Spam Rules'!$B$3,"Likely Spam","Genuine") -> Genuine | X51: =IFERROR(INDEX('Scoring Model'!$B$5:$B$11,MATCH(C51,'Scoring Model'!$A$5:$A$11,0)),0) -> 25 | Y51: =IFERROR(INDEX('Scoring Model'!$E$5:$E$7,MATCH(F51,'Scoring Model'!$D$5:$D$7,0)),0) -> 20 | Z51: =IFERROR(INDEX('Scoring Model'!$H$5:$H$13,MATCH(J51,'Scoring Model'!$G$5:$G$13,0)),0) -> 15 | AA51: =IF(L51>='Scoring Model'!$B$14,'Scoring Model'!$B$15,IF(L51>='Scoring Model'!$B$16,'Scoring Model'!$B$17,0)) -> 15 | AB51: =IF(SUMPRODUCT(--ISNUMBER(SEARCH('Scoring Model'!$D$16:$D$25,K51)))>0,'Scoring Model'!$B$18,0) -> 15 | AC51: =IF(SUMPRODUCT(--ISNUMBER(SEARCH('Scoring Model'!$G$16:$G$23,K51)))>0,'Scoring Model'!$B$19,0) -> 0 | AD51: =IF(W51="Likely Spam","",SUM(X51:AC51)) -> 90 | AE51: =IF(W51="Likely Spam","Spam",IF(AD51>='Scoring Model'!$B$21,"Hot",IF(AD51>='Scoring Model'!$B$22,"Warm","Nurture"))) -> Hot | AF51: =IF(W51="Likely Spam","Flagged by spam rules",TRIM(IF(X51>=20,"Strong source. ","")&IF(Y51>0,"Company email. ","")&IF(Z51>=15,"High-value product. ","")&IF(AA51>='Scoring Model'!$B$15,"High engagement. ","")&IF(AB51>0,"Buying intent in message. ","")&IF(AC51<0,"Negative intent in message. ",""))) -> Strong source. Company email. High-value product. High engagement. Buying intent in message. | AG51: =IF(W51="Likely Spam","",1/(1+EXP(-('Conversion Model'!$B$5+IFERROR(INDEX('Conversion Model'!$B$8:$B$14,MATCH(C51,'Conversion Model'!$A$8:$A$14,0)),0)+IFERROR(INDEX('Conversion Model'!$E$8:$E$9,MATCH(F51,'Conversion Model'!$D$8:$D$9,0)),0)+IFERROR(INDEX('Conversion Model'!$H$8:$H$12,MATCH(IF(LEFT(J51,8)="Payments","Payments",IF(LEFT(J51,7)="Lending","Lending",J51)),'Conversion Model'!$G$8:$G$12,0)),0)+MIN(L51,15)*'Conversion Model'!$B$17+IF(SUMPRODUCT(--ISNUMBER(SEARCH('Scoring Model'!$D$16:$D$25,K51)))>0,'Conversion Model'!$B$18,0)+IF(SUMPRODUCT(--ISNUMBER(SEARCH('Scoring Model'!$G$16:$G$23,K51)))>0,'Conversion Model'!$B$19,0))))) -> 0.99779319 | AH51: =IF(OR(O51="Qualified",O51="Won",O51="Lost"),1,IF(O51="Unqualified",0,"")) -> 1
A52: L-0051 | B52: 45959.072 | C52: Website Contact Form | D52: Tariq Okafor | E52: tariq566@rankfarrowseoagency.example | F52: Company | G52: Rankfarrow SEO Agency | H52: https://rankfarrowseoagency.example | I52: South Korea | J52: Other | K52: asdf qwer | L52: 1 | M52: 47.4 | N52: Rahul | Q52: =IF(F52="Disposable",1,0) -> 0 | R52: =IF(SUMPRODUCT(--ISNUMBER(SEARCH('Spam Rules'!$A$22:$A$35,K52)))>0,1,0) -> 0 | S52: =IF(AND(F52="Free",G52=""),1,0) -> 0 | T52: =IF(LEN(TRIM(K52))<15,1,0) -> 1 | U52: =IF(COUNTIF($E$2:$E$801,E52)>1,1,0) -> 0 | V52: =Q52*'Spam Rules'!$H$6+R52*'Spam Rules'!$H$7+S52*'Spam Rules'!$H$8+T52*'Spam Rules'!$H$9+U52*'Spam Rules'!$H$10 -> 1 | W52: =IF(V52>='Spam Rules'!$B$3,"Likely Spam","Genuine") -> Likely Spam | X52: =IFERROR(INDEX('Scoring Model'!$B$5:$B$11,MATCH(C52,'Scoring Model'!$A$5:$A$11,0)),0) -> 10 | Y52: =IFERROR(INDEX('Scoring Model'!$E$5:$E$7,MATCH(F52,'Scoring Model'!$D$5:$D$7,0)),0) -> 20 | Z52: =IFERROR(INDEX('Scoring Model'!$H$5:$H$13,MATCH(J52,'Scoring Model'!$G$5:$G$13,0)),0) -> 0 | AA52: =IF(L52>='Scoring Model'!$B$14,'Scoring Model'!$B$15,IF(L52>='Scoring Model'!$B$16,'Scoring Model'!$B$17,0)) -> 0 | AB52: =IF(SUMPRODUCT(--ISNUMBER(SEARCH('Scoring Model'!$D$16:$D$25,K52)))>0,'Scoring Model'!$B$18,0) -> 0 | AC52: =IF(SUMPRODUCT(--ISNUMBER(SEARCH('Scoring Model'!$G$16:$G$23,K52)))>0,'Scoring Model'!$B$19,0) -> 0 | AD52: =IF(W52="Likely Spam","",SUM(X52:AC52)) | AE52: =IF(W52="Likely Spam","Spam",IF(AD52>='Scoring Model'!$B$21,"Hot",IF(AD52>='Scoring Model'!$B$22,"Warm","Nurture"))) -> Spam | AF52: =IF(W52="Likely Spam","Flagged by spam rules",TRIM(IF(X52>=20,"Strong source. ","")&IF(Y52>0,"Company email. ","")&IF(Z52>=15,"High-value product. ","")&IF(AA52>='Scoring Model'!$B$15,"High engagement. ","")&IF(AB52>0,"Buying intent in message. ","")&IF(AC52<0,"Negative intent in message. ",""))) -> Flagged by spam rules | AG52: =IF(W52="Likely Spam","",1/(1+EXP(-('Conversion Model'!$B$5+IFERROR(INDEX('Conversion Model'!$B$8:$B$14,MATCH(C52,'Conversion Model'!$A$8:$A$14,0)),0)+IFERROR(INDEX('Conversion Model'!$E$8:$E$9,MATCH(F52,'Conversion Model'!$D$8:$D$9,0)),0)+IFERROR(INDEX('Conversion Model'!$H$8:$H$12,MATCH(IF(LEFT(J52,8)="Payments","Payments",IF(LEFT(J52,7)="Lending","Lending",J52)),'Conversion Model'!$G$8:$G$12,0)),0)+MIN(L52,15)*'Conversion Model'!$B$17+IF(SUMPRODUCT(--ISNUMBER(SEARCH('Scoring Model'!$D$16:$D$25,K52)))>0,'Conversion Model'!$B$18,0)+IF(SUMPRODUCT(--ISNUMBER(SEARCH('Scoring Model'!$G$16:$G$23,K52)))>0,'Conversion Model'!$B$19,0))))) | AH52: =IF(OR(O52="Qualified",O52="Won",O52="Lost"),1,IF(O52="Unqualified",0,""))
A53: L-0052 | B53: 45959.997 | C53: LinkedIn ABM | D53: Ji-woo Chen | E53: ji-woo.chen@pellowincommerce.example | F53: Company | G53: Pellowin Commerce | H53: https://pellowincommerce.example | I53: Japan | J53: Payments - Card Issuing | K53: Our team is building a lending product for small businesses. Need help with sandbox setup and credit rules. Timeline 2 to 3 months. | L53: 11 | M53: 30.4 | N53: Vikram | O53: Qualified | Q53: =IF(F53="Disposable",1,0) -> 0 | R53: =IF(SUMPRODUCT(--ISNUMBER(SEARCH('Spam Rules'!$A$22:$A$35,K53)))>0,1,0) -> 0 | S53: =IF(AND(F53="Free",G53=""),1,0) -> 0 | T53: =IF(LEN(TRIM(K53))<15,1,0) -> 0 | U53: =IF(COUNTIF($E$2:$E$801,E53)>1,1,0) -> 0 | V53: =Q53*'Spam Rules'!$H$6+R53*'Spam Rules'!$H$7+S53*'Spam Rules'!$H$8+T53*'Spam Rules'!$H$9+U53*'Spam Rules'!$H$10 -> 0 | W53: =IF(V53>='Spam Rules'!$B$3,"Likely Spam","Genuine") -> Genuine | X53: =IFERROR(INDEX('Scoring Model'!$B$5:$B$11,MATCH(C53,'Scoring Model'!$A$5:$A$11,0)),0) -> 20 | Y53: =IFERROR(INDEX('Scoring Model'!$E$5:$E$7,MATCH(F53,'Scoring Model'!$D$5:$D$7,0)),0) -> 20 | Z53: =IFERROR(INDEX('Scoring Model'!$H$5:$H$13,MATCH(J53,'Scoring Model'!$G$5:$G$13,0)),0) -> 15 | AA53: =IF(L53>='Scoring Model'!$B$14,'Scoring Model'!$B$15,IF(L53>='Scoring Model'!$B$16,'Scoring Model'!$B$17,0)) -> 15 | AB53: =IF(SUMPRODUCT(--ISNUMBER(SEARCH('Scoring Model'!$D$16:$D$25,K53)))>0,'Scoring Model'!$B$18,0) -> 15 | AC53: =IF(SUMPRODUCT(--ISNUMBER(SEARCH('Scoring Model'!$G$16:$G$23,K53)))>0,'Scoring Model'!$B$19,0) -> 0 | AD53: =IF(W53="Likely Spam","",SUM(X53:AC53)) -> 85 | AE53: =IF(W53="Likely Spam","Spam",IF(AD53>='Scoring Model'!$B$21,"Hot",IF(AD53>='Scoring Model'!$B$22,"Warm","Nurture"))) -> Hot | AF53: =IF(W53="Likely Spam","Flagged by spam rules",TRIM(IF(X53>=20,"Strong source. ","")&IF(Y53>0,"Company email. ","")&IF(Z53>=15,"High-value product. ","")&IF(AA53>='Scoring Model'!$B$15,"High engagement. ","")&IF(AB53>0,"Buying intent in message. ","")&IF(AC53<0,"Negative intent in message. ",""))) -> Strong source. Company email. High-value product. High engagement. Buying intent in message. | AG53: =IF(W53="Likely Spam","",1/(1+EXP(-('Conversion Model'!$B$5+IFERROR(INDEX('Conversion Model'!$B$8:$B$14,MATCH(C53,'Conversion Model'!$A$8:$A$14,0)),0)+IFERROR(INDEX('Conversion Model'!$E$8:$E$9,MATCH(F53,'Conversion Model'!$D$8:$D$9,0)),0)+IFERROR(INDEX('Conversion Model'!$H$8:$H$12,MATCH(IF(LEFT(J53,8)="Payments","Payments",IF(LEFT(J53,7)="Lending","Lending",J53)),'Conversion Model'!$G$8:$G$12,0)),0)+MIN(L53,15)*'Conversion Model'!$B$17+IF(SUMPRODUCT(--ISNUMBER(SEARCH('Scoring Model'!$D$16:$D$25,K53)))>0,'Conversion Model'!$B$18,0)+IF(SUMPRODUCT(--ISNUMBER(SEARCH('Scoring Model'!$G$16:$G$23,K53)))>0,'Conversion Model'!$B$19,0))))) -> 0.9984578 | AH53: =IF(OR(O53="Qualified",O53="Won",O53="Lost"),1,IF(O53="Unqualified",0,"")) -> 1
A54: L-0053 | B54: 45961.363 | C54: Event | D54: Lina Costa | E54: lina.costa@ostrivolabs.example | F54: Company | G54: Ostrivo Labs | H54: https://ostrivolabs.example | I54: Canada | J54: Payments - Cross-Border | K54: Looking for pricing on KYC verification across 3 countries. Our current vendor keeps missing checks. | L54: 2 | M54: 9.3 | N54: Rahul | Q54: =IF(F54="Disposable",1,0) -> 0 | R54: =IF(SUMPRODUCT(--ISNUMBER(SEARCH('Spam Rules'!$A$22:$A$35,K54)))>0,1,0) -> 0 | S54: =IF(AND(F54="Free",G54=""),1,0) -> 0 | T54: =IF(LEN(TRIM(K54))<15,1,0) -> 0 | U54: =IF(COUNTIF($E$2:$E$801,E54)>1,1,0) -> 0 | V54: =Q54*'Spam Rules'!$H$6+R54*'Spam Rules'!$H$7+S54*'Spam Rules'!$H$8+T54*'Spam Rules'!$H$9+U54*'Spam Rules'!$H$10 -> 0 | W54: =IF(V54>='Spam Rules'!$B$3,"Likely Spam","Genuine") -> Genuine | X54: =IFERROR(INDEX('Scoring Model'!$B$5:$B$11,MATCH(C54,'Scoring Model'!$A$5:$A$11,0)),0) -> 15 | Y54: =IFERROR(INDEX('Scoring Model'!$E$5:$E$7,MATCH(F54,'Scoring Model'!$D$5:$D$7,0)),0) -> 20 | Z54: =IFERROR(INDEX('Scoring Model'!$H$5:$H$13,MATCH(J54,'Scoring Model'!$G$5:$G$13,0)),0) -> 15 | AA54: =IF(L54>='Scoring Model'!$B$14,'Scoring Model'!$B$15,IF(L54>='Scoring Model'!$B$16,'Scoring Model'!$B$17,0)) -> 0 | AB54: =IF(SUMPRODUCT(--ISNUMBER(SEARCH('Scoring Model'!$D$16:$D$25,K54)))>0,'Scoring Model'!$B$18,0) -> 15 | AC54: =IF(SUMPRODUCT(--ISNUMBER(SEARCH('Scoring Model'!$G$16:$G$23,K54)))>0,'Scoring Model'!$B$19,0) -> 0 | AD54: =IF(W54="Likely Spam","",SUM(X54:AC54)) -> 65 | AE54: =IF(W54="Likely Spam","Spam",IF(AD54>='Scoring Model'!$B$21,"Hot",IF(AD54>='Scoring Model'!$B$22,"Warm","Nurture"))) -> Warm | AF54: =IF(W54="Likely Spam","Flagged by spam rules",TRIM(IF(X54>=20,"Strong source. ","")&IF(Y54>0,"Company email. ","")&IF(Z54>=15,"High-value product. ","")&IF(AA54>='Scoring Model'!$B$15,"High engagement. ","")&IF(AB54>0,"Buying intent in message. ","")&IF(AC54<0,"Negative intent in message. ",""))) -> Company email. High-value product. Buying intent in message. | AG54: =IF(W54="Likely Spam","",1/(1+EXP(-('Conversion Model'!$B$5+IFERROR(INDEX('Conversion Model'!$B$8:$B$14,MATCH(C54,'Conversion Model'!$A$8:$A$14,0)),0)+IFERROR(INDEX('Conversion Model'!$E$8:$E$9,MATCH(F54,'Conversion Model'!$D$8:$D$9,0)),0)+IFERROR(INDEX('Conversion Model'!$H$8:$H$12,MATCH(IF(LEFT(J54,8)="Payments","Payments",IF(LEFT(J54,7)="Lending","Lending",J54)),'Conversion Model'!$G$8:$G$12,0)),0)+MIN(L54,15)*'Conversion Model'!$B$17+IF(SUMPRODUCT(--ISNUMBER(SEARCH('Scoring Model'!$D$16:$D$25,K54)))>0,'Conversion Model'!$B$18,0)+IF(SUMPRODUCT(--ISNUMBER(SEARCH('Scoring Model'!$G$16:$G$23,K54)))>0,'Conversion Model'!$B$19,0))))) -> 0.1693839 | AH54: =IF(OR(O54="Qualified",O54="Won",O54="Lost"),1,IF(O54="Unqualified",0,""))
A55: L-0054 | B55: 45961.485 | C55: Docs Signup | D55: Sam Chen | E55: sam.chen@freemail.example | F55: Free | I55: UK | J55: Other | K55: Just exploring, what does your company do? | L55: 1 | M55: 1.6 | N55: Neha | O55: Unqualified | Q55: =IF(F55="Disposable",1,0) -> 0 | R55: =IF(SUMPRODUCT(--ISNUMBER(SEARCH('Spam Rules'!$A$22:$A$35,K55)))>0,1,0) -> 0 | S55: =IF(AND(F55="Free",G55=""),1,0) -> 1 | T55: =IF(LEN(TRIM(K55))<15,1,0) -> 0 | U55: =IF(COUNTIF($E$2:$E$801,E55)>1,1,0) -> 0 | V55: =Q55*'Spam Rules'!$H$6+R55*'Spam Rules'!$H$7+S55*'Spam Rules'!$H$8+T55*'Spam Rules'!$H$9+U55*'Spam Rules'!$H$10 -> 0 | W55: =IF(V55>='Spam Rules'!$B$3,"Likely Spam","Genuine") -> Genuine | X55: =IFERROR(INDEX('Scoring Model'!$B$5:$B$11,MATCH(C55,'Scoring Model'!$A$5:$A$11,0)),0) -> 5 | Y55: =IFERROR(INDEX('Scoring Model'!$E$5:$E$7,MATCH(F55,'Scoring Model'!$D$5:$D$7,0)),0) -> 0 | Z55: =IFERROR(INDEX('Scoring Model'!$H$5:$H$13,MATCH(J55,'Scoring Model'!$G$5:$G$13,0)),0) -> 0 | AA55: =IF(L55>='Scoring Model'!$B$14,'Scoring Model'!$B$15,IF(L55>='Scoring Model'!$B$16,'Scoring Model'!$B$17,0)) -> 0 | AB55: =IF(SUMPRODUCT(--ISNUMBER(SEARCH('Scoring Model'!$D$16:$D$25,K55)))>0,'Scoring Model'!$B$18,0) -> 0 | AC55: =IF(SUMPRODUCT(--ISNUMBER(SEARCH('Scoring Model'!$G$16:$G$23,K55)))>0,'Scoring Model'!$B$19,0) -> -30 | AD55: =IF(W55="Likely Spam","",SUM(X55:AC55)) -> -25 | AE55: =IF(W55="Likely Spam","Spam",IF(AD55>='Scoring Model'!$B$21,"Hot",IF(AD55>='Scoring Model'!$B$22,"Warm","Nurture"))) -> Nurture | AF55: =IF(W55="Likely Spam","Flagged by spam rules",TRIM(IF(X55>=20,"Strong source. ","")&IF(Y55>0,"Company email. ","")&IF(Z55>=15,"High-value product. ","")&IF(AA55>='Scoring Model'!$B$15,"High engagement. ","")&IF(AB55>0,"Buying intent in message. ","")&IF(AC55<0,"Negative intent in message. ",""))) -> Negative intent in message. | AG55: =IF(W55="Likely Spam","",1/(1+EXP(-('Conversion Model'!$B$5+IFERROR(INDEX('Conversion Model'!$B$8:$B$14,MATCH(C55,'Conversion Model'!$A$8:$A$14,0)),0)+IFERROR(INDEX('Conversion Model'!$E$8:$E$9,MATCH(F55,'Conversion Model'!$D$8:$D$9,0)),0)+IFERROR(INDEX('Conversion Model'!$H$8:$H$12,MATCH(IF(LEFT(J55,8)="Payments","Payments",IF(LEFT(J55,7)="Lending","Lending",J55)),'Conversion Model'!$G$8:$G$12,0)),0)+MIN(L55,15)*'Conversion Model'!$B$17+IF(SUMPRODUCT(--ISNUMBER(SEARCH('Scoring Model'!$D$16:$D$25,K55)))>0,'Conversion Model'!$B$18,0)+IF(SUMPRODUCT(--ISNUMBER(SEARCH('Scoring Model'!$G$16:$G$23,K55)))>0,'Conversion Model'!$B$19,0))))) -> 0.00067914264 | AH55: =IF(OR(O55="Qualified",O55="Won",O55="Lost"),1,IF(O55="Unqualified",0,"")) -> 0
A56: L-0055 | B56: 45962.039 | C56: LinkedIn ABM | D56: Sam Berg | E56: sam.berg@rushbarrowsystems.example | F56: Company | G56: Rushbarrow Systems | H56: https://rushbarrowsystems.example | I56: UK | J56: Lending - Loan Origination | K56: Looking for pricing on KYC verification across 4 countries. Our current vendor keeps missing checks. | L56: 8 | M56: 85.8 | N56: Vikram | O56: Lost | Q56: =IF(F56="Disposable",1,0) -> 0 | R56: =IF(SUMPRODUCT(--ISNUMBER(SEARCH('Spam Rules'!$A$22:$A$35,K56)))>0,1,0) -> 0 | S56: =IF(AND(F56="Free",G56=""),1,0) -> 0 | T56: =IF(LEN(TRIM(K56))<15,1,0) -> 0 | U56: =IF(COUNTIF($E$2:$E$801,E56)>1,1,0) -> 0 | V56: =Q56*'Spam Rules'!$H$6+R56*'Spam Rules'!$H$7+S56*'Spam Rules'!$H$8+T56*'Spam Rules'!$H$9+U56*'Spam Rules'!$H$10 -> 0 | W56: =IF(V56>='Spam Rules'!$B$3,"Likely Spam","Genuine") -> Genuine | X56: =IFERROR(INDEX('Scoring Model'!$B$5:$B$11,MATCH(C56,'Scoring Model'!$A$5:$A$11,0)),0) -> 20 | Y56: =IFERROR(INDEX('Scoring Model'!$E$5:$E$7,MATCH(F56,'Scoring Model'!$D$5:$D$7,0)),0) -> 20 | Z56: =IFERROR(INDEX('Scoring Model'!$H$5:$H$13,MATCH(J56,'Scoring Model'!$G$5:$G$13,0)),0) -> 15 | AA56: =IF(L56>='Scoring Model'!$B$14,'Scoring Model'!$B$15,IF(L56>='Scoring Model'!$B$16,'Scoring Model'!$B$17,0)) -> 15 | AB56: =IF(SUMPRODUCT(--ISNUMBER(SEARCH('Scoring Model'!$D$16:$D$25,K56)))>0,'Scoring Model'!$B$18,0) -> 15 | AC56: =IF(SUMPRODUCT(--ISNUMBER(SEARCH('Scoring Model'!$G$16:$G$23,K56)))>0,'Scoring Model'!$B$19,0) -> 0 | AD56: =IF(W56="Likely Spam","",SUM(X56:AC56)) -> 85 | AE56: =IF(W56="Likely Spam","Spam",IF(AD56>='Scoring Model'!$B$21,"Hot",IF(AD56>='Scoring Model'!$B$22,"Warm","Nurture"))) -> Hot | AF56: =IF(W56="Likely Spam","Flagged by spam rules",TRIM(IF(X56>=20,"Strong source. ","")&IF(Y56>0,"Company email. ","")&IF(Z56>=15,"High-value product. ","")&IF(AA56>='Scoring Model'!$B$15,"High engagement. ","")&IF(AB56>0,"Buying intent in message. ","")&IF(AC56<0,"Negative intent in message. ",""))) -> Strong source. Company email. High-value product. High engagement. Buying intent in message. | AG56: =IF(W56="Likely Spam","",1/(1+EXP(-('Conversion Model'!$B$5+IFERROR(INDEX('Conversion Model'!$B$8:$B$14,MATCH(C56,'Conversion Model'!$A$8:$A$14,0)),0)+IFERROR(INDEX('Conversion Model'!$E$8:$E$9,MATCH(F56,'Conversion Model'!$D$8:$D$9,0)),0)+IFERROR(INDEX('Conversion Model'!$H$8:$H$12,MATCH(IF(LEFT(J56,8)="Payments","Payments",IF(LEFT(J56,7)="Lending","Lending",J56)),'Conversion Model'!$G$8:$G$12,0)),0)+MIN(L56,15)*'Conversion Model'!$B$17+IF(SUMPRODUCT(--ISNUMBER(SEARCH('Scoring Model'!$D$16:$D$25,K56)))>0,'Conversion Model'!$B$18,0)+IF(SUMPRODUCT(--ISNUMBER(SEARCH('Scoring Model'!$G$16:$G$23,K56)))>0,'Conversion Model'!$B$19,0))))) -> 0.99332043 | AH56: =IF(OR(O56="Qualified",O56="Won",O56="Lost"),1,IF(O56="Unqualified",0,"")) -> 1
A57: L-0056 | B57: 45962.095 | C57: Partner Referral | D57: Chloe Novak | E57: chloe.novak@letterdrop.example | F57: Free | G57: Larkspindle Systems | I57: Brazil | J57: Other | K57: I am a student researching open banking for my thesis. Can you share some material? | L57: 1 | M57: 14.6 | N57: Vikram | Q57: =IF(F57="Disposable",1,0) -> 0 | R57: =IF(SUMPRODUCT(--ISNUMBER(SEARCH('Spam Rules'!$A$22:$A$35,K57)))>0,1,0) -> 0 | S57: =IF(AND(F57="Free",G57=""),1,0) -> 0 | T57: =IF(LEN(TRIM(K57))<15,1,0) -> 0 | U57: =IF(COUNTIF($E$2:$E$801,E57)>1,1,0) -> 0 | V57: =Q57*'Spam Rules'!$H$6+R57*'Spam Rules'!$H$7+S57*'Spam Rules'!$H$8+T57*'Spam Rules'!$H$9+U57*'Spam Rules'!$H$10 -> 0 | W57: =IF(V57>='Spam Rules'!$B$3,"Likely Spam","Genuine") -> Genuine | X57: =IFERROR(INDEX('Scoring Model'!$B$5:$B$11,MATCH(C57,'Scoring Model'!$A$5:$A$11,0)),0) -> 30 | Y57: =IFERROR(INDEX('Scoring Model'!$E$5:$E$7,MATCH(F57,'Scoring Model'!$D$5:$D$7,0)),0) -> 0 | Z57: =IFERROR(INDEX('Scoring Model'!$H$5:$H$13,MATCH(J57,'Scoring Model'!$G$5:$G$13,0)),0) -> 0 | AA57: =IF(L57>='Scoring Model'!$B$14,'Scoring Model'!$B$15,IF(L57>='Scoring Model'!$B$16,'Scoring Model'!$B$17,0)) -> 0 | AB57: =IF(SUMPRODUCT(--ISNUMBER(SEARCH('Scoring Model'!$D$16:$D$25,K57)))>0,'Scoring Model'!$B$18,0) -> 0 | AC57: =IF(SUMPRODUCT(--ISNUMBER(SEARCH('Scoring Model'!$G$16:$G$23,K57)))>0,'Scoring Model'!$B$19,0) -> -30 | AD57: =IF(W57="Likely Spam","",SUM(X57:AC57)) -> 0 | AE57: =IF(W57="Likely Spam","Spam",IF(AD57>='Scoring Model'!$B$21,"Hot",IF(AD57>='Scoring Model'!$B$22,"Warm","Nurture"))) -> Nurture | AF57: =IF(W57="Likely Spam","Flagged by spam rules",TRIM(IF(X57>=20,"Strong source. ","")&IF(Y57>0,"Company email. ","")&IF(Z57>=15,"High-value product. ","")&IF(AA57>='Scoring Model'!$B$15,"High engagement. ","")&IF(AB57>0,"Buying intent in message. ","")&IF(AC57<0,"Negative intent in message. ",""))) -> Strong source. Negative intent in message. | AG57: =IF(W57="Likely Spam","",1/(1+EXP(-('Conversion Model'!$B$5+IFERROR(INDEX('Conversion Model'!$B$8:$B$14,MATCH(C57,'Conversion Model'!$A$8:$A$14,0)),0)+IFERROR(INDEX('Conversion Model'!$E$8:$E$9,MATCH(F57,'Conversion Model'!$D$8:$D$9,0)),0)+IFERROR(INDEX('Conversion Model'!$H$8:$H$12,MATCH(IF(LEFT(J57,8)="Payments","Payments",IF(LEFT(J57,7)="Lending","Lending",J57)),'Conversion Model'!$G$8:$G$12,0)),0)+MIN(L57,15)*'Conversion Model'!$B$17+IF(SUMPRODUCT(--ISNUMBER(SEARCH('Scoring Model'!$D$16:$D$25,K57)))>0,'Conversion Model'!$B$18,0)+IF(SUMPRODUCT(--ISNUMBER(SEARCH('Scoring Model'!$G$16:$G$23,K57)))>0,'Conversion Model'!$B$19,0))))) -> 0.0030608411 | AH57: =IF(OR(O57="Qualified",O57="Won",O57="Lost"),1,IF(O57="Unqualified",0,""))
A58: L-0057 | B58: 45963.449 | C58: Website Contact Form | D58: Ravi Ivanova | E58: tariq625@vanishmail.example | F58: Free | I58: Vietnam | J58: Other | K58: We offer premium SEO backlinks and guest post services for fintech websites. Reply for rates. | L58: 2 | N58: Neha | Q58: =IF(F58="Disposable",1,0) -> 0 | R58: =IF(SUMPRODUCT(--ISNUMBER(SEARCH('Spam Rules'!$A$22:$A$35,K58)))>0,1,0) -> 1 | S58: =IF(AND(F58="Free",G58=""),1,0) -> 1 | T58: =IF(LEN(TRIM(K58))<15,1,0) -> 0 | U58: =IF(COUNTIF($E$2:$E$801,E58)>1,1,0) -> 1 | V58: =Q58*'Spam Rules'!$H$6+R58*'Spam Rules'!$H$7+S58*'Spam Rules'!$H$8+T58*'Spam Rules'!$H$9+U58*'Spam Rules'!$H$10 -> 1 | W58: =IF(V58>='Spam Rules'!$B$3,"Likely Spam","Genuine") -> Likely Spam | X58: =IFERROR(INDEX('Scoring Model'!$B$5:$B$11,MATCH(C58,'Scoring Model'!$A$5:$A$11,0)),0) -> 10 | Y58: =IFERROR(INDEX('Scoring Model'!$E$5:$E$7,MATCH(F58,'Scoring Model'!$D$5:$D$7,0)),0) -> 0 | Z58: =IFERROR(INDEX('Scoring Model'!$H$5:$H$13,MATCH(J58,'Scoring Model'!$G$5:$G$13,0)),0) -> 0 | AA58: =IF(L58>='Scoring Model'!$B$14,'Scoring Model'!$B$15,IF(L58>='Scoring Model'!$B$16,'Scoring Model'!$B$17,0)) -> 0 | AB58: =IF(SUMPRODUCT(--ISNUMBER(SEARCH('Scoring Model'!$D$16:$D$25,K58)))>0,'Scoring Model'!$B$18,0) -> 0 | AC58: =IF(SUMPRODUCT(--ISNUMBER(SEARCH('Scoring Model'!$G$16:$G$23,K58)))>0,'Scoring Model'!$B$19,0) -> 0 | AD58: =IF(W58="Likely Spam","",SUM(X58:AC58)) | AE58: =IF(W58="Likely Spam","Spam",IF(AD58>='Scoring Model'!$B$21,"Hot",IF(AD58>='Scoring Model'!$B$22,"Warm","Nurture"))) -> Spam | AF58: =IF(W58="Likely Spam","Flagged by spam rules",TRIM(IF(X58>=20,"Strong source. ","")&IF(Y58>0,"Company email. ","")&IF(Z58>=15,"High-value product. ","")&IF(AA58>='Scoring Model'!$B$15,"High engagement. ","")&IF(AB58>0,"Buying intent in message. ","")&IF(AC58<0,"Negative intent in message. ",""))) -> Flagged by spam rules | AG58: =IF(W58="Likely Spam","",1/(1+EXP(-('Conversion Model'!$B$5+IFERROR(INDEX('Conversion Model'!$B$8:$B$14,MATCH(C58,'Conversion Model'!$A$8:$A$14,0)),0)+IFERROR(INDEX('Conversion Model'!$E$8:$E$9,MATCH(F58,'Conversion Model'!$D$8:$D$9,0)),0)+IFERROR(INDEX('Conversion Model'!$H$8:$H$12,MATCH(IF(LEFT(J58,8)="Payments","Payments",IF(LEFT(J58,7)="Lending","Lending",J58)),'Conversion Model'!$G$8:$G$12,0)),0)+MIN(L58,15)*'Conversion Model'!$B$17+IF(SUMPRODUCT(--ISNUMBER(SEARCH('Scoring Model'!$D$16:$D$25,K58)))>0,'Conversion Model'!$B$18,0)+IF(SUMPRODUCT(--ISNUMBER(SEARCH('Scoring Model'!$G$16:$G$23,K58)))>0,'Conversion Model'!$B$19,0))))) | AH58: =IF(OR(O58="Qualified",O58="Won",O58="Lost"),1,IF(O58="Unqualified",0,""))
A59: L-0058 | B59: 45964.31 | C59: Website Contact Form | D59: Fatima Rossi | E59: fatima.rossi@letterdrop.example | F59: Free | G59: Wyndlefoss Capital | I59: Japan | J59: Payments - Card Issuing | K59: Just exploring, what does your company do? | L59: 4 | M59: 9.5 | N59: Neha | Q59: =IF(F59="Disposable",1,0) -> 0 | R59: =IF(SUMPRODUCT(--ISNUMBER(SEARCH('Spam Rules'!$A$22:$A$35,K59)))>0,1,0) -> 0 | S59: =IF(AND(F59="Free",G59=""),1,0) -> 0 | T59: =IF(LEN(TRIM(K59))<15,1,0) -> 0 | U59: =IF(COUNTIF($E$2:$E$801,E59)>1,1,0) -> 0 | V59: =Q59*'Spam Rules'!$H$6+R59*'Spam Rules'!$H$7+S59*'Spam Rules'!$H$8+T59*'Spam Rules'!$H$9+U59*'Spam Rules'!$H$10 -> 0 | W59: =IF(V59>='Spam Rules'!$B$3,"Likely Spam","Genuine") -> Genuine | X59: =IFERROR(INDEX('Scoring Model'!$B$5:$B$11,MATCH(C59,'Scoring Model'!$A$5:$A$11,0)),0) -> 10 | Y59: =IFERROR(INDEX('Scoring Model'!$E$5:$E$7,MATCH(F59,'Scoring Model'!$D$5:$D$7,0)),0) -> 0 | Z59: =IFERROR(INDEX('Scoring Model'!$H$5:$H$13,MATCH(J59,'Scoring Model'!$G$5:$G$13,0)),0) -> 15 | AA59: =IF(L59>='Scoring Model'!$B$14,'Scoring Model'!$B$15,IF(L59>='Scoring Model'!$B$16,'Scoring Model'!$B$17,0)) -> 8 | AB59: =IF(SUMPRODUCT(--ISNUMBER(SEARCH('Scoring Model'!$D$16:$D$25,K59)))>0,'Scoring Model'!$B$18,0) -> 0 | AC59: =IF(SUMPRODUCT(--ISNUMBER(SEARCH('Scoring Model'!$G$16:$G$23,K59)))>0,'Scoring Model'!$B$19,0) -> -30 | AD59: =IF(W59="Likely Spam","",SUM(X59:AC59)) -> 3 | AE59: =IF(W59="Likely Spam","Spam",IF(AD59>='Scoring Model'!$B$21,"Hot",IF(AD59>='Scoring Model'!$B$22,"Warm","Nurture"))) -> Nurture | AF59: =IF(W59="Likely Spam","Flagged by spam rules",TRIM(IF(X59>=20,"Strong source. ","")&IF(Y59>0,"Company email. ","")&IF(Z59>=15,"High-value product. ","")&IF(AA59>='Scoring Model'!$B$15,"High engagement. ","")&IF(AB59>0,"Buying intent in message. ","")&IF(AC59<0,"Negative intent in message. ",""))) -> High-value product. Negative intent in message. | AG59: =IF(W59="Likely Spam","",1/(1+EXP(-('Conversion Model'!$B$5+IFERROR(INDEX('Conversion Model'!$B$8:$B$14,MATCH(C59,'Conversion Model'!$A$8:$A$14,0)),0)+IFERROR(INDEX('Conversion Model'!$E$8:$E$9,MATCH(F59,'Conversion Model'!$D$8:$D$9,0)),0)+IFERROR(INDEX('Conversion Model'!$H$8:$H$12,MATCH(IF(LEFT(J59,8)="Payments","Payments",IF(LEFT(J59,7)="Lending","Lending",J59)),'Conversion Model'!$G$8:$G$12,0)),0)+MIN(L59,15)*'Conversion Model'!$B$17+IF(SUMPRODUCT(--ISNUMBER(SEARCH('Scoring Model'!$D$16:$D$25,K59)))>0,'Conversion Model'!$B$18,0)+IF(SUMPRODUCT(--ISNUMBER(SEARCH('Scoring Model'!$G$16:$G$23,K59)))>0,'Conversion Model'!$B$19,0))))) -> 0.012044851 | AH59: =IF(OR(O59="Qualified",O59="Won",O59="Lost"),1,IF(O59="Unqualified",0,""))
A60: L-0059 | B60: 45965.033 | C60: LinkedIn ABM | D60: Arjun Okafor | E60: arjun.okafor@umberwickmoney.example | F60: Company | G60: Umberwick Money | H60: https://umberwickmoney.example | I60: Germany | J60: Banking Data API | K60: Just exploring, what does your company do? | L60: 1 | M60: 10.8 | N60: Neha | O60: Unqualified | Q60: =IF(F60="Disposable",1,0) -> 0 | R60: =IF(SUMPRODUCT(--ISNUMBER(SEARCH('Spam Rules'!$A$22:$A$35,K60)))>0,1,0) -> 0 | S60: =IF(AND(F60="Free",G60=""),1,0) -> 0 | T60: =IF(LEN(TRIM(K60))<15,1,0) -> 0 | U60: =IF(COUNTIF($E$2:$E$801,E60)>1,1,0) -> 0 | V60: =Q60*'Spam Rules'!$H$6+R60*'Spam Rules'!$H$7+S60*'Spam Rules'!$H$8+T60*'Spam Rules'!$H$9+U60*'Spam Rules'!$H$10 -> 0 | W60: =IF(V60>='Spam Rules'!$B$3,"Likely Spam","Genuine") -> Genuine | X60: =IFERROR(INDEX('Scoring Model'!$B$5:$B$11,MATCH(C60,'Scoring Model'!$A$5:$A$11,0)),0) -> 20 | Y60: =IFERROR(INDEX('Scoring Model'!$E$5:$E$7,MATCH(F60,'Scoring Model'!$D$5:$D$7,0)),0) -> 20 | Z60: =IFERROR(INDEX('Scoring Model'!$H$5:$H$13,MATCH(J60,'Scoring Model'!$G$5:$G$13,0)),0) -> 5 | AA60: =IF(L60>='Scoring Model'!$B$14,'Scoring Model'!$B$15,IF(L60>='Scoring Model'!$B$16,'Scoring Model'!$B$17,0)) -> 0 | AB60: =IF(SUMPRODUCT(--ISNUMBER(SEARCH('Scoring Model'!$D$16:$D$25,K60)))>0,'Scoring Model'!$B$18,0) -> 0 | AC60: =IF(SUMPRODUCT(--ISNUMBER(SEARCH('Scoring Model'!$G$16:$G$23,K60)))>0,'Scoring Model'!$B$19,0) -> -30 | AD60: =IF(W60="Likely Spam","",SUM(X60:AC60)) -> 15 | AE60: =IF(W60="Likely Spam","Spam",IF(AD60>='Scoring Model'!$B$21,"Hot",IF(AD60>='Scoring Model'!$B$22,"Warm","Nurture"))) -> Nurture | AF60: =IF(W60="Likely Spam","Flagged by spam rules",TRIM(IF(X60>=20,"Strong source. ","")&IF(Y60>0,"Company email. ","")&IF(Z60>=15,"High-value product. ","")&IF(AA60>='Scoring Model'!$B$15,"High engagement. ","")&IF(AB60>0,"Buying intent in message. ","")&IF(AC60<0,"Negative intent in message. ",""))) -> Strong source. Company email. Negative intent in message. | AG60: =IF(W60="Likely Spam","",1/(1+EXP(-('Conversion Model'!$B$5+IFERROR(INDEX('Conversion Model'!$B$8:$B$14,MATCH(C60,'Conversion Model'!$A$8:$A$14,0)),0)+IFERROR(INDEX('Conversion Model'!$E$8:$E$9,MATCH(F60,'Conversion Model'!$D$8:$D$9,0)),0)+IFERROR(INDEX('Conversion Model'!$H$8:$H$12,MATCH(IF(LEFT(J60,8)="Payments","Payments",IF(LEFT(J60,7)="Lending","Lending",J60)),'Conversion Model'!$G$8:$G$12,0)),0)+MIN(L60,15)*'Conversion Model'!$B$17+IF(SUMPRODUCT(--ISNUMBER(SEARCH('Scoring Model'!$D$16:$D$25,K60)))>0,'Conversion Model'!$B$18,0)+IF(SUMPRODUCT(--ISNUMBER(SEARCH('Scoring Model'!$G$16:$G$23,K60)))>0,'Conversion Model'!$B$19,0))))) -> 0.0074430772 | AH60: =IF(OR(O60="Qualified",O60="Won",O60="Lost"),1,IF(O60="Unqualified",0,"")) -> 0
A61: L-0060 | B61: 45965.242 | C61: Pricing Page Form | D61: Ravi Muller | E61: ravi811@webmail.example | F61: Free | G61: Rankfarrow SEO Agency | I61: South Korea | J61: Other | K61: Claim your cashback reward now at the link below. | L61: 2 | M61: 36.3 | N61: Unassigned | O61: Spam | Q61: =IF(F61="Disposable",1,0) -> 0 | R61: =IF(SUMPRODUCT(--ISNUMBER(SEARCH('Spam Rules'!$A$22:$A$35,K61)))>0,1,0) -> 1 | S61: =IF(AND(F61="Free",G61=""),1,0) -> 0 | T61: =IF(LEN(TRIM(K61))<15,1,0) -> 0 | U61: =IF(COUNTIF($E$2:$E$801,E61)>1,1,0) -> 0 | V61: =Q61*'Spam Rules'!$H$6+R61*'Spam Rules'!$H$7+S61*'Spam Rules'!$H$8+T61*'Spam Rules'!$H$9+U61*'Spam Rules'!$H$10 -> 1 | W61: =IF(V61>='Spam Rules'!$B$3,"Likely Spam","Genuine") -> Likely Spam | X61: =IFERROR(INDEX('Scoring Model'!$B$5:$B$11,MATCH(C61,'Scoring Model'!$A$5:$A$11,0)),0) -> 25 | Y61: =IFERROR(INDEX('Scoring Model'!$E$5:$E$7,MATCH(F61,'Scoring Model'!$D$5:$D$7,0)),0) -> 0 | Z61: =IFERROR(INDEX('Scoring Model'!$H$5:$H$13,MATCH(J61,'Scoring Model'!$G$5:$G$13,0)),0) -> 0 | AA61: =IF(L61>='Scoring Model'!$B$14,'Scoring Model'!$B$15,IF(L61>='Scoring Model'!$B$16,'Scoring Model'!$B$17,0)) -> 0 | AB61: =IF(SUMPRODUCT(--ISNUMBER(SEARCH('Scoring Model'!$D$16:$D$25,K61)))>0,'Scoring Model'!$B$18,0) -> 0 | AC61: =IF(SUMPRODUCT(--ISNUMBER(SEARCH('Scoring Model'!$G$16:$G$23,K61)))>0,'Scoring Model'!$B$19,0) -> 0 | AD61: =IF(W61="Likely Spam","",SUM(X61:AC61)) | AE61: =IF(W61="Likely Spam","Spam",IF(AD61>='Scoring Model'!$B$21,"Hot",IF(AD61>='Scoring Model'!$B$22,"Warm","Nurture"))) -> Spam | AF61: =IF(W61="Likely Spam","Flagged by spam rules",TRIM(IF(X61>=20,"Strong source. ","")&IF(Y61>0,"Company email. ","")&IF(Z61>=15,"High-value product. ","")&IF(AA61>='Scoring Model'!$B$15,"High engagement. ","")&IF(AB61>0,"Buying intent in message. ","")&IF(AC61<0,"Negative intent in message. ",""))) -> Flagged by spam rules | AG61: =IF(W61="Likely Spam","",1/(1+EXP(-('Conversion Model'!$B$5+IFERROR(INDEX('Conversion Model'!$B$8:$B$14,MATCH(C61,'Conversion Model'!$A$8:$A$14,0)),0)+IFERROR(INDEX('Conversion Model'!$E$8:$E$9,MATCH(F61,'Conversion Model'!$D$8:$D$9,0)),0)+IFERROR(INDEX('Conversion Model'!$H$8:$H$12,MATCH(IF(LEFT(J61,8)="Payments","Payments",IF(LEFT(J61,7)="Lending","Lending",J61)),'Conversion Model'!$G$8:$G$12,0)),0)+MIN(L61,15)*'Conversion Model'!$B$17+IF(SUMPRODUCT(--ISNUMBER(SEARCH('Scoring Model'!$D$16:$D$25,K61)))>0,'Conversion Model'!$B$18,0)+IF(SUMPRODUCT(--ISNUMBER(SEARCH('Scoring Model'!$G$16:$G$23,K61)))>0,'Conversion Model'!$B$19,0))))) | AH61: =IF(OR(O61="Qualified",O61="Won",O61="Lost"),1,IF(O61="Unqualified",0,""))
A62: L-0061 | B62: 45965.599 | C62: Website Contact Form | D62: Ravi Lee | E62: ravi.lee@inboxly.example | F62: Free | I62: Japan | J62: Other | K62: Can you give a free account for our hackathon project? | L62: 1 | M62: 9.1 | N62: Unassigned | Q62: =IF(F62="Disposable",1,0) -> 0 | R62: =IF(SUMPRODUCT(--ISNUMBER(SEARCH('Spam Rules'!$A$22:$A$35,K62)))>0,1,0) -> 0 | S62: =IF(AND(F62="Free",G62=""),1,0) -> 1 | T62: =IF(LEN(TRIM(K62))<15,1,0) -> 0 | U62: =IF(COUNTIF($E$2:$E$801,E62)>1,1,0) -> 0 | V62: =Q62*'Spam Rules'!$H$6+R62*'Spam Rules'!$H$7+S62*'Spam Rules'!$H$8+T62*'Spam Rules'!$H$9+U62*'Spam Rules'!$H$10 -> 0 | W62: =IF(V62>='Spam Rules'!$B$3,"Likely Spam","Genuine") -> Genuine | X62: =IFERROR(INDEX('Scoring Model'!$B$5:$B$11,MATCH(C62,'Scoring Model'!$A$5:$A$11,0)),0) -> 10 | Y62: =IFERROR(INDEX('Scoring Model'!$E$5:$E$7,MATCH(F62,'Scoring Model'!$D$5:$D$7,0)),0) -> 0 | Z62: =IFERROR(INDEX('Scoring Model'!$H$5:$H$13,MATCH(J62,'Scoring Model'!$G$5:$G$13,0)),0) -> 0 | AA62: =IF(L62>='Scoring Model'!$B$14,'Scoring Model'!$B$15,IF(L62>='Scoring Model'!$B$16,'Scoring Model'!$B$17,0)) -> 0 | AB62: =IF(SUMPRODUCT(--ISNUMBER(SEARCH('Scoring Model'!$D$16:$D$25,K62)))>0,'Scoring Model'!$B$18,0) -> 0 | AC62: =IF(SUMPRODUCT(--ISNUMBER(SEARCH('Scoring Model'!$G$16:$G$23,K62)))>0,'Scoring Model'!$B$19,0) -> -30 | AD62: =IF(W62="Likely Spam","",SUM(X62:AC62)) -> -20 | AE62: =IF(W62="Likely Spam","Spam",IF(AD62>='Scoring Model'!$B$21,"Hot",IF(AD62>='Scoring Model'!$B$22,"Warm","Nurture"))) -> Nurture | AF62: =IF(W62="Likely Spam","Flagged by spam rules",TRIM(IF(X62>=20,"Strong source. ","")&IF(Y62>0,"Company email. ","")&IF(Z62>=15,"High-value product. ","")&IF(AA62>='Scoring Model'!$B$15,"High engagement. ","")&IF(AB62>0,"Buying intent in message. ","")&IF(AC62<0,"Negative intent in message. ",""))) -> Negative intent in message. | AG62: =IF(W62="Likely Spam","",1/(1+EXP(-('Conversion Model'!$B$5+IFERROR(INDEX('Conversion Model'!$B$8:$B$14,MATCH(C62,'Conversion Model'!$A$8:$A$14,0)),0)+IFERROR(INDEX('Conversion Model'!$E$8:$E$9,MATCH(F62,'Conversion Model'!$D$8:$D$9,0)),0)+IFERROR(INDEX('Conversion Model'!$H$8:$H$12,MATCH(IF(LEFT(J62,8)="Payments","Payments",IF(LEFT(J62,7)="Lending","Lending",J62)),'Conversion Model'!$G$8:$G$12,0)),0)+MIN(L62,15)*'Conversion Model'!$B$17+IF(SUMPRODUCT(--ISNUMBER(SEARCH('Scoring Model'!$D$16:$D$25,K62)))>0,'Conversion Model'!$B$18,0)+IF(SUMPRODUCT(--ISNUMBER(SEARCH('Scoring Model'!$G$16:$G$23,K62)))>0,'Conversion Model'!$B$19,0))))) -> 0.00092758325 | AH62: =IF(OR(O62="Qualified",O62="Won",O62="Lost"),1,IF(O62="Unqualified",0,""))
A63: L-0062 | B63: 45965.62 | C63: Partner Referral | D63: Sofia Tanaka | E63: sofia.tanaka@quillmoorstudio.example | F63: Company | G63: Quillmoor Studio | H63: https://quillmoorstudio.example | I63: UAE | J63: Payments - Virtual Accounts | K63: Evaluating virtual accounts providers for our payroll app. Can we get a demo and a cost comparison? | L63: 2 | M63: 35.6 | N63: Vikram | Q63: =IF(F63="Disposable",1,0) -> 0 | R63: =IF(SUMPRODUCT(--ISNUMBER(SEARCH('Spam Rules'!$A$22:$A$35,K63)))>0,1,0) -> 0 | S63: =IF(AND(F63="Free",G63=""),1,0) -> 0 | T63: =IF(LEN(TRIM(K63))<15,1,0) -> 0 | U63: =IF(COUNTIF($E$2:$E$801,E63)>1,1,0) -> 0 | V63: =Q63*'Spam Rules'!$H$6+R63*'Spam Rules'!$H$7+S63*'Spam Rules'!$H$8+T63*'Spam Rules'!$H$9+U63*'Spam Rules'!$H$10 -> 0 | W63: =IF(V63>='Spam Rules'!$B$3,"Likely Spam","Genuine") -> Genuine | X63: =IFERROR(INDEX('Scoring Model'!$B$5:$B$11,MATCH(C63,'Scoring Model'!$A$5:$A$11,0)),0) -> 30 | Y63: =IFERROR(INDEX('Scoring Model'!$E$5:$E$7,MATCH(F63,'Scoring Model'!$D$5:$D$7,0)),0) -> 20 | Z63: =IFERROR(INDEX('Scoring Model'!$H$5:$H$13,MATCH(J63,'Scoring Model'!$G$5:$G$13,0)),0) -> 15 | AA63: =IF(L63>='Scoring Model'!$B$14,'Scoring Model'!$B$15,IF(L63>='Scoring Model'!$B$16,'Scoring Model'!$B$17,0)) -> 0 | AB63: =IF(SUMPRODUCT(--ISNUMBER(SEARCH('Scoring Model'!$D$16:$D$25,K63)))>0,'Scoring Model'!$B$18,0) -> 15 | AC63: =IF(SUMPRODUCT(--ISNUMBER(SEARCH('Scoring Model'!$G$16:$G$23,K63)))>0,'Scoring Model'!$B$19,0) -> 0 | AD63: =IF(W63="Likely Spam","",SUM(X63:AC63)) -> 80 | AE63: =IF(W63="Likely Spam","Spam",IF(AD63>='Scoring Model'!$B$21,"Hot",IF(AD63>='Scoring Model'!$B$22,"Warm","Nurture"))) -> Hot | AF63: =IF(W63="Likely Spam","Flagged by spam rules",TRIM(IF(X63>=20,"Strong source. ","")&IF(Y63>0,"Company email. ","")&IF(Z63>=15,"High-value product. ","")&IF(AA63>='Scoring Model'!$B$15,"High engagement. ","")&IF(AB63>0,"Buying intent in message. ","")&IF(AC63<0,"Negative intent in message. ",""))) -> Strong source. Company email. High-value product. Buying intent in message. | AG63: =IF(W63="Likely Spam","",1/(1+EXP(-('Conversion Model'!$B$5+IFERROR(INDEX('Conversion Model'!$B$8:$B$14,MATCH(C63,'Conversion Model'!$A$8:$A$14,0)),0)+IFERROR(INDEX('Conversion Model'!$E$8:$E$9,MATCH(F63,'Conversion Model'!$D$8:$D$9,0)),0)+IFERROR(INDEX('Conversion Model'!$H$8:$H$12,MATCH(IF(LEFT(J63,8)="Payments","Payments",IF(LEFT(J63,7)="Lending","Lending",J63)),'Conversion Model'!$G$8:$G$12,0)),0)+MIN(L63,15)*'Conversion Model'!$B$17+IF(SUMPRODUCT(--ISNUMBER(SEARCH('Scoring Model'!$D$16:$D$25,K63)))>0,'Conversion Model'!$B$18,0)+IF(SUMPRODUCT(--ISNUMBER(SEARCH('Scoring Model'!$G$16:$G$23,K63)))>0,'Conversion Model'!$B$19,0))))) -> 0.39532092 | AH63: =IF(OR(O63="Qualified",O63="Won",O63="Lost"),1,IF(O63="Unqualified",0,""))
A64: L-0063 | B64: 45965.846 | C64: Chat Widget | D64: Felix Kim | E64: mei443@webmail.example | F64: Company | G64: Boostquill Media | H64: https://boostquillmedia.example | I64: Nigeria | J64: Other | K64: test | L64: 1 | N64: Unassigned | O64: Spam | Q64: =IF(F64="Disposable",1,0) -> 0 | R64: =IF(SUMPRODUCT(--ISNUMBER(SEARCH('Spam Rules'!$A$22:$A$35,K64)))>0,1,0) -> 0 | S64: =IF(AND(F64="Free",G64=""),1,0) -> 0 | T64: =IF(LEN(TRIM(K64))<15,1,0) -> 1 | U64: =IF(COUNTIF($E$2:$E$801,E64)>1,1,0) -> 1 | V64: =Q64*'Spam Rules'!$H$6+R64*'Spam Rules'!$H$7+S64*'Spam Rules'!$H$8+T64*'Spam Rules'!$H$9+U64*'Spam Rules'!$H$10 -> 1 | W64: =IF(V64>='Spam Rules'!$B$3,"Likely Spam","Genuine") -> Likely Spam | X64: =IFERROR(INDEX('Scoring Model'!$B$5:$B$11,MATCH(C64,'Scoring Model'!$A$5:$A$11,0)),0) -> 0 | Y64: =IFERROR(INDEX('Scoring Model'!$E$5:$E$7,MATCH(F64,'Scoring Model'!$D$5:$D$7,0)),0) -> 20 | Z64: =IFERROR(INDEX('Scoring Model'!$H$5:$H$13,MATCH(J64,'Scoring Model'!$G$5:$G$13,0)),0) -> 0 | AA64: =IF(L64>='Scoring Model'!$B$14,'Scoring Model'!$B$15,IF(L64>='Scoring Model'!$B$16,'Scoring Model'!$B$17,0)) -> 0 | AB64: =IF(SUMPRODUCT(--ISNUMBER(SEARCH('Scoring Model'!$D$16:$D$25,K64)))>0,'Scoring Model'!$B$18,0) -> 0 | AC64: =IF(SUMPRODUCT(--ISNUMBER(SEARCH('Scoring Model'!$G$16:$G$23,K64)))>0,'Scoring Model'!$B$19,0) -> 0 | AD64: =IF(W64="Likely Spam","",SUM(X64:AC64)) | AE64: =IF(W64="Likely Spam","Spam",IF(AD64>='Scoring Model'!$B$21,"Hot",IF(AD64>='Scoring Model'!$B$22,"Warm","Nurture"))) -> Spam | AF64: =IF(W64="Likely Spam","Flagged by spam rules",TRIM(IF(X64>=20,"Strong source. ","")&IF(Y64>0,"Company email. ","")&IF(Z64>=15,"High-value product. ","")&IF(AA64>='Scoring Model'!$B$15,"High engagement. ","")&IF(AB64>0,"Buying intent in message. ","")&IF(AC64<0,"Negative intent in message. ",""))) -> Flagged by spam rules | AG64: =IF(W64="Likely Spam","",1/(1+EXP(-('Conversion Model'!$B$5+IFERROR(INDEX('Conversion Model'!$B$8:$B$14,MATCH(C64,'Conversion Model'!$A$8:$A$14,0)),0)+IFERROR(INDEX('Conversion Model'!$E$8:$E$9,MATCH(F64,'Conversion Model'!$D$8:$D$9,0)),0)+IFERROR(INDEX('Conversion Model'!$H$8:$H$12,MATCH(IF(LEFT(J64,8)="Payments","Payments",IF(LEFT(J64,7)="Lending","Lending",J64)),'Conversion Model'!$G$8:$G$12,0)),0)+MIN(L64,15)*'Conversion Model'!$B$17+IF(SUMPRODUCT(--ISNUMBER(SEARCH('Scoring Model'!$D$16:$D$25,K64)))>0,'Conversion Model'!$B$18,0)+IF(SUMPRODUCT(--ISNUMBER(SEARCH('Scoring Model'!$G$16:$G$23,K64)))>0,'Conversion Model'!$B$19,0))))) | AH64: =IF(OR(O64="Qualified",O64="Won",O64="Lost"),1,IF(O64="Unqualified",0,""))
A65: L-0064 | B65: 45966.301 | C65: Partner Referral | D65: Lina Mehta | E65: lina.mehta@juniperholtsystems.example | F65: Company | G65: Juniperholt Systems | H65: https://juniperholtsystems.example | I65: South Korea | J65: KYC Verification | K65: Interested in learning about fintech, where do I start? | L65: 3 | M65: 25.2 | N65: Neha | Q65: =IF(F65="Disposable",1,0) -> 0 | R65: =IF(SUMPRODUCT(--ISNUMBER(SEARCH('Spam Rules'!$A$22:$A$35,K65)))>0,1,0) -> 0 | S65: =IF(AND(F65="Free",G65=""),1,0) -> 0 | T65: =IF(LEN(TRIM(K65))<15,1,0) -> 0 | U65: =IF(COUNTIF($E$2:$E$801,E65)>1,1,0) -> 0 | V65: =Q65*'Spam Rules'!$H$6+R65*'Spam Rules'!$H$7+S65*'Spam Rules'!$H$8+T65*'Spam Rules'!$H$9+U65*'Spam Rules'!$H$10 -> 0 | W65: =IF(V65>='Spam Rules'!$B$3,"Likely Spam","Genuine") -> Genuine | X65: =IFERROR(INDEX('Scoring Model'!$B$5:$B$11,MATCH(C65,'Scoring Model'!$A$5:$A$11,0)),0) -> 30 | Y65: =IFERROR(INDEX('Scoring Model'!$E$5:$E$7,MATCH(F65,'Scoring Model'!$D$5:$D$7,0)),0) -> 20 | Z65: =IFERROR(INDEX('Scoring Model'!$H$5:$H$13,MATCH(J65,'Scoring Model'!$G$5:$G$13,0)),0) -> 5 | AA65: =IF(L65>='Scoring Model'!$B$14,'Scoring Model'!$B$15,IF(L65>='Scoring Model'!$B$16,'Scoring Model'!$B$17,0)) -> 0 | AB65: =IF(SUMPRODUCT(--ISNUMBER(SEARCH('Scoring Model'!$D$16:$D$25,K65)))>0,'Scoring Model'!$B$18,0) -> 0 | AC65: =IF(SUMPRODUCT(--ISNUMBER(SEARCH('Scoring Model'!$G$16:$G$23,K65)))>0,'Scoring Model'!$B$19,0) -> -30 | AD65: =IF(W65="Likely Spam","",SUM(X65:AC65)) -> 25 | AE65: =IF(W65="Likely Spam","Spam",IF(AD65>='Scoring Model'!$B$21,"Hot",IF(AD65>='Scoring Model'!$B$22,"Warm","Nurture"))) -> Nurture | AF65: =IF(W65="Likely Spam","Flagged by spam rules",TRIM(IF(X65>=20,"Strong source. ","")&IF(Y65>0,"Company email. ","")&IF(Z65>=15,"High-value product. ","")&IF(AA65>='Scoring Model'!$B$15,"High engagement. ","")&IF(AB65>0,"Buying intent in message. ","")&IF(AC65<0,"Negative intent in message. ",""))) -> Strong source. Company email. Negative intent in message. | AG65: =IF(W65="Likely Spam","",1/(1+EXP(-('Conversion Model'!$B$5+IFERROR(INDEX('Conversion Model'!$B$8:$B$14,MATCH(C65,'Conversion Model'!$A$8:$A$14,0)),0)+IFERROR(INDEX('Conversion Model'!$E$8:$E$9,MATCH(F65,'Conversion Model'!$D$8:$D$9,0)),0)+IFERROR(INDEX('Conversion Model'!$H$8:$H$12,MATCH(IF(LEFT(J65,8)="Payments","Payments",IF(LEFT(J65,7)="Lending","Lending",J65)),'Conversion Model'!$G$8:$G$12,0)),0)+MIN(L65,15)*'Conversion Model'!$B$17+IF(SUMPRODUCT(--ISNUMBER(SEARCH('Scoring Model'!$D$16:$D$25,K65)))>0,'Conversion Model'!$B$18,0)+IF(SUMPRODUCT(--ISNUMBER(SEARCH('Scoring Model'!$G$16:$G$23,K65)))>0,'Conversion Model'!$B$19,0))))) -> 0.028804393 | AH65: =IF(OR(O65="Qualified",O65="Won",O65="Lost"),1,IF(O65="Unqualified",0,""))
A66: L-0065 | B66: 45966.827 | C66: LinkedIn ABM | D66: Noah Mehta | E66: noah.mehta@yarrowtuncommerce.example | F66: Company | G66: Yarrowtun Commerce | H66: https://yarrowtuncommerce.example | I66: Canada | J66: Lending - Loan Origination | K66: Need a banking data API with SLA for our budgeting app, around 47M calls per day. | L66: 11 | M66: 28.5 | N66: Unassigned | O66: Lost | Q66: =IF(F66="Disposable",1,0) -> 0 | R66: =IF(SUMPRODUCT(--ISNUMBER(SEARCH('Spam Rules'!$A$22:$A$35,K66)))>0,1,0) -> 0 | S66: =IF(AND(F66="Free",G66=""),1,0) -> 0 | T66: =IF(LEN(TRIM(K66))<15,1,0) -> 0 | U66: =IF(COUNTIF($E$2:$E$801,E66)>1,1,0) -> 0 | V66: =Q66*'Spam Rules'!$H$6+R66*'Spam Rules'!$H$7+S66*'Spam Rules'!$H$8+T66*'Spam Rules'!$H$9+U66*'Spam Rules'!$H$10 -> 0 | W66: =IF(V66>='Spam Rules'!$B$3,"Likely Spam","Genuine") -> Genuine | X66: =IFERROR(INDEX('Scoring Model'!$B$5:$B$11,MATCH(C66,'Scoring Model'!$A$5:$A$11,0)),0) -> 20 | Y66: =IFERROR(INDEX('Scoring Model'!$E$5:$E$7,MATCH(F66,'Scoring Model'!$D$5:$D$7,0)),0) -> 20 | Z66: =IFERROR(INDEX('Scoring Model'!$H$5:$H$13,MATCH(J66,'Scoring Model'!$G$5:$G$13,0)),0) -> 15 | AA66: =IF(L66>='Scoring Model'!$B$14,'Scoring Model'!$B$15,IF(L66>='Scoring Model'!$B$16,'Scoring Model'!$B$17,0)) -> 15 | AB66: =IF(SUMPRODUCT(--ISNUMBER(SEARCH('Scoring Model'!$D$16:$D$25,K66)))>0,'Scoring Model'!$B$18,0) -> 15 | AC66: =IF(SUMPRODUCT(--ISNUMBER(SEARCH('Scoring Model'!$G$16:$G$23,K66)))>0,'Scoring Model'!$B$19,0) -> 0 | AD66: =IF(W66="Likely Spam","",SUM(X66:AC66)) -> 85 | AE66: =IF(W66="Likely Spam","Spam",IF(AD66>='Scoring Model'!$B$21,"Hot",IF(AD66>='Scoring Model'!$B$22,"Warm","Nurture"))) -> Hot | AF66: =IF(W66="Likely Spam","Flagged by spam rules",TRIM(IF(X66>=20,"Strong source. ","")&IF(Y66>0,"Company email. ","")&IF(Z66>=15,"High-value product. ","")&IF(AA66>='Scoring Model'!$B$15,"High engagement. ","")&IF(AB66>0,"Buying intent in message. ","")&IF(AC66<0,"Negative intent in message. ",""))) -> Strong source. Company email. High-value product. High engagement. Buying intent in message. | AG66: =IF(W66="Likely Spam","",1/(1+EXP(-('Conversion Model'!$B$5+IFERROR(INDEX('Conversion Model'!$B$8:$B$14,MATCH(C66,'Conversion Model'!$A$8:$A$14,0)),0)+IFERROR(INDEX('Conversion Model'!$E$8:$E$9,MATCH(F66,'Conversion Model'!$D$8:$D$9,0)),0)+IFERROR(INDEX('Conversion Model'!$H$8:$H$12,MATCH(IF(LEFT(J66,8)="Payments","Payments",IF(LEFT(J66,7)="Lending","Lending",J66)),'Conversion Model'!$G$8:$G$12,0)),0)+MIN(L66,15)*'Conversion Model'!$B$17+IF(SUMPRODUCT(--ISNUMBER(SEARCH('Scoring Model'!$D$16:$D$25,K66)))>0,'Conversion Model'!$B$18,0)+IF(SUMPRODUCT(--ISNUMBER(SEARCH('Scoring Model'!$G$16:$G$23,K66)))>0,'Conversion Model'!$B$19,0))))) -> 0.99939399 | AH66: =IF(OR(O66="Qualified",O66="Won",O66="Lost"),1,IF(O66="Unqualified",0,"")) -> 1
A67: L-0066 | B67: 45967.261 | C67: LinkedIn ABM | D67: Noah Rossi | E67: noah.rossi@ferrowindwallet.example | F67: Company | G67: Ferrowind Wallet | H67: https://ferrowindwallet.example | I67: Canada | J67: Banking Data API | K67: Are you hiring fintech developers? Please share openings. | L67: 3 | M67: 21.8 | N67: Unassigned | O67: Unqualified | Q67: =IF(F67="Disposable",1,0) -> 0 | R67: =IF(SUMPRODUCT(--ISNUMBER(SEARCH('Spam Rules'!$A$22:$A$35,K67)))>0,1,0) -> 0 | S67: =IF(AND(F67="Free",G67=""),1,0) -> 0 | T67: =IF(LEN(TRIM(K67))<15,1,0) -> 0 | U67: =IF(COUNTIF($E$2:$E$801,E67)>1,1,0) -> 0 | V67: =Q67*'Spam Rules'!$H$6+R67*'Spam Rules'!$H$7+S67*'Spam Rules'!$H$8+T67*'Spam Rules'!$H$9+U67*'Spam Rules'!$H$10 -> 0 | W67: =IF(V67>='Spam Rules'!$B$3,"Likely Spam","Genuine") -> Genuine | X67: =IFERROR(INDEX('Scoring Model'!$B$5:$B$11,MATCH(C67,'Scoring Model'!$A$5:$A$11,0)),0) -> 20 | Y67: =IFERROR(INDEX('Scoring Model'!$E$5:$E$7,MATCH(F67,'Scoring Model'!$D$5:$D$7,0)),0) -> 20 | Z67: =IFERROR(INDEX('Scoring Model'!$H$5:$H$13,MATCH(J67,'Scoring Model'!$G$5:$G$13,0)),0) -> 5 | AA67: =IF(L67>='Scoring Model'!$B$14,'Scoring Model'!$B$15,IF(L67>='Scoring Model'!$B$16,'Scoring Model'!$B$17,0)) -> 0 | AB67: =IF(SUMPRODUCT(--ISNUMBER(SEARCH('Scoring Model'!$D$16:$D$25,K67)))>0,'Scoring Model'!$B$18,0) -> 0 | AC67: =IF(SUMPRODUCT(--ISNUMBER(SEARCH('Scoring Model'!$G$16:$G$23,K67)))>0,'Scoring Model'!$B$19,0) -> -30 | AD67: =IF(W67="Likely Spam","",SUM(X67:AC67)) -> 15 | AE67: =IF(W67="Likely Spam","Spam",IF(AD67>='Scoring Model'!$B$21,"Hot",IF(AD67>='Scoring Model'!$B$22,"Warm","Nurture"))) -> Nurture | AF67: =IF(W67="Likely Spam","Flagged by spam rules",TRIM(IF(X67>=20,"Strong source. ","")&IF(Y67>0,"Company email. ","")&IF(Z67>=15,"High-value product. ","")&IF(AA67>='Scoring Model'!$B$15,"High engagement. ","")&IF(AB67>0,"Buying intent in message. ","")&IF(AC67<0,"Negative intent in message. ",""))) -> Strong source. Company email. Negative intent in message. | AG67: =IF(W67="Likely Spam","",1/(1+EXP(-('Conversion Model'!$B$5+IFERROR(INDEX('Conversion Model'!$B$8:$B$14,MATCH(C67,'Conversion Model'!$A$8:$A$14,0)),0)+IFERROR(INDEX('Conversion Model'!$E$8:$E$9,MATCH(F67,'Conversion Model'!$D$8:$D$9,0)),0)+IFERROR(INDEX('Conversion Model'!$H$8:$H$12,MATCH(IF(LEFT(J67,8)="Payments","Payments",IF(LEFT(J67,7)="Lending","Lending",J67)),'Conversion Model'!$G$8:$G$12,0)),0)+MIN(L67,15)*'Conversion Model'!$B$17+IF(SUMPRODUCT(--ISNUMBER(SEARCH('Scoring Model'!$D$16:$D$25,K67)))>0,'Conversion Model'!$B$18,0)+IF(SUMPRODUCT(--ISNUMBER(SEARCH('Scoring Model'!$G$16:$G$23,K67)))>0,'Conversion Model'!$B$19,0))))) -> 0.035950488 | AH67: =IF(OR(O67="Qualified",O67="Won",O67="Lost"),1,IF(O67="Unqualified",0,"")) -> 0
A68: L-0067 | B68: 45967.282 | C68: Chat Widget | D68: Felix Khan | E68: felix.khan@freemail.example | F68: Free | I68: Singapore | J68: Banking Data API | K68: Are you hiring fintech developers? Please share openings. | L68: 3 | M68: 22.2 | N68: Unassigned | O68: Unqualified | Q68: =IF(F68="Disposable",1,0) -> 0 | R68: =IF(SUMPRODUCT(--ISNUMBER(SEARCH('Spam Rules'!$A$22:$A$35,K68)))>0,1,0) -> 0 | S68: =IF(AND(F68="Free",G68=""),1,0) -> 1 | T68: =IF(LEN(TRIM(K68))<15,1,0) -> 0 | U68: =IF(COUNTIF($E$2:$E$801,E68)>1,1,0) -> 0 | V68: =Q68*'Spam Rules'!$H$6+R68*'Spam Rules'!$H$7+S68*'Spam Rules'!$H$8+T68*'Spam Rules'!$H$9+U68*'Spam Rules'!$H$10 -> 0 | W68: =IF(V68>='Spam Rules'!$B$3,"Likely Spam","Genuine") -> Genuine | X68: =IFERROR(INDEX('Scoring Model'!$B$5:$B$11,MATCH(C68,'Scoring Model'!$A$5:$A$11,0)),0) -> 0 | Y68: =IFERROR(INDEX('Scoring Model'!$E$5:$E$7,MATCH(F68,'Scoring Model'!$D$5:$D$7,0)),0) -> 0 | Z68: =IFERROR(INDEX('Scoring Model'!$H$5:$H$13,MATCH(J68,'Scoring Model'!$G$5:$G$13,0)),0) -> 5 | AA68: =IF(L68>='Scoring Model'!$B$14,'Scoring Model'!$B$15,IF(L68>='Scoring Model'!$B$16,'Scoring Model'!$B$17,0)) -> 0 | AB68: =IF(SUMPRODUCT(--ISNUMBER(SEARCH('Scoring Model'!$D$16:$D$25,K68)))>0,'Scoring Model'!$B$18,0) -> 0 | AC68: =IF(SUMPRODUCT(--ISNUMBER(SEARCH('Scoring Model'!$G$16:$G$23,K68)))>0,'Scoring Model'!$B$19,0) -> -30 | AD68: =IF(W68="Likely Spam","",SUM(X68:AC68)) -> -25 | AE68: =IF(W68="Likely Spam","Spam",IF(AD68>='Scoring Model'!$B$21,"Hot",IF(AD68>='Scoring Model'!$B$22,"Warm","Nurture"))) -> Nurture | AF68: =IF(W68="Likely Spam","Flagged by spam rules",TRIM(IF(X68>=20,"Strong source. ","")&IF(Y68>0,"Company email. ","")&IF(Z68>=15,"High-value product. ","")&IF(AA68>='Scoring Model'!$B$15,"High engagement. ","")&IF(AB68>0,"Buying intent in message. ","")&IF(AC68<0,"Negative intent in message. ",""))) -> Negative intent in message. | AG68: =IF(W68="Likely Spam","",1/(1+EXP(-('Conversion Model'!$B$5+IFERROR(INDEX('Conversion Model'!$B$8:$B$14,MATCH(C68,'Conversion Model'!$A$8:$A$14,0)),0)+IFERROR(INDEX('Conversion Model'!$E$8:$E$9,MATCH(F68,'Conversion Model'!$D$8:$D$9,0)),0)+IFERROR(INDEX('Conversion Model'!$H$8:$H$12,MATCH(IF(LEFT(J68,8)="Payments","Payments",IF(LEFT(J68,7)="Lending","Lending",J68)),'Conversion Model'!$G$8:$G$12,0)),0)+MIN(L68,15)*'Conversion Model'!$B$17+IF(SUMPRODUCT(--ISNUMBER(SEARCH('Scoring Model'!$D$16:$D$25,K68)))>0,'Conversion Model'!$B$18,0)+IF(SUMPRODUCT(--ISNUMBER(SEARCH('Scoring Model'!$G$16:$G$23,K68)))>0,'Conversion Model'!$B$19,0))))) -> 0.0046929028 | AH68: =IF(OR(O68="Qualified",O68="Won",O68="Lost"),1,IF(O68="Unqualified",0,"")) -> 0
A69: L-0068 | B69: 45968.358 | C69: Website Contact Form | D69: Tariq Brown | E69: tariq676@inboxly.example | F69: Free | I69: UAE | J69: KYC Verification | K69: Get your app listing on top review sites in 48 hours, guaranteed. Contact our listing agent. | L69: 2 | M69: 32 | N69: Rahul | Q69: =IF(F69="Disposable",1,0) -> 0 | R69: =IF(SUMPRODUCT(--ISNUMBER(SEARCH('Spam Rules'!$A$22:$A$35,K69)))>0,1,0) -> 1 | S69: =IF(AND(F69="Free",G69=""),1,0) -> 1 | T69: =IF(LEN(TRIM(K69))<15,1,0) -> 0 | U69: =IF(COUNTIF($E$2:$E$801,E69)>1,1,0) -> 0 | V69: =Q69*'Spam Rules'!$H$6+R69*'Spam Rules'!$H$7+S69*'Spam Rules'!$H$8+T69*'Spam Rules'!$H$9+U69*'Spam Rules'!$H$10 -> 1 | W69: =IF(V69>='Spam Rules'!$B$3,"Likely Spam","Genuine") -> Likely Spam | X69: =IFERROR(INDEX('Scoring Model'!$B$5:$B$11,MATCH(C69,'Scoring Model'!$A$5:$A$11,0)),0) -> 10 | Y69: =IFERROR(INDEX('Scoring Model'!$E$5:$E$7,MATCH(F69,'Scoring Model'!$D$5:$D$7,0)),0) -> 0 | Z69: =IFERROR(INDEX('Scoring Model'!$H$5:$H$13,MATCH(J69,'Scoring Model'!$G$5:$G$13,0)),0) -> 5 | AA69: =IF(L69>='Scoring Model'!$B$14,'Scoring Model'!$B$15,IF(L69>='Scoring Model'!$B$16,'Scoring Model'!$B$17,0)) -> 0 | AB69: =IF(SUMPRODUCT(--ISNUMBER(SEARCH('Scoring Model'!$D$16:$D$25,K69)))>0,'Scoring Model'!$B$18,0) -> 0 | AC69: =IF(SUMPRODUCT(--ISNUMBER(SEARCH('Scoring Model'!$G$16:$G$23,K69)))>0,'Scoring Model'!$B$19,0) -> 0 | AD69: =IF(W69="Likely Spam","",SUM(X69:AC69)) | AE69: =IF(W69="Likely Spam","Spam",IF(AD69>='Scoring Model'!$B$21,"Hot",IF(AD69>='Scoring Model'!$B$22,"Warm","Nurture"))) -> Spam | AF69: =IF(W69="Likely Spam","Flagged by spam rules",TRIM(IF(X69>=20,"Strong source. ","")&IF(Y69>0,"Company email. ","")&IF(Z69>=15,"High-value product. ","")&IF(AA69>='Scoring Model'!$B$15,"High engagement. ","")&IF(AB69>0,"Buying intent in message. ","")&IF(AC69<0,"Negative intent in message. ",""))) -> Flagged by spam rules | AG69: =IF(W69="Likely Spam","",1/(1+EXP(-('Conversion Model'!$B$5+IFERROR(INDEX('Conversion Model'!$B$8:$B$14,MATCH(C69,'Conversion Model'!$A$8:$A$14,0)),0)+IFERROR(INDEX('Conversion Model'!$E$8:$E$9,MATCH(F69,'Conversion Model'!$D$8:$D$9,0)),0)+IFERROR(INDEX('Conversion Model'!$H$8:$H$12,MATCH(IF(LEFT(J69,8)="Payments","Payments",IF(LEFT(J69,7)="Lending","Lending",J69)),'Conversion Model'!$G$8:$G$12,0)),0)+MIN(L69,15)*'Conversion Model'!$B$17+IF(SUMPRODUCT(--ISNUMBER(SEARCH('Scoring Model'!$D$16:$D$25,K69)))>0,'Conversion Model'!$B$18,0)+IF(SUMPRODUCT(--ISNUMBER(SEARCH('Scoring Model'!$G$16:$G$23,K69)))>0,'Conversion Model'!$B$19,0))))) | AH69: =IF(OR(O69="Qualified",O69="Won",O69="Lost"),1,IF(O69="Unqualified",0,""))
A70: L-0069 | B70: 45968.358 | C70: Website Contact Form | D70: Mateo Rossi | E70: mateo602@postbox.example | F70: Free | I70: USA | J70: Other | K70: Partnership proposal for fintech influencer marketing campaign, 500k reach. | L70: 1 | M70: 192.2 | N70: Rahul | O70: Spam | Q70: =IF(F70="Disposable",1,0) -> 0 | R70: =IF(SUMPRODUCT(--ISNUMBER(SEARCH('Spam Rules'!$A$22:$A$35,K70)))>0,1,0) -> 1 | S70: =IF(AND(F70="Free",G70=""),1,0) -> 1 | T70: =IF(LEN(TRIM(K70))<15,1,0) -> 0 | U70: =IF(COUNTIF($E$2:$E$801,E70)>1,1,0) -> 0 | V70: =Q70*'Spam Rules'!$H$6+R70*'Spam Rules'!$H$7+S70*'Spam Rules'!$H$8+T70*'Spam Rules'!$H$9+U70*'Spam Rules'!$H$10 -> 1 | W70: =IF(V70>='Spam Rules'!$B$3,"Likely Spam","Genuine") -> Likely Spam | X70: =IFERROR(INDEX('Scoring Model'!$B$5:$B$11,MATCH(C70,'Scoring Model'!$A$5:$A$11,0)),0) -> 10 | Y70: =IFERROR(INDEX('Scoring Model'!$E$5:$E$7,MATCH(F70,'Scoring Model'!$D$5:$D$7,0)),0) -> 0 | Z70: =IFERROR(INDEX('Scoring Model'!$H$5:$H$13,MATCH(J70,'Scoring Model'!$G$5:$G$13,0)),0) -> 0 | AA70: =IF(L70>='Scoring Model'!$B$14,'Scoring Model'!$B$15,IF(L70>='Scoring Model'!$B$16,'Scoring Model'!$B$17,0)) -> 0 | AB70: =IF(SUMPRODUCT(--ISNUMBER(SEARCH('Scoring Model'!$D$16:$D$25,K70)))>0,'Scoring Model'!$B$18,0) -> 0 | AC70: =IF(SUMPRODUCT(--ISNUMBER(SEARCH('Scoring Model'!$G$16:$G$23,K70)))>0,'Scoring Model'!$B$19,0) -> 0 | AD70: =IF(W70="Likely Spam","",SUM(X70:AC70)) | AE70: =IF(W70="Likely Spam","Spam",IF(AD70>='Scoring Model'!$B$21,"Hot",IF(AD70>='Scoring Model'!$B$22,"Warm","Nurture"))) -> Spam | AF70: =IF(W70="Likely Spam","Flagged by spam rules",TRIM(IF(X70>=20,"Strong source. ","")&IF(Y70>0,"Company email. ","")&IF(Z70>=15,"High-value product. ","")&IF(AA70>='Scoring Model'!$B$15,"High engagement. ","")&IF(AB70>0,"Buying intent in message. ","")&IF(AC70<0,"Negative intent in message. ",""))) -> Flagged by spam rules | AG70: =IF(W70="Likely Spam","",1/(1+EXP(-('Conversion Model'!$B$5+IFERROR(INDEX('Conversion Model'!$B$8:$B$14,MATCH(C70,'Conversion Model'!$A$8:$A$14,0)),0)+IFERROR(INDEX('Conversion Model'!$E$8:$E$9,MATCH(F70,'Conversion Model'!$D$8:$D$9,0)),0)+IFERROR(INDEX('Conversion Model'!$H$8:$H$12,MATCH(IF(LEFT(J70,8)="Payments","Payments",IF(LEFT(J70,7)="Lending","Lending",J70)),'Conversion Model'!$G$8:$G$12,0)),0)+MIN(L70,15)*'Conversion Model'!$B$17+IF(SUMPRODUCT(--ISNUMBER(SEARCH('Scoring Model'!$D$16:$D$25,K70)))>0,'Conversion Model'!$B$18,0)+IF(SUMPRODUCT(--ISNUMBER(SEARCH('Scoring Model'!$G$16:$G$23,K70)))>0,'Conversion Model'!$B$19,0))))) | AH70: =IF(OR(O70="Qualified",O70="Won",O70="Lost"),1,IF(O70="Unqualified",0,""))
A71: L-0070 | B71: 45968.432 | C71: Chat Widget | D71: Arjun Tanaka | E71: arjun.tanaka@marrowgatewallet.example | F71: Company | G71: Marrowgate Wallet | H71: https://marrowgatewallet.example | I71: UK | J71: KYC Verification | K71: Interested in learning about fintech, where do I start? | L71: 3 | M71: 130.4 | N71: Neha | Q71: =IF(F71="Disposable",1,0) -> 0 | R71: =IF(SUMPRODUCT(--ISNUMBER(SEARCH('Spam Rules'!$A$22:$A$35,K71)))>0,1,0) -> 0 | S71: =IF(AND(F71="Free",G71=""),1,0) -> 0 | T71: =IF(LEN(TRIM(K71))<15,1,0) -> 0 | U71: =IF(COUNTIF($E$2:$E$801,E71)>1,1,0) -> 0 | V71: =Q71*'Spam Rules'!$H$6+R71*'Spam Rules'!$H$7+S71*'Spam Rules'!$H$8+T71*'Spam Rules'!$H$9+U71*'Spam Rules'!$H$10 -> 0 | W71: =IF(V71>='Spam Rules'!$B$3,"Likely Spam","Genuine") -> Genuine | X71: =IFERROR(INDEX('Scoring Model'!$B$5:$B$11,MATCH(C71,'Scoring Model'!$A$5:$A$11,0)),0) -> 0 | Y71: =IFERROR(INDEX('Scoring Model'!$E$5:$E$7,MATCH(F71,'Scoring Model'!$D$5:$D$7,0)),0) -> 20 | Z71: =IFERROR(INDEX('Scoring Model'!$H$5:$H$13,MATCH(J71,'Scoring Model'!$G$5:$G$13,0)),0) -> 5 | AA71: =IF(L71>='Scoring Model'!$B$14,'Scoring Model'!$B$15,IF(L71>='Scoring Model'!$B$16,'Scoring Model'!$B$17,0)) -> 0 | AB71: =IF(SUMPRODUCT(--ISNUMBER(SEARCH('Scoring Model'!$D$16:$D$25,K71)))>0,'Scoring Model'!$B$18,0) -> 0 | AC71: =IF(SUMPRODUCT(--ISNUMBER(SEARCH('Scoring Model'!$G$16:$G$23,K71)))>0,'Scoring Model'!$B$19,0) -> -30 | AD71: =IF(W71="Likely Spam","",SUM(X71:AC71)) -> -5 | AE71: =IF(W71="Likely Spam","Spam",IF(AD71>='Scoring Model'!$B$21,"Hot",IF(AD71>='Scoring Model'!$B$22,"Warm","Nurture"))) -> Nurture | AF71: =IF(W71="Likely Spam","Flagged by spam rules",TRIM(IF(X71>=20,"Strong source. ","")&IF(Y71>0,"Company email. ","")&IF(Z71>=15,"High-value product. ","")&IF(AA71>='Scoring Model'!$B$15,"High engagement. ","")&IF(AB71>0,"Buying intent in message. ","")&IF(AC71<0,"Negative intent in message. ",""))) -> Company email. Negative intent in message. | AG71: =IF(W71="Likely Spam","",1/(1+EXP(-('Conversion Model'!$B$5+IFERROR(INDEX('Conversion Model'!$B$8:$B$14,MATCH(C71,'Conversion Model'!$A$8:$A$14,0)),0)+IFERROR(INDEX('Conversion Model'!$E$8:$E$9,MATCH(F71,'Conversion Model'!$D$8:$D$9,0)),0)+IFERROR(INDEX('Conversion Model'!$H$8:$H$12,MATCH(IF(LEFT(J71,8)="Payments","Payments",IF(LEFT(J71,7)="Lending","Lending",J71)),'Conversion Model'!$G$8:$G$12,0)),0)+MIN(L71,15)*'Conversion Model'!$B$17+IF(SUMPRODUCT(--ISNUMBER(SEARCH('Scoring Model'!$D$16:$D$25,K71)))>0,'Conversion Model'!$B$18,0)+IF(SUMPRODUCT(--ISNUMBER(SEARCH('Scoring Model'!$G$16:$G$23,K71)))>0,'Conversion Model'!$B$19,0))))) -> 0.0065286827 | AH71: =IF(OR(O71="Qualified",O71="Won",O71="Lost"),1,IF(O71="Unqualified",0,""))
A72: L-0071 | B72: 45968.536 | C72: Pricing Page Form | D72: Nadia Patel | E72: nadia.patel@wyndlefosscapital.example | F72: Company | G72: Wyndlefoss Capital | H72: https://wyndlefosscapital.example | I72: USA | J72: Payments - Card Issuing | K72: Need a banking data API with SLA for our budgeting app, around 80M calls per day. | L72: 9 | M72: 10.2 | N72: Unassigned | O72: Qualified | Q72: =IF(F72="Disposable",1,0) -> 0 | R72: =IF(SUMPRODUCT(--ISNUMBER(SEARCH('Spam Rules'!$A$22:$A$35,K72)))>0,1,0) -> 0 | S72: =IF(AND(F72="Free",G72=""),1,0) -> 0 | T72: =IF(LEN(TRIM(K72))<15,1,0) -> 0 | U72: =IF(COUNTIF($E$2:$E$801,E72)>1,1,0) -> 0 | V72: =Q72*'Spam Rules'!$H$6+R72*'Spam Rules'!$H$7+S72*'Spam Rules'!$H$8+T72*'Spam Rules'!$H$9+U72*'Spam Rules'!$H$10 -> 0 | W72: =IF(V72>='Spam Rules'!$B$3,"Likely Spam","Genuine") -> Genuine | X72: =IFERROR(INDEX('Scoring Model'!$B$5:$B$11,MATCH(C72,'Scoring Model'!$A$5:$A$11,0)),0) -> 25 | Y72: =IFERROR(INDEX('Scoring Model'!$E$5:$E$7,MATCH(F72,'Scoring Model'!$D$5:$D$7,0)),0) -> 20 | Z72: =IFERROR(INDEX('Scoring Model'!$H$5:$H$13,MATCH(J72,'Scoring Model'!$G$5:$G$13,0)),0) -> 15 | AA72: =IF(L72>='Scoring Model'!$B$14,'Scoring Model'!$B$15,IF(L72>='Scoring Model'!$B$16,'Scoring Model'!$B$17,0)) -> 15 | AB72: =IF(SUMPRODUCT(--ISNUMBER(SEARCH('Scoring Model'!$D$16:$D$25,K72)))>0,'Scoring Model'!$B$18,0) -> 15 | AC72: =IF(SUMPRODUCT(--ISNUMBER(SEARCH('Scoring Model'!$G$16:$G$23,K72)))>0,'Scoring Model'!$B$19,0) -> 0 | AD72: =IF(W72="Likely Spam","",SUM(X72:AC72)) -> 90 | AE72: =IF(W72="Likely Spam","Spam",IF(AD72>='Scoring Model'!$B$21,"Hot",IF(AD72>='Scoring Model'!$B$22,"Warm","Nurture"))) -> Hot | AF72: =IF(W72="Likely Spam","Flagged by spam rules",TRIM(IF(X72>=20,"Strong source. ","")&IF(Y72>0,"Company email. ","")&IF(Z72>=15,"High-value product. ","")&IF(AA72>='Scoring Model'!$B$15,"High engagement. ","")&IF(AB72>0,"Buying intent in message. ","")&IF(AC72<0,"Negative intent in message. ",""))) -> Strong source. Company email. High-value product. High engagement. Buying intent in message. | AG72: =IF(W72="Likely Spam","",1/(1+EXP(-('Conversion Model'!$B$5+IFERROR(INDEX('Conversion Model'!$B$8:$B$14,MATCH(C72,'Conversion Model'!$A$8:$A$14,0)),0)+IFERROR(INDEX('Conversion Model'!$E$8:$E$9,MATCH(F72,'Conversion Model'!$D$8:$D$9,0)),0)+IFERROR(INDEX('Conversion Model'!$H$8:$H$12,MATCH(IF(LEFT(J72,8)="Payments","Payments",IF(LEFT(J72,7)="Lending","Lending",J72)),'Conversion Model'!$G$8:$G$12,0)),0)+MIN(L72,15)*'Conversion Model'!$B$17+IF(SUMPRODUCT(--ISNUMBER(SEARCH('Scoring Model'!$D$16:$D$25,K72)))>0,'Conversion Model'!$B$18,0)+IF(SUMPRODUCT(--ISNUMBER(SEARCH('Scoring Model'!$G$16:$G$23,K72)))>0,'Conversion Model'!$B$19,0))))) -> 0.98912119 | AH72: =IF(OR(O72="Qualified",O72="Won",O72="Lost"),1,IF(O72="Unqualified",0,"")) -> 1
A73: L-0072 | B73: 45968.539 | C73: Chat Widget | D73: Priya Mehta | E73: priya.mehta@postbox.example | F73: Free | G73: Dunmarrow Labs | I73: Canada | J73: KYC Verification | K73: Interested in learning about fintech, where do I start? | L73: 2 | M73: 7.4 | N73: Neha | O73: Unqualified | Q73: =IF(F73="Disposable",1,0) -> 0 | R73: =IF(SUMPRODUCT(--ISNUMBER(SEARCH('Spam Rules'!$A$22:$A$35,K73)))>0,1,0) -> 0 | S73: =IF(AND(F73="Free",G73=""),1,0) -> 0 | T73: =IF(LEN(TRIM(K73))<15,1,0) -> 0 | U73: =IF(COUNTIF($E$2:$E$801,E73)>1,1,0) -> 0 | V73: =Q73*'Spam Rules'!$H$6+R73*'Spam Rules'!$H$7+S73*'Spam Rules'!$H$8+T73*'Spam Rules'!$H$9+U73*'Spam Rules'!$H$10 -> 0 | W73: =IF(V73>='Spam Rules'!$B$3,"Likely Spam","Genuine") -> Genuine | X73: =IFERROR(INDEX('Scoring Model'!$B$5:$B$11,MATCH(C73,'Scoring Model'!$A$5:$A$11,0)),0) -> 0 | Y73: =IFERROR(INDEX('Scoring Model'!$E$5:$E$7,MATCH(F73,'Scoring Model'!$D$5:$D$7,0)),0) -> 0 | Z73: =IFERROR(INDEX('Scoring Model'!$H$5:$H$13,MATCH(J73,'Scoring Model'!$G$5:$G$13,0)),0) -> 5 | AA73: =IF(L73>='Scoring Model'!$B$14,'Scoring Model'!$B$15,IF(L73>='Scoring Model'!$B$16,'Scoring Model'!$B$17,0)) -> 0 | AB73: =IF(SUMPRODUCT(--ISNUMBER(SEARCH('Scoring Model'!$D$16:$D$25,K73)))>0,'Scoring Model'!$B$18,0) -> 0 | AC73: =IF(SUMPRODUCT(--ISNUMBER(SEARCH('Scoring Model'!$G$16:$G$23,K73)))>0,'Scoring Model'!$B$19,0) -> -30 | AD73: =IF(W73="Likely Spam","",SUM(X73:AC73)) -> -25 | AE73: =IF(W73="Likely Spam","Spam",IF(AD73>='Scoring Model'!$B$21,"Hot",IF(AD73>='Scoring Model'!$B$22,"Warm","Nurture"))) -> Nurture | AF73: =IF(W73="Likely Spam","Flagged by spam rules",TRIM(IF(X73>=20,"Strong source. ","")&IF(Y73>0,"Company email. ","")&IF(Z73>=15,"High-value product. ","")&IF(AA73>='Scoring Model'!$B$15,"High engagement. ","")&IF(AB73>0,"Buying intent in message. ","")&IF(AC73<0,"Negative intent in message. ",""))) -> Negative intent in message. | AG73: =IF(W73="Likely Spam","",1/(1+EXP(-('Conversion Model'!$B$5+IFERROR(INDEX('Conversion Model'!$B$8:$B$14,MATCH(C73,'Conversion Model'!$A$8:$A$14,0)),0)+IFERROR(INDEX('Conversion Model'!$E$8:$E$9,MATCH(F73,'Conversion Model'!$D$8:$D$9,0)),0)+IFERROR(INDEX('Conversion Model'!$H$8:$H$12,MATCH(IF(LEFT(J73,8)="Payments","Payments",IF(LEFT(J73,7)="Lending","Lending",J73)),'Conversion Model'!$G$8:$G$12,0)),0)+MIN(L73,15)*'Conversion Model'!$B$17+IF(SUMPRODUCT(--ISNUMBER(SEARCH('Scoring Model'!$D$16:$D$25,K73)))>0,'Conversion Model'!$B$18,0)+IF(SUMPRODUCT(--ISNUMBER(SEARCH('Scoring Model'!$G$16:$G$23,K73)))>0,'Conversion Model'!$B$19,0))))) -> 0.0012196146 | AH73: =IF(OR(O73="Qualified",O73="Won",O73="Lost"),1,IF(O73="Unqualified",0,"")) -> 0
A74: L-0073 | B74: 45968.766 | C74: LinkedIn ABM | D74: Tariq Berg | E74: tariq.berg@letterdrop.example | F74: Free | G74: Wyndlefoss Money | I74: UK | J74: KYC Verification | K74: Evaluating card issuing providers for our loyalty app. Can we get a demo and a cost comparison? | L74: 6 | M74: 7.4 | N74: Neha | Q74: =IF(F74="Disposable",1,0) -> 0 | R74: =IF(SUMPRODUCT(--ISNUMBER(SEARCH('Spam Rules'!$A$22:$A$35,K74)))>0,1,0) -> 0 | S74: =IF(AND(F74="Free",G74=""),1,0) -> 0 | T74: =IF(LEN(TRIM(K74))<15,1,0) -> 0 | U74: =IF(COUNTIF($E$2:$E$801,E74)>1,1,0) -> 0 | V74: =Q74*'Spam Rules'!$H$6+R74*'Spam Rules'!$H$7+S74*'Spam Rules'!$H$8+T74*'Spam Rules'!$H$9+U74*'Spam Rules'!$H$10 -> 0 | W74: =IF(V74>='Spam Rules'!$B$3,"Likely Spam","Genuine") -> Genuine | X74: =IFERROR(INDEX('Scoring Model'!$B$5:$B$11,MATCH(C74,'Scoring Model'!$A$5:$A$11,0)),0) -> 20 | Y74: =IFERROR(INDEX('Scoring Model'!$E$5:$E$7,MATCH(F74,'Scoring Model'!$D$5:$D$7,0)),0) -> 0 | Z74: =IFERROR(INDEX('Scoring Model'!$H$5:$H$13,MATCH(J74,'Scoring Model'!$G$5:$G$13,0)),0) -> 5 | AA74: =IF(L74>='Scoring Model'!$B$14,'Scoring Model'!$B$15,IF(L74>='Scoring Model'!$B$16,'Scoring Model'!$B$17,0)) -> 8 | AB74: =IF(SUMPRODUCT(--ISNUMBER(SEARCH('Scoring Model'!$D$16:$D$25,K74)))>0,'Scoring Model'!$B$18,0) -> 15 | AC74: =IF(SUMPRODUCT(--ISNUMBER(SEARCH('Scoring Model'!$G$16:$G$23,K74)))>0,'Scoring Model'!$B$19,0) -> 0 | AD74: =IF(W74="Likely Spam","",SUM(X74:AC74)) -> 48 | AE74: =IF(W74="Likely Spam","Spam",IF(AD74>='Scoring Model'!$B$21,"Hot",IF(AD74>='Scoring Model'!$B$22,"Warm","Nurture"))) -> Warm | AF74: =IF(W74="Likely Spam","Flagged by spam rules",TRIM(IF(X74>=20,"Strong source. ","")&IF(Y74>0,"Company email. ","")&IF(Z74>=15,"High-value product. ","")&IF(AA74>='Scoring Model'!$B$15,"High engagement. ","")&IF(AB74>0,"Buying intent in message. ","")&IF(AC74<0,"Negative intent in message. ",""))) -> Strong source. Buying intent in message. | AG74: =IF(W74="Likely Spam","",1/(1+EXP(-('Conversion Model'!$B$5+IFERROR(INDEX('Conversion Model'!$B$8:$B$14,MATCH(C74,'Conversion Model'!$A$8:$A$14,0)),0)+IFERROR(INDEX('Conversion Model'!$E$8:$E$9,MATCH(F74,'Conversion Model'!$D$8:$D$9,0)),0)+IFERROR(INDEX('Conversion Model'!$H$8:$H$12,MATCH(IF(LEFT(J74,8)="Payments","Payments",IF(LEFT(J74,7)="Lending","Lending",J74)),'Conversion Model'!$G$8:$G$12,0)),0)+MIN(L74,15)*'Conversion Model'!$B$17+IF(SUMPRODUCT(--ISNUMBER(SEARCH('Scoring Model'!$D$16:$D$25,K74)))>0,'Conversion Model'!$B$18,0)+IF(SUMPRODUCT(--ISNUMBER(SEARCH('Scoring Model'!$G$16:$G$23,K74)))>0,'Conversion Model'!$B$19,0))))) -> 0.76781244 | AH74: =IF(OR(O74="Qualified",O74="Won",O74="Lost"),1,IF(O74="Unqualified",0,""))
